Workbook

Sheet Instrucciones
A1: FP-180 — Matriz comparativa y cálculo de resultados (TINV-05 / FP-51)
A3: Estado: Motor de cálculo terminado y validado contra el ejemplo sintético de FP-177. Las 17 herramientas de la población de FP-51/FP-179 están investigadas con evidencia real, citada e individual, en sus escenarios elegibles: 5 herramientas cloud nativas (AWS Cost Explorer, AWS Cost Optimization Hub, Azure Cost Management, Google Cloud Billing, Google Cloud FinOps Hub), 6 plataformas multicloud (Cloudability, CloudHealth, CloudZero, Vantage, Finout, nOps), 4 herramientas de Kubernetes (OpenCost, Kubecost, Cast AI, StormForge) y 2 de estimación temprana (Infracost, Cloud Custodian). Documento estructurado con asistencia de IA; queda a validación humana del equipo antes de dar por cumplidos los criterios de término de FP-180.
A5: Este libro aplica, como fórmulas reproducibles de Excel, la metodología aprobada en docs/fp-177/metodologia-comparativa-borrador.md y la matriz de indicadores de docs/fp-177/matriz-criterios-y-ponderaciones-borrador.md. No sustituye esos documentos: ante cualquier discrepancia, prevalece el texto aprobado por el equipo.
A7: Límite metodológico de esta investigación: la verificación se hizo contra documentación oficial publicada, sin acceso práctico a una cuenta real de AWS/Azure/GCP ni a las consolas de los productos comerciales. Por eso ningún indicador recibe el valor 3: la metodología exige doble evidencia (documentación primaria + estudio independiente, demostración reproducible o verificación práctica del equipo) para ese valor, y aquí solo se dispone de la primera. El equipo puede subir cualquier valor a 3 si aporta esa segunda evidencia.
A9: Dos limitaciones puntuales quedan registradas para revisión del equipo: (1) la documentación técnica oficial de IBM Docs para Cloudability devolvió error 403 en todos los intentos de acceso durante esta investigación (2026-09-16); toda su evidencia proviene de páginas comerciales de apptio.com, por lo que, según la propia metodología, ningún indicador de Cloudability supera el valor 1 (ver columna Notas de sus filas). (2) Cloud Custodian está incluido en la población de FP-179 dentro de "herramientas de estimación temprana" (escenario E4), pero la evidencia oficial revisada muestra que es un motor de políticas/remediación sobre recursos YA desplegados, no una herramienta que estime costo antes del despliegue como Infracost; sus indicadores de Precio (P1, P2) y Visibilidad/Asignación se marcaron NA con esa justificación explícita, y se deja anotado por si el equipo prefiere revisar su clasificación en la población.
A11: Hojas de este libro:
A12: • Pesos — pesos de línea base y de sensibilidad por criterio (editable; todo el cálculo lee de aquí).
A13: • Puntuacion — una fila por Escenario x Producto x Indicador. Columnas: Valor (0-3/NE/NA), tipo de evidencia, evidencia, fuente, fecha de verificación y notas. Editar aquí para cargar nueva evidencia.
A14: • Calculo — una fila por Escenario x Producto. Calcula C_c por criterio, cobertura, renormalización, S (línea base y sensibilidad), banda e incumplimientos críticos, mediante fórmulas que leen directamente de Puntuacion y Pesos. No escribir valores fijos en esta hoja.
A15: • Graficos — gráficos de barras (S por producto y escenario) vinculados a la hoja Calculo.
A17: Reglas de puntuación (resumen; ver metodologia-comparativa-borrador.md para el detalle):
A18: • Escala 0-3: 0 ausencia/incumplimiento verificado; 1 práctica básica/manual; 2 práctica definida y proactiva; 3 práctica integrada y automatizada con doble evidencia.
... A27: Cruce con los papers académicos de FP-48 (revisión explícita a pedido del equipo): se revisaron los 13 PDF de "FP-48 TINV02/Papers academicos - FP-48/". Solo un paper nombra herramientas de la población de FP-51 -- Manurung y Aji (2025), que registra a 6 organizaciones reales usando AWS Cost Explorer, Cast.ai e Infracost, y encuentra que el 100% carece de showback/chargeback pese a ello. Según la propia metodología de FP-177 ("se excluye inferir resultados de herramientas desde evidencia académica que estudia prácticas... no el producto evaluado"), esa evidencia describe uso y brechas organizacionales, no verifica una capacidad del producto: se registró como nota de contexto en las filas de Puntuacion (columna Notas) para AWS Cost Explorer y se reutilizará para Cast AI / Infracost, pero no cambia ningún puntaje numérico. Los demás 12 papers ya están reflejados en docs/fp-177/ (metodología, criterios y escenarios) y no nombran productos comerciales adicionales.

Sheet Pesos
A1: Criterio | B1: Peso linea base (%) | C1: Peso sensibilidad (%)
A2: Visibilidad | B2: 11.111111 | C2: 15
A3: Asignación | B3: 11.111111 | C3: 15
A4: Optimización | B4: 11.111111 | C4: 15
A5: Automatización | B5: 11.111111 | C5: 10
A6: Multicloud | B6: 11.111111 | C6: 8
A7: Integración | B7: 11.111111 | C7: 10
A8: Adopción | B8: 11.111111 | C8: 8
A9: Precio | B9: 11.111111 | C9: 12
A10: Dependencia | B10: 11.111111 | C10: 7
A11: Total | B11: =SUM(B2:B10) | C11: =SUM(C2:C10)

Sheet Puntuacion
A1: Escenario | B1: Categoria | C1: Producto | D1: Criterio | E1: Indicador | F1: Pregunta observable | G1: Valor (0-3/NE/NA) | H1: Tipo de evidencia | I1: Evidencia | J1: Fuente | K1: Fecha de verificacion | L1: Notas
A2: E1 | B2: Cloud nativa | C2: AWS Cost Explorer | D2: Visibilidad | E2: V1 | F2: ¿Desagrega costo y uso por cuenta/proyecto, servicio y período? | G2: 2 | H2: Oficial | I2: Las etiquetas de asignación de costos y las Cost Categories desglosan el gasto por cuenta/proyecto y servicio, y son filtrables en Cost Explorer ("You can also use tags to filter views in Cost Explorer"). La actualización tiene hasta 24 h de latencia, no es en tiempo real. | J2: https://docs.aws.amazon.com/awsaccountbilling/latest/aboutv2/cost-alloc-tags.html | K2: 2026-09-16
A3: E1 | B3: Cloud nativa | C3: AWS Cost Explorer | D3: Visibilidad | E3: V2 | F3: ¿Permite rastrear un total hasta registros o fuente de facturación? | G3: 2 | H3: Oficial | I3: El Cost and Usage Report (CUR) entrega detalle por línea de facturación y "reconciles with the total charges on your Bills page", permitiendo rastrear un total hasta el registro fuente. | J3: https://docs.aws.amazon.com/cur/latest/userguide/what-is-cur.html | K3: 2026-09-16
A4: E1 | B4: Cloud nativa | C4: AWS Cost Explorer | D4: Asignacion | E4: A1 | F4: ¿Calcula gasto asignado/no asignado por responsable, centro o entidad? | G4: 2 | H4: Oficial | I4: Cost Categories es "a cost allocation service to help you map your AWS costs to your unique internal business structures" mediante reglas; expone una categoría de costos no mapeados. | J4: https://docs.aws.amazon.com/awsaccountbilling/latest/aboutv2/manage-cost-categories.html | K4: 2026-09-16 | L4: Contexto académico (no usado para puntuar): Manurung y Aji (2025) entrevistaron a 6 organizaciones que usan explícitamente esta herramienta ("We use AWS Cost Explorer, cast.ai, and infracost.", P2) y encontraron que el 100% (6/6) carece de showback/chargeback pese a ello ("[Gap] Cost ownership is centralized, no showback/chargeback", Tabla 4). Es evidencia de brecha organizacional, no de una limitación verificada del producto; se deja como insumo para el análisis de sensibilidad/limitaciones de FP-181, no como ajuste de este puntaje.
A5: E1 | B5: Cloud nativa | C5: AWS Cost Explorer | D5: Asignacion | E5: A2 | F5: ¿Explicita y aplica reglas para costo compartido/multi-tenant? | G5: 2 | H5: Oficial | I5: Cost Categories admite "Splitting charges within cost categories" (split charge rules) para repartir costos compartidos entre categorías/equipos. | J5: https://docs.aws.amazon.com/awsaccountbilling/latest/aboutv2/manage-cost-categories.html | K5: 2026-09-16
A6: E1 | B6: Cloud nativa | C6: AWS Cost Explorer | D6: Optimizacion | E6: O1 | F6: ¿Detecta desperdicio, rightsizing o compromiso relevante al escenario? | G6: 1 | H6: Oficial | I6: Cost Explorer conserva una vista propia de "rightsizing recommendations" (principalmente EC2), de alcance más acotado que Cost Optimization Hub. | J6: https://docs.aws.amazon.com/cost-management/latest/userguide/ce-rightsizing.html | K6: 2026-09-16
A7: E1 | B7: Cloud nativa | C7: AWS Cost Explorer | D7: Optimizacion | E7: O2 | F7: ¿Explica supuesto/impacto y permite seguir una recomendación? | G7: 1 | H7: Oficial | I7: La vista de rightsizing de Cost Explorer muestra el ahorro estimado por recomendación, sin el ciclo de seguimiento/objetivos que sí documenta Cost Optimization Hub. | J7: https://docs.aws.amazon.com/cost-management/latest/userguide/ce-rightsizing.html | K7: 2026-09-16
A8: E1 | B8: Cloud nativa | C8: AWS Cost Explorer | D8: Automatizacion | E8: AU1 | F8: ¿Ejecuta o bloquea acciones/políticas de costo con control verificable? | G8: 2 | H8: Oficial | I8: AWS Budgets puede ejecutar "budget actions" (política IAM Deny, SCP, detener instancias EC2/RDS) "either automatically or after your manual approval". | J8: https://docs.aws.amazon.com/cost-management/latest/userguide/budgets-controls.html | K8: 2026-09-16
A9: E1 | B9: Cloud nativa | C9: AWS Cost Explorer | D9: Automatizacion | E9: AU2 | F9: ¿Ofrece aprobación, reversión, registro o límites antes de actuar? | G9: 2 | H9: Oficial | I9: Las budget actions permiten exigir aprobación manual antes de ejecutarse. La documentación revisada no detalla registro de auditoría ni mecanismo de reversión explícito (limitación registrada). | J9: https://docs.aws.amazon.com/cost-management/latest/userguide/budgets-controls.html | K9: 2026-09-16
A10: E1 | B10: Cloud nativa | C10: AWS Cost Explorer | D10: Multicloud | E10: M1 | F10: ¿Consolida al menos dos proveedores bajo el mismo esquema declarado? | G10: 0 | H10: Oficial | I10: Cost Explorer y el CUR cubren exclusivamente cuentas y facturación de AWS; no ingieren ni consolidan datos de Azure o GCP. | J10: https://docs.aws.amazon.com/cur/latest/userguide/what-is-cur.html | K10: 2026-09-16
A11: E1 | B11: Cloud nativa | C11: AWS Cost Explorer | D11: Multicloud | E11: M2 | F11: ¿Hace visibles proveedor, cobertura y diferencias semánticas? | G11: 0 | H11: Oficial | I11: Al no consolidar otros proveedores, la herramienta no expone diferencias de cobertura o semántica entre nubes. | J11: https://docs.aws.amazon.com/cur/latest/userguide/what-is-cur.html | K11: 2026-09-16
A12: E1 | B12: Cloud nativa | C12: AWS Cost Explorer | D12: Integracion | E12: I1 | F12: ¿Integra datos requeridos (facturación, uso, clúster o IaC) del escenario? | G12: 2 | H12: Oficial | I12: El CUR/la API de Cost Explorer ingieren datos de facturación y uso de forma automatizada; para EKS, "Split Cost Allocation Data" añade métricas de clúster a nivel de pod/namespace al CUR. | J12: https://aws.amazon.com/about-aws/whats-new/2024/04/aws-split-cost-allocation-data-amazon-eks/ | K12: 2026-09-16
A13: E1 | B13: Cloud nativa | C13: AWS Cost Explorer | D13: Integracion | E13: I2 | F13: ¿Se integra con el flujo de trabajo relevante (alerta, ticket, CI/CD o reporte)? | G13: 2 | H13: Oficial | I13: AWS Cost Anomaly Detection y Budgets envían alertas (p. ej., a SNS/correo) integradas a un flujo operativo de revisión. | J13: https://docs.aws.amazon.com/cost-management/latest/userguide/budgets-controls.html | K13: 2026-09-16
A14: E1 | B14: Cloud nativa | C14: AWS Cost Explorer | D14: Adopcion | E14: AD1 | F14: ¿Soporta acceso/entrega para los roles del escenario? | G14: 2 | H14: Oficial (control de acceso IAM; pendiente cita directa de la guía de permisos de Billing) | I14: El acceso a Cost Explorer/Budgets se controla mediante políticas de IAM por usuario/rol (control de acceso estándar de AWS Billing). | J14: https://docs.aws.amazon.com/awsaccountbilling/latest/aboutv2/cost-alloc-tags.html | K14: 2026-09-16
A15: E1 | B15: Cloud nativa | C15: AWS Cost Explorer | D15: Adopcion | E15: AD2 | F15: ¿Ofrece guías, ownership o mecanismos de seguimiento para uso sostenido? | G15: 2 | H15: Oficial | I15: AWS publica guías oficiales de adopción, entre ellas el whitepaper de mejores prácticas de etiquetado y estrategia de asignación de costos. | J15: https://docs.aws.amazon.com/whitepapers/latest/tagging-best-practices/building-a-cost-allocation-strategy.html | K15: 2026-09-16 | L15: Contexto académico (no usado para puntuar): Manurung y Aji (2025) entrevistaron a 6 organizaciones que usan explícitamente esta herramienta ("We use AWS Cost Explorer, cast.ai, and infracost.", P2) y encontraron que el 100% (6/6) carece de showback/chargeback pese a ello ("[Gap] Cost ownership is centralized, no showback/chargeback", Tabla 4). Es evidencia de brecha organizacional, no de una limitación verificada del producto; se deja como insumo para el análisis de sensibilidad/limitaciones de FP-181, no como ajuste de este puntaje.
A16: E1 | B16: Cloud nativa | C16: AWS Cost Explorer | D16: Precio | E16: P1 | F16: ¿Expone precio, moneda, región, unidad, período y supuestos relevantes? | G16: 2 | H16: Oficial | I16: El CUR y los Data Exports FOCUS 1.0/1.2 exponen moneda, período, servicio y columnas estandarizadas de costo (ListCost, ContractedCost, BilledCost, EffectiveCost). | J16: https://aws.amazon.com/about-aws/whats-new/2024/11/aws-billing-cost-management-data-exports-focus-1-0 | K16: 2026-09-16
A17: E1 | B17: Cloud nativa | C17: AWS Cost Explorer | D17: Precio | E17: P2 | F17: ¿Permite estimar o comparar componentes sin ocultar límites de equivalencia? | G17: 1 | H17: Oficial (pendiente cita directa de la página de forecast) | I17: Cost Explorer ofrece pronóstico de costo futuro basado en tendencia histórica; no es una calculadora de estimación de componentes antes del despliegue (esa función es de AWS Pricing Calculator, evaluada aparte). | J17: https://docs.aws.amazon.com/cost-management/latest/userguide/ce-what-is.html | K17: 2026-09-16
A18: E1 | B18: Cloud nativa | C18: AWS Cost Explorer | D18: Dependencia | E18: D1 | F18: ¿Exporta datos/resultados en formato utilizable y documentado? | G18: 2 | H18: Oficial | I18: El CUR exporta a S3 en CSV/Parquet y, desde 2024-2025, también en el estándar abierto FOCUS 1.0/1.2. | J18: https://aws.amazon.com/about-aws/whats-new/2024/11/aws-billing-cost-management-data-exports-focus-1-0 | K18: 2026-09-16
A19: E1 | B19: Cloud nativa | C19: AWS Cost Explorer | D19: Dependencia | E19: D2 | F19: ¿Documenta dependencias propietarias y un camino de salida/configuración reversible? | G19: 1 | H19: Oficial | I19: No se encontró documentación específica de un "camino de salida" dedicado. El riesgo de dependencia es menor porque los datos son exportables en formato estándar (FOCUS) y el servicio no tiene costo propio, pero no hay guía de reversibilidad dedicada (limitación registrada). | J19: https://aws.amazon.com/about-aws/whats-new/2024/11/aws-billing-cost-management-data-exports-focus-1-0 | K19: 2026-09-16
A20: E2 | B20: Cloud nativa | C20: AWS Cost Explorer | D20: Visibilidad | E20: V1 | F20: ¿Desagrega costo y uso por cuenta/proyecto, servicio y período? | G20: NE | H20: Pendiente | I20: Las etiquetas de asignación de costos y las Cost Categories desglosan el gasto por cuenta/proyecto y servicio, y son filtrables en Cost Explorer ("You can also use tags to filter views in Cost Explorer"). La actualización tiene hasta 24 h de latencia, no es en tiempo real. | J20: https://docs.aws.amazon.com/awsaccountbilling/latest/aboutv2/cost-alloc-tags.html | K20: 2026-09-16 | L20: Celda heredada FP-180 (2026-09-16): el valor 2 proviene de la investigacion del escenario E1 y no cuenta con evidencia propia de E2. Segun FP-177 el indicador V1 depende del escenario, por lo que pasa a NE (no evidenciado, reduce cobertura) hasta investigarlo. La evidencia y la fuente originales se conservan como referencia del escenario de origen.
A21: E2 | B21: Cloud nativa | C21: AWS Cost Explorer | D21: Visibilidad | E21: V2 | F21: ¿Permite rastrear un total hasta registros o fuente de facturación? | G21: 2 | H21: Oficial | I21: El Cost and Usage Report (CUR) entrega detalle por línea de facturación y "reconciles with the total charges on your Bills page", permitiendo rastrear un total hasta el registro fuente. | J21: https://docs.aws.amazon.com/cur/latest/userguide/what-is-cur.html | K21: 2026-09-16
A22: E2 | B22: Cloud nativa | C22: AWS Cost Explorer | D22: Asignacion | E22: A1 | F22: ¿Calcula gasto asignado/no asignado por responsable, centro o entidad? | G22: NE | H22: Pendiente | I22: Cost Categories es "a cost allocation service to help you map your AWS costs to your unique internal business structures" mediante reglas; expone una categoría de costos no mapeados. | J22: https://docs.aws.amazon.com/awsaccountbilling/latest/aboutv2/manage-cost-categories.html | K22: 2026-09-16 | L22: Contexto académico (no usado para puntuar): Manurung y Aji (2025) entrevistaron a 6 organizaciones que usan explícitamente esta herramienta ("We use AWS Cost Explorer, cast.ai, and infracost.", P2) y encontraron que el 100% (6/6) carece de showback/chargeback pese a ello ("[Gap] Cost ownership is centralized, no showback/chargeback", Tabla 4). Es evidencia de brecha organizacional, no de una limitación verificada del producto; se deja como insumo para el análisis de sensibilidad/limitaciones de FP-181, no como ajuste de este puntaje. | Celda heredada FP-180 (2026-09-16): el valor 2 proviene de la investigacion del escenario E1 y no cuenta con evidencia propia de E2. Segun FP-177 el indicador A1 depende del escenario, por lo que pasa a NE (no evidenciado, reduce cobertura) hasta investigarlo. La evidencia y la fuente originales se conservan como referencia del escenario de origen.
A23: E2 | B23: Cloud nativa | C23: AWS Cost Explorer | D23: Asignacion | E23: A2 | F23: ¿Explicita y aplica reglas para costo compartido/multi-tenant? | G23: NE | H23: Pendiente | I23: Cost Categories admite "Splitting charges within cost categories" (split charge rules) para repartir costos compartidos entre categorías/equipos. | J23: https://docs.aws.amazon.com/awsaccountbilling/latest/aboutv2/manage-cost-categories.html | K23: 2026-09-16 | L23: Celda heredada FP-180 (2026-09-16): el valor 2 proviene de la investigacion del escenario E1 y no cuenta con evidencia propia de E2. Segun FP-177 el indicador A2 depende del escenario, por lo que pasa a NE (no evidenciado, reduce cobertura) hasta investigarlo. La evidencia y la fuente originales se conservan como referencia del escenario de origen.
A24: E2 | B24: Cloud nativa | C24: AWS Cost Explorer | D24: Optimizacion | E24: O1 | F24: ¿Detecta desperdicio, rightsizing o compromiso relevante al escenario? | G24: NE | H24: Pendiente | I24: Cost Explorer conserva una vista propia de "rightsizing recommendations" (principalmente EC2), de alcance más acotado que Cost Optimization Hub. | J24: https://docs.aws.amazon.com/cost-management/latest/userguide/ce-rightsizing.html | K24: 2026-09-16 | L24: Celda heredada FP-180 (2026-09-16): el valor 1 proviene de la investigacion del escenario E1 y no cuenta con evidencia propia de E2. Segun FP-177 el indicador O1 depende del escenario, por lo que pasa a NE (no evidenciado, reduce cobertura) hasta investigarlo. La evidencia y la fuente originales se conservan como referencia del escenario de origen.
A25: E2 | B25: Cloud nativa | C25: AWS Cost Explorer | D25: Optimizacion | E25: O2 | F25: ¿Explica supuesto/impacto y permite seguir una recomendación? | G25: 1 | H25: Oficial | I25: La vista de rightsizing de Cost Explorer muestra el ahorro estimado por recomendación, sin el ciclo de seguimiento/objetivos que sí documenta Cost Optimization Hub. | J25: https://docs.aws.amazon.com/cost-management/latest/userguide/ce-rightsizing.html | K25: 2026-09-16
A26: E2 | B26: Cloud nativa | C26: AWS Cost Explorer | D26: Automatizacion | E26: AU1 | F26: ¿Ejecuta o bloquea acciones/políticas de costo con control verificable? | G26: NE | H26: Pendiente | I26: AWS Budgets puede ejecutar "budget actions" (política IAM Deny, SCP, detener instancias EC2/RDS) "either automatically or after your manual approval". | J26: https://docs.aws.amazon.com/cost-management/latest/userguide/budgets-controls.html | K26: 2026-09-16 | L26: Celda heredada FP-180 (2026-09-16): el valor 2 proviene de la investigacion del escenario E1 y no cuenta con evidencia propia de E2. Segun FP-177 el indicador AU1 depende del escenario, por lo que pasa a NE (no evidenciado, reduce cobertura) hasta investigarlo. La evidencia y la fuente originales se conservan como referencia del escenario de origen.
A27: E2 | B27: Cloud nativa | C27: AWS Cost Explorer | D27: Automatizacion | E27: AU2 | F27: ¿Ofrece aprobación, reversión, registro o límites antes de actuar? | G27: 2 | H27: Oficial | I27: Las budget actions permiten exigir aprobación manual antes de ejecutarse. La documentación revisada no detalla registro de auditoría ni mecanismo de reversión explícito (limitación registrada). | J27: https://docs.aws.amazon.com/cost-management/latest/userguide/budgets-controls.html | K27: 2026-09-16
A28: E2 | B28: Cloud nativa | C28: AWS Cost Explorer | D28: Multicloud | E28: M1 | F28: ¿Consolida al menos dos proveedores bajo el mismo esquema declarado? | G28: 0 | H28: Oficial | I28: Cost Explorer y el CUR cubren exclusivamente cuentas y facturación de AWS; no ingieren ni consolidan datos de Azure o GCP. | J28: https://docs.aws.amazon.com/cur/latest/userguide/what-is-cur.html | K28: 2026-09-16
A29: E2 | B29: Cloud nativa | C29: AWS Cost Explorer | D29: Multicloud | E29: M2 | F29: ¿Hace visibles proveedor, cobertura y diferencias semánticas? | G29: 0 | H29: Oficial | I29: Al no consolidar otros proveedores, la herramienta no expone diferencias de cobertura o semántica entre nubes. | J29: https://docs.aws.amazon.com/cur/latest/userguide/what-is-cur.html | K29: 2026-09-16
A30: E2 | B30: Cloud nativa | C30: AWS Cost Explorer | D30: Integracion | E30: I1 | F30: ¿Integra datos requeridos (facturación, uso, clúster o IaC) del escenario? | G30: NE | H30: Pendiente | I30: El CUR/la API de Cost Explorer ingieren datos de facturación y uso de forma automatizada; para EKS, "Split Cost Allocation Data" añade métricas de clúster a nivel de pod/namespace al CUR. | J30: https://aws.amazon.com/about-aws/whats-new/2024/04/aws-split-cost-allocation-data-amazon-eks/ | K30: 2026-09-16 | L30: Celda heredada FP-180 (2026-09-16): el valor 2 proviene de la investigacion del escenario E1 y no cuenta con evidencia propia de E2. Segun FP-177 el indicador I1 depende del escenario, por lo que pasa a NE (no evidenciado, reduce cobertura) hasta investigarlo. La evidencia y la fuente originales se conservan como referencia del escenario de origen.
A31: E2 | B31: Cloud nativa | C31: AWS Cost Explorer | D31: Integracion | E31: I2 | F31: ¿Se integra con el flujo de trabajo relevante (alerta, ticket, CI/CD o reporte)? | G31: NE | H31: Pendiente | I31: AWS Cost Anomaly Detection y Budgets envían alertas (p. ej., a SNS/correo) integradas a un flujo operativo de revisión. | J31: https://docs.aws.amazon.com/cost-management/latest/userguide/budgets-controls.html | K31: 2026-09-16 | L31: Celda heredada FP-180 (2026-09-16): el valor 2 proviene de la investigacion del escenario E1 y no cuenta con evidencia propia de E2. Segun FP-177 el indicador I2 depende del escenario, por lo que pasa a NE (no evidenciado, reduce cobertura) hasta investigarlo. La evidencia y la fuente originales se conservan como referencia del escenario de origen.
A32: E2 | B32: Cloud nativa | C32: AWS Cost Explorer | D32: Adopcion | E32: AD1 | F32: ¿Soporta acceso/entrega para los roles del escenario? | G32: NE | H32: Pendiente | I32: El acceso a Cost Explorer/Budgets se controla mediante políticas de IAM por usuario/rol (control de acceso estándar de AWS Billing). | J32: https://docs.aws.amazon.com/awsaccountbilling/latest/aboutv2/cost-alloc-tags.html | K32: 2026-09-16 | L32: Celda heredada FP-180 (2026-09-16): el valor 2 proviene de la investigacion del escenario E1 y no cuenta con evidencia propia de E2. Segun FP-177 el indicador AD1 depende del escenario, por lo que pasa a NE (no evidenciado, reduce cobertura) hasta investigarlo. La evidencia y la fuente originales se conservan como referencia del escenario de origen.
A33: E2 | B33: Cloud nativa | C33: AWS Cost Explorer | D33: Adopcion | E33: AD2 | F33: ¿Ofrece guías, ownership o mecanismos de seguimiento para uso sostenido? | G33: 2 | H33: Oficial | I33: AWS publica guías oficiales de adopción, entre ellas el whitepaper de mejores prácticas de etiquetado y estrategia de asignación de costos. | J33: https://docs.aws.amazon.com/whitepapers/latest/tagging-best-practices/building-a-cost-allocation-strategy.html | K33: 2026-09-16 | L33: Contexto académico (no usado para puntuar): Manurung y Aji (2025) entrevistaron a 6 organizaciones que usan explícitamente esta herramienta ("We use AWS Cost Explorer, cast.ai, and infracost.", P2) y encontraron que el 100% (6/6) carece de showback/chargeback pese a ello ("[Gap] Cost ownership is centralized, no showback/chargeback", Tabla 4). Es evidencia de brecha organizacional, no de una limitación verificada del producto; se deja como insumo para el análisis de sensibilidad/limitaciones de FP-181, no como ajuste de este puntaje.
A34: E2 | B34: Cloud nativa | C34: AWS Cost Explorer | D34: Precio | E34: P1 | F34: ¿Expone precio, moneda, región, unidad, período y supuestos relevantes? | G34: 2 | H34: Oficial | I34: El CUR y los Data Exports FOCUS 1.0/1.2 exponen moneda, período, servicio y columnas estandarizadas de costo (ListCost, ContractedCost, BilledCost, EffectiveCost). | J34: https://aws.amazon.com/about-aws/whats-new/2024/11/aws-billing-cost-management-data-exports-focus-1-0 | K34: 2026-09-16
A35: E2 | B35: Cloud nativa | C35: AWS Cost Explorer | D35: Precio | E35: P2 | F35: ¿Permite estimar o comparar componentes sin ocultar límites de equivalencia? | G35: NE | H35: Pendiente | I35: Cost Explorer ofrece pronóstico de costo futuro basado en tendencia histórica; no es una calculadora de estimación de componentes antes del despliegue (esa función es de AWS Pricing Calculator, evaluada aparte). | J35: https://docs.aws.amazon.com/cost-management/latest/userguide/ce-what-is.html | K35: 2026-09-16 | L35: Celda heredada FP-180 (2026-09-16): el valor 1 proviene de la investigacion del escenario E1 y no cuenta con evidencia propia de E2. Segun FP-177 el indicador P2 depende del escenario, por lo que pasa a NE (no evidenciado, reduce cobertura) hasta investigarlo. La evidencia y la fuente originales se conservan como referencia del escenario de origen.
A36: E2 | B36: Cloud nativa | C36: AWS Cost Explorer | D36: Dependencia | E36: D1 | F36: ¿Exporta datos/resultados en formato utilizable y documentado? | G36: 2 | H36: Oficial | I36: El CUR exporta a S3 en CSV/Parquet y, desde 2024-2025, también en el estándar abierto FOCUS 1.0/1.2. | J36: https://aws.amazon.com/about-aws/whats-new/2024/11/aws-billing-cost-management-data-exports-focus-1-0 | K36: 2026-09-16
A37: E2 | B37: Cloud nativa | C37: AWS Cost Explorer | D37: Dependencia | E37: D2 | F37: ¿Documenta dependencias propietarias y un camino de salida/configuración reversible? | G37: 1 | H37: Oficial | I37: No se encontró documentación específica de un "camino de salida" dedicado. El riesgo de dependencia es menor porque los datos son exportables en formato estándar (FOCUS) y el servicio no tiene costo propio, pero no hay guía de reversibilidad dedicada (limitación registrada). | J37: https://aws.amazon.com/about-aws/whats-new/2024/11/aws-billing-cost-management-data-exports-focus-1-0 | K37: 2026-09-16
A38: E3 | B38: Cloud nativa | C38: AWS Cost Explorer | D38: Visibilidad | E38: V1 | F38: ¿Desagrega costo y uso por cuenta/proyecto, servicio y período? | G38: NE | H38: Pendiente | I38: Las etiquetas de asignación de costos y las Cost Categories desglosan el gasto por cuenta/proyecto y servicio, y son filtrables en Cost Explorer ("You can also use tags to filter views in Cost Explorer"). La actualización tiene hasta 24 h de latencia, no es en tiempo real. | J38: https://docs.aws.amazon.com/awsaccountbilling/latest/aboutv2/cost-alloc-tags.html | K38: 2026-09-16 | L38: En E3, la evidencia de granularidad de clúster proviene de "Split Cost Allocation Data" para Amazon EKS (visibilidad a nivel de pod/namespace); las recomendaciones de rightsizing de AWS (Cost Explorer/Cost Optimization Hub) operan sobre el nodo EC2 subyacente, no sobre el dimensionamiento de pods dentro del clúster, lo que limita su alcance frente a herramientas especializadas en Kubernetes (OpenCost, Kubecost, Cast AI, StormForge). | Celda heredada FP-180 (2026-09-16): el valor 2 proviene de la investigacion del escenario E1 y no cuenta con evidencia propia de E3. Segun FP-177 el indicador V1 depende del escenario, por lo que pasa a NE (no evidenciado, reduce cobertura) hasta investigarlo. La evidencia y la fuente originales se conservan como referencia del escenario de origen.
A39: E3 | B39: Cloud nativa | C39: AWS Cost Explorer | D39: Visibilidad | E39: V2 | F39: ¿Permite rastrear un total hasta registros o fuente de facturación? | G39: 2 | H39: Oficial | I39: El Cost and Usage Report (CUR) entrega detalle por línea de facturación y "reconciles with the total charges on your Bills page", permitiendo rastrear un total hasta el registro fuente. | J39: https://docs.aws.amazon.com/cur/latest/userguide/what-is-cur.html | K39: 2026-09-16 | L39: En E3, la evidencia de granularidad de clúster proviene de "Split Cost Allocation Data" para Amazon EKS (visibilidad a nivel de pod/namespace); las recomendaciones de rightsizing de AWS (Cost Explorer/Cost Optimization Hub) operan sobre el nodo EC2 subyacente, no sobre el dimensionamiento de pods dentro del clúster, lo que limita su alcance frente a herramientas especializadas en Kubernetes (OpenCost, Kubecost, Cast AI, StormForge).
A40: E3 | B40: Cloud nativa | C40: AWS Cost Explorer | D40: Asignacion | E40: A1 | F40: ¿Calcula gasto asignado/no asignado por responsable, centro o entidad? | G40: NE | H40: Pendiente | I40: Cost Categories es "a cost allocation service to help you map your AWS costs to your unique internal business structures" mediante reglas; expone una categoría de costos no mapeados. | J40: https://docs.aws.amazon.com/awsaccountbilling/latest/aboutv2/manage-cost-categories.html | K40: 2026-09-16 | L40: En E3, la evidencia de granularidad de clúster proviene de "Split Cost Allocation Data" para Amazon EKS (visibilidad a nivel de pod/namespace); las recomendaciones de rightsizing de AWS (Cost Explorer/Cost Optimization Hub) operan sobre el nodo EC2 subyacente, no sobre el dimensionamiento de pods dentro del clúster, lo que limita su alcance frente a herramientas especializadas en Kubernetes (OpenCost, Kubecost, Cast AI, StormForge). Contexto académico (no usado para puntuar): Manurung y Aji (2025) entrevistaron a 6 organizaciones que usan explícitamente esta herramienta ("We use AWS Cost Explorer, cast.ai, and infracost.", P2) y encontraron que el 100% (6/6) carece de showback/chargeback pese a ello ("[Gap] Cost ownership is centralized, no showback/chargeback", Tabla 4). Es evidencia de brecha organizacional, no de una limitación verificada del producto; se deja como insumo para el análisis de sensibilidad/limitaciones de FP-181, no como ajuste de este puntaje. | Celda heredada FP-180 (2026-09-16): el valor 2 proviene de la investigacion del escenario E1 y no cuenta con evidencia propia de E3. Segun FP-177 el indicador A1 depende del escenario, por lo que pasa a NE (no evidenciado, reduce cobertura) hasta investigarlo. La evidencia y la fuente originales se conservan como referencia del escenario de origen.
A41: E3 | B41: Cloud nativa | C41: AWS Cost Explorer | D41: Asignacion | E41: A2 | F41: ¿Explicita y aplica reglas para costo compartido/multi-tenant? | G41: NE | H41: Pendiente | I41: Cost Categories admite "Splitting charges within cost categories" (split charge rules) para repartir costos compartidos entre categorías/equipos. | J41: https://docs.aws.amazon.com/awsaccountbilling/latest/aboutv2/manage-cost-categories.html | K41: 2026-09-16 | L41: En E3, la evidencia de granularidad de clúster proviene de "Split Cost Allocation Data" para Amazon EKS (visibilidad a nivel de pod/namespace); las recomendaciones de rightsizing de AWS (Cost Explorer/Cost Optimization Hub) operan sobre el nodo EC2 subyacente, no sobre el dimensionamiento de pods dentro del clúster, lo que limita su alcance frente a herramientas especializadas en Kubernetes (OpenCost, Kubecost, Cast AI, StormForge). | Celda heredada FP-180 (2026-09-16): el valor 2 proviene de la investigacion del escenario E1 y no cuenta con evidencia propia de E3. Segun FP-177 el indicador A2 depende del escenario, por lo que pasa a NE (no evidenciado, reduce cobertura) hasta investigarlo. La evidencia y la fuente originales se conservan como referencia del escenario de origen.
A42: E3 | B42: Cloud nativa | C42: AWS Cost Explorer | D42: Optimizacion | E42: O1 | F42: ¿Detecta desperdicio, rightsizing o compromiso relevante al escenario? | G42: NE | H42: Pendiente | I42: Cost Explorer conserva una vista propia de "rightsizing recommendations" (principalmente EC2), de alcance más acotado que Cost Optimization Hub. | J42: https://docs.aws.amazon.com/cost-management/latest/userguide/ce-rightsizing.html | K42: 2026-09-16 | L42: En E3, la evidencia de granularidad de clúster proviene de "Split Cost Allocation Data" para Amazon EKS (visibilidad a nivel de pod/namespace); las recomendaciones de rightsizing de AWS (Cost Explorer/Cost Optimization Hub) operan sobre el nodo EC2 subyacente, no sobre el dimensionamiento de pods dentro del clúster, lo que limita su alcance frente a herramientas especializadas en Kubernetes (OpenCost, Kubecost, Cast AI, StormForge). | Celda heredada FP-180 (2026-09-16): el valor 1 proviene de la investigacion del escenario E1 y no cuenta con evidencia propia de E3. Segun FP-177 el indicador O1 depende del escenario, por lo que pasa a NE (no evidenciado, reduce cobertura) hasta investigarlo. La evidencia y la fuente originales se conservan como referencia del escenario de origen.
A43: E3 | B43: Cloud nativa | C43: AWS Cost Explorer | D43: Optimizacion | E43: O2 | F43: ¿Explica supuesto/impacto y permite seguir una recomendación? | G43: 1 | H43: Oficial | I43: La vista de rightsizing de Cost Explorer muestra el ahorro estimado por recomendación, sin el ciclo de seguimiento/objetivos que sí documenta Cost Optimization Hub. | J43: https://docs.aws.amazon.com/cost-management/latest/userguide/ce-rightsizing.html | K43: 2026-09-16 | L43: En E3, la evidencia de granularidad de clúster proviene de "Split Cost Allocation Data" para Amazon EKS (visibilidad a nivel de pod/namespace); las recomendaciones de rightsizing de AWS (Cost Explorer/Cost Optimization Hub) operan sobre el nodo EC2 subyacente, no sobre el dimensionamiento de pods dentro del clúster, lo que limita su alcance frente a herramientas especializadas en Kubernetes (OpenCost, Kubecost, Cast AI, StormForge).
A44: E3 | B44: Cloud nativa | C44: AWS Cost Explorer | D44: Automatizacion | E44: AU1 | F44: ¿Ejecuta o bloquea acciones/políticas de costo con control verificable? | G44: NE | H44: Pendiente | I44: AWS Budgets puede ejecutar "budget actions" (política IAM Deny, SCP, detener instancias EC2/RDS) "either automatically or after your manual approval". | J44: https://docs.aws.amazon.com/cost-management/latest/userguide/budgets-controls.html | K44: 2026-09-16 | L44: En E3, la evidencia de granularidad de clúster proviene de "Split Cost Allocation Data" para Amazon EKS (visibilidad a nivel de pod/namespace); las recomendaciones de rightsizing de AWS (Cost Explorer/Cost Optimization Hub) operan sobre el nodo EC2 subyacente, no sobre el dimensionamiento de pods dentro del clúster, lo que limita su alcance frente a herramientas especializadas en Kubernetes (OpenCost, Kubecost, Cast AI, StormForge). | Celda heredada FP-180 (2026-09-16): el valor 2 proviene de la investigacion del escenario E1 y no cuenta con evidencia propia de E3. Segun FP-177 el indicador AU1 depende del escenario, por lo que pasa a NE (no evidenciado, reduce cobertura) hasta investigarlo. La evidencia y la fuente originales se conservan como referencia del escenario de origen.
A45: E3 | B45: Cloud nativa | C45: AWS Cost Explorer | D45: Automatizacion | E45: AU2 | F45: ¿Ofrece aprobación, reversión, registro o límites antes de actuar? | G45: 2 | H45: Oficial | I45: Las budget actions permiten exigir aprobación manual antes de ejecutarse. La documentación revisada no detalla registro de auditoría ni mecanismo de reversión explícito (limitación registrada). | J45: https://docs.aws.amazon.com/cost-management/latest/userguide/budgets-controls.html | K45: 2026-09-16 | L45: En E3, la evidencia de granularidad de clúster proviene de "Split Cost Allocation Data" para Amazon EKS (visibilidad a nivel de pod/namespace); las recomendaciones de rightsizing de AWS (Cost Explorer/Cost Optimization Hub) operan sobre el nodo EC2 subyacente, no sobre el dimensionamiento de pods dentro del clúster, lo que limita su alcance frente a herramientas especializadas en Kubernetes (OpenCost, Kubecost, Cast AI, StormForge).
A46: E3 | B46: Cloud nativa | C46: AWS Cost Explorer | D46: Multicloud | E46: M1 | F46: ¿Consolida al menos dos proveedores bajo el mismo esquema declarado? | G46: 0 | H46: Oficial | I46: Cost Explorer y el CUR cubren exclusivamente cuentas y facturación de AWS; no ingieren ni consolidan datos de Azure o GCP. | J46: https://docs.aws.amazon.com/cur/latest/userguide/what-is-cur.html | K46: 2026-09-16 | L46: En E3, la evidencia de granularidad de clúster proviene de "Split Cost Allocation Data" para Amazon EKS (visibilidad a nivel de pod/namespace); las recomendaciones de rightsizing de AWS (Cost Explorer/Cost Optimization Hub) operan sobre el nodo EC2 subyacente, no sobre el dimensionamiento de pods dentro del clúster, lo que limita su alcance frente a herramientas especializadas en Kubernetes (OpenCost, Kubecost, Cast AI, StormForge).
A47: E3 | B47: Cloud nativa | C47: AWS Cost Explorer | D47: Multicloud | E47: M2 | F47: ¿Hace visibles proveedor, cobertura y diferencias semánticas? | G47: 0 | H47: Oficial | I47: Al no consolidar otros proveedores, la herramienta no expone diferencias de cobertura o semántica entre nubes. | J47: https://docs.aws.amazon.com/cur/latest/userguide/what-is-cur.html | K47: 2026-09-16 | L47: En E3, la evidencia de granularidad de clúster proviene de "Split Cost Allocation Data" para Amazon EKS (visibilidad a nivel de pod/namespace); las recomendaciones de rightsizing de AWS (Cost Explorer/Cost Optimization Hub) operan sobre el nodo EC2 subyacente, no sobre el dimensionamiento de pods dentro del clúster, lo que limita su alcance frente a herramientas especializadas en Kubernetes (OpenCost, Kubecost, Cast AI, StormForge).
A48: E3 | B48: Cloud nativa | C48: AWS Cost Explorer | D48: Integracion | E48: I1 | F48: ¿Integra datos requeridos (facturación, uso, clúster o IaC) del escenario? | G48: NE | H48: Pendiente | I48: El CUR/la API de Cost Explorer ingieren datos de facturación y uso de forma automatizada; para EKS, "Split Cost Allocation Data" añade métricas de clúster a nivel de pod/namespace al CUR. | J48: https://aws.amazon.com/about-aws/whats-new/2024/04/aws-split-cost-allocation-data-amazon-eks/ | K48: 2026-09-16 | L48: En E3, la evidencia de granularidad de clúster proviene de "Split Cost Allocation Data" para Amazon EKS (visibilidad a nivel de pod/namespace); las recomendaciones de rightsizing de AWS (Cost Explorer/Cost Optimization Hub) operan sobre el nodo EC2 subyacente, no sobre el dimensionamiento de pods dentro del clúster, lo que limita su alcance frente a herramientas especializadas en Kubernetes (OpenCost, Kubecost, Cast AI, StormForge). | Celda heredada FP-180 (2026-09-16): el valor 2 proviene de la investigacion del escenario E1 y no cuenta con evidencia propia de E3. Segun FP-177 el indicador I1 depende del escenario, por lo que pasa a NE (no evidenciado, reduce cobertura) hasta investigarlo. La evidencia y la fuente originales se conservan como referencia del escenario de origen.
A49: E3 | B49: Cloud nativa | C49: AWS Cost Explorer | D49: Integracion | E49: I2 | F49: ¿Se integra con el flujo de trabajo relevante (alerta, ticket, CI/CD o reporte)? | G49: NE | H49: Pendiente | I49: AWS Cost Anomaly Detection y Budgets envían alertas (p. ej., a SNS/correo) integradas a un flujo operativo de revisión. | J49: https://docs.aws.amazon.com/cost-management/latest/userguide/budgets-controls.html | K49: 2026-09-16 | L49: En E3, la evidencia de granularidad de clúster proviene de "Split Cost Allocation Data" para Amazon EKS (visibilidad a nivel de pod/namespace); las recomendaciones de rightsizing de AWS (Cost Explorer/Cost Optimization Hub) operan sobre el nodo EC2 subyacente, no sobre el dimensionamiento de pods dentro del clúster, lo que limita su alcance frente a herramientas especializadas en Kubernetes (OpenCost, Kubecost, Cast AI, StormForge). | Celda heredada FP-180 (2026-09-16): el valor 2 proviene de la investigacion del escenario E1 y no cuenta con evidencia propia de E3. Segun FP-177 el indicador I2 depende del escenario, por lo que pasa a NE (no evidenciado, reduce cobertura) hasta investigarlo. La evidencia y la fuente originales se conservan como referencia del escenario de origen.
A50: E3 | B50: Cloud nativa | C50: AWS Cost Explorer | D50: Adopcion | E50: AD1 | F50: ¿Soporta acceso/entrega para los roles del escenario? | G50: NE | H50: Pendiente | I50: El acceso a Cost Explorer/Budgets se controla mediante políticas de IAM por usuario/rol (control de acceso estándar de AWS Billing). | J50: https://docs.aws.amazon.com/awsaccountbilling/latest/aboutv2/cost-alloc-tags.html | K50: 2026-09-16 | L50: En E3, la evidencia de granularidad de clúster proviene de "Split Cost Allocation Data" para Amazon EKS (visibilidad a nivel de pod/namespace); las recomendaciones de rightsizing de AWS (Cost Explorer/Cost Optimization Hub) operan sobre el nodo EC2 subyacente, no sobre el dimensionamiento de pods dentro del clúster, lo que limita su alcance frente a herramientas especializadas en Kubernetes (OpenCost, Kubecost, Cast AI, StormForge). | Celda heredada FP-180 (2026-09-16): el valor 2 proviene de la investigacion del escenario E1 y no cuenta con evidencia propia de E3. Segun FP-177 el indicador AD1 depende del escenario, por lo que pasa a NE (no evidenciado, reduce cobertura) hasta investigarlo. La evidencia y la fuente originales se conservan como referencia del escenario de origen.
A51: E3 | B51: Cloud nativa | C51: AWS Cost Explorer | D51: Adopcion | E51: AD2 | F51: ¿Ofrece guías, ownership o mecanismos de seguimiento para uso sostenido? | G51: 2 | H51: Oficial | I51: AWS publica guías oficiales de adopción, entre ellas el whitepaper de mejores prácticas de etiquetado y estrategia de asignación de costos. | J51: https://docs.aws.amazon.com/whitepapers/latest/tagging-best-practices/building-a-cost-allocation-strategy.html | K51: 2026-09-16 | L51: En E3, la evidencia de granularidad de clúster proviene de "Split Cost Allocation Data" para Amazon EKS (visibilidad a nivel de pod/namespace); las recomendaciones de rightsizing de AWS (Cost Explorer/Cost Optimization Hub) operan sobre el nodo EC2 subyacente, no sobre el dimensionamiento de pods dentro del clúster, lo que limita su alcance frente a herramientas especializadas en Kubernetes (OpenCost, Kubecost, Cast AI, StormForge). Contexto académico (no usado para puntuar): Manurung y Aji (2025) entrevistaron a 6 organizaciones que usan explícitamente esta herramienta ("We use AWS Cost Explorer, cast.ai, and infracost.", P2) y encontraron que el 100% (6/6) carece de showback/chargeback pese a ello ("[Gap] Cost ownership is centralized, no showback/chargeback", Tabla 4). Es evidencia de brecha organizacional, no de una limitación verificada del producto; se deja como insumo para el análisis de sensibilidad/limitaciones de FP-181, no como ajuste de este puntaje.
A52: E3 | B52: Cloud nativa | C52: AWS Cost Explorer | D52: Precio | E52: P1 | F52: ¿Expone precio, moneda, región, unidad, período y supuestos relevantes? | G52: 2 | H52: Oficial | I52: El CUR y los Data Exports FOCUS 1.0/1.2 exponen moneda, período, servicio y columnas estandarizadas de costo (ListCost, ContractedCost, BilledCost, EffectiveCost). | J52: https://aws.amazon.com/about-aws/whats-new/2024/11/aws-billing-cost-management-data-exports-focus-1-0 | K52: 2026-09-16 | L52: En E3, la evidencia de granularidad de clúster proviene de "Split Cost Allocation Data" para Amazon EKS (visibilidad a nivel de pod/namespace); las recomendaciones de rightsizing de AWS (Cost Explorer/Cost Optimization Hub) operan sobre el nodo EC2 subyacente, no sobre el dimensionamiento de pods dentro del clúster, lo que limita su alcance frente a herramientas especializadas en Kubernetes (OpenCost, Kubecost, Cast AI, StormForge).
A53: E3 | B53: Cloud nativa | C53: AWS Cost Explorer | D53: Precio | E53: P2 | F53: ¿Permite estimar o comparar componentes sin ocultar límites de equivalencia? | G53: NE | H53: Pendiente | I53: Cost Explorer ofrece pronóstico de costo futuro basado en tendencia histórica; no es una calculadora de estimación de componentes antes del despliegue (esa función es de AWS Pricing Calculator, evaluada aparte). | J53: https://docs.aws.amazon.com/cost-management/latest/userguide/ce-what-is.html | K53: 2026-09-16 | L53: En E3, la evidencia de granularidad de clúster proviene de "Split Cost Allocation Data" para Amazon EKS (visibilidad a nivel de pod/namespace); las recomendaciones de rightsizing de AWS (Cost Explorer/Cost Optimization Hub) operan sobre el nodo EC2 subyacente, no sobre el dimensionamiento de pods dentro del clúster, lo que limita su alcance frente a herramientas especializadas en Kubernetes (OpenCost, Kubecost, Cast AI, StormForge). | Celda heredada FP-180 (2026-09-16): el valor 1 proviene de la investigacion del escenario E1 y no cuenta con evidencia propia de E3. Segun FP-177 el indicador P2 depende del escenario, por lo que pasa a NE (no evidenciado, reduce cobertura) hasta investigarlo. La evidencia y la fuente originales se conservan como referencia del escenario de origen.
A54: E3 | B54: Cloud nativa | C54: AWS Cost Explorer | D54: Dependencia | E54: D1 | F54: ¿Exporta datos/resultados en formato utilizable y documentado? | G54: 2 | H54: Oficial | I54: El CUR exporta a S3 en CSV/Parquet y, desde 2024-2025, también en el estándar abierto FOCUS 1.0/1.2. | J54: https://aws.amazon.com/about-aws/whats-new/2024/11/aws-billing-cost-management-data-exports-focus-1-0 | K54: 2026-09-16 | L54: En E3, la evidencia de granularidad de clúster proviene de "Split Cost Allocation Data" para Amazon EKS (visibilidad a nivel de pod/namespace); las recomendaciones de rightsizing de AWS (Cost Explorer/Cost Optimization Hub) operan sobre el nodo EC2 subyacente, no sobre el dimensionamiento de pods dentro del clúster, lo que limita su alcance frente a herramientas especializadas en Kubernetes (OpenCost, Kubecost, Cast AI, StormForge).
A55: E3 | B55: Cloud nativa | C55: AWS Cost Explorer | D55: Dependencia | E55: D2 | F55: ¿Documenta dependencias propietarias y un camino de salida/configuración reversible? | G55: 1 | H55: Oficial | I55: No se encontró documentación específica de un "camino de salida" dedicado. El riesgo de dependencia es menor porque los datos son exportables en formato estándar (FOCUS) y el servicio no tiene costo propio, pero no hay guía de reversibilidad dedicada (limitación registrada). | J55: https://aws.amazon.com/about-aws/whats-new/2024/11/aws-billing-cost-management-data-exports-focus-1-0 | K55: 2026-09-16 | L55: En E3, la evidencia de granularidad de clúster proviene de "Split Cost Allocation Data" para Amazon EKS (visibilidad a nivel de pod/namespace); las recomendaciones de rightsizing de AWS (Cost Explorer/Cost Optimization Hub) operan sobre el nodo EC2 subyacente, no sobre el dimensionamiento de pods dentro del clúster, lo que limita su alcance frente a herramientas especializadas en Kubernetes (OpenCost, Kubecost, Cast AI, StormForge).
A56: E5 | B56: Cloud nativa | C56: AWS Cost Explorer | D56: Visibilidad | E56: V1 | F56: ¿Desagrega costo y uso por cuenta/proyecto, servicio y período? | G56: NE | H56: Pendiente | I56: Las etiquetas de asignación de costos y las Cost Categories desglosan el gasto por cuenta/proyecto y servicio, y son filtrables en Cost Explorer ("You can also use tags to filter views in Cost Explorer"). La actualización tiene hasta 24 h de latencia, no es en tiempo real. | J56: https://docs.aws.amazon.com/awsaccountbilling/latest/aboutv2/cost-alloc-tags.html | K56: 2026-09-16 | L56: Celda heredada FP-180 (2026-09-16): el valor 2 proviene de la investigacion del escenario E1 y no cuenta con evidencia propia de E5. Segun FP-177 el indicador V1 depende del escenario, por lo que pasa a NE (no evidenciado, reduce cobertura) hasta investigarlo. La evidencia y la fuente originales se conservan como referencia del escenario de origen.
A57: E5 | B57: Cloud nativa | C57: AWS Cost Explorer | D57: Visibilidad | E57: V2 | F57: ¿Permite rastrear un total hasta registros o fuente de facturación? | G57: 2 | H57: Oficial | I57: El Cost and Usage Report (CUR) entrega detalle por línea de facturación y "reconciles with the total charges on your Bills page", permitiendo rastrear un total hasta el registro fuente. | J57: https://docs.aws.amazon.com/cur/latest/userguide/what-is-cur.html | K57: 2026-09-16
A58: E5 | B58: Cloud nativa | C58: AWS Cost Explorer | D58: Asignacion | E58: A1 | F58: ¿Calcula gasto asignado/no asignado por responsable, centro o entidad? | G58: NE | H58: Pendiente | I58: Cost Categories es "a cost allocation service to help you map your AWS costs to your unique internal business structures" mediante reglas; expone una categoría de costos no mapeados. | J58: https://docs.aws.amazon.com/awsaccountbilling/latest/aboutv2/manage-cost-categories.html | K58: 2026-09-16 | L58: Contexto académico (no usado para puntuar): Manurung y Aji (2025) entrevistaron a 6 organizaciones que usan explícitamente esta herramienta ("We use AWS Cost Explorer, cast.ai, and infracost.", P2) y encontraron que el 100% (6/6) carece de showback/chargeback pese a ello ("[Gap] Cost ownership is centralized, no showback/chargeback", Tabla 4). Es evidencia de brecha organizacional, no de una limitación verificada del producto; se deja como insumo para el análisis de sensibilidad/limitaciones de FP-181, no como ajuste de este puntaje. | Celda heredada FP-180 (2026-09-16): el valor 2 proviene de la investigacion del escenario E1 y no cuenta con evidencia propia de E5. Segun FP-177 el indicador A1 depende del escenario, por lo que pasa a NE (no evidenciado, reduce cobertura) hasta investigarlo. La evidencia y la fuente originales se conservan como referencia del escenario de origen.
A59: E5 | B59: Cloud nativa | C59: AWS Cost Explorer | D59: Asignacion | E59: A2 | F59: ¿Explicita y aplica reglas para costo compartido/multi-tenant? | G59: NE | H59: Pendiente | I59: Cost Categories admite "Splitting charges within cost categories" (split charge rules) para repartir costos compartidos entre categorías/equipos. | J59: https://docs.aws.amazon.com/awsaccountbilling/latest/aboutv2/manage-cost-categories.html | K59: 2026-09-16 | L59: Celda heredada FP-180 (2026-09-16): el valor 2 proviene de la investigacion del escenario E1 y no cuenta con evidencia propia de E5. Segun FP-177 el indicador A2 depende del escenario, por lo que pasa a NE (no evidenciado, reduce cobertura) hasta investigarlo. La evidencia y la fuente originales se conservan como referencia del escenario de origen.
A60: E5 | B60: Cloud nativa | C60: AWS Cost Explorer | D60: Optimizacion | E60: O1 | F60: ¿Detecta desperdicio, rightsizing o compromiso relevante al escenario? | G60: NE | H60: Pendiente | I60: Cost Explorer conserva una vista propia de "rightsizing recommendations" (principalmente EC2), de alcance más acotado que Cost Optimization Hub. | J60: https://docs.aws.amazon.com/cost-management/latest/userguide/ce-rightsizing.html | K60: 2026-09-16 | L60: Celda heredada FP-180 (2026-09-16): el valor 1 proviene de la investigacion del escenario E1 y no cuenta con evidencia propia de E5. Segun FP-177 el indicador O1 depende del escenario, por lo que pasa a NE (no evidenciado, reduce cobertura) hasta investigarlo. La evidencia y la fuente originales se conservan como referencia del escenario de origen.
A61: E5 | B61: Cloud nativa | C61: AWS Cost Explorer | D61: Optimizacion | E61: O2 | F61: ¿Explica supuesto/impacto y permite seguir una recomendación? | G61: 1 | H61: Oficial | I61: La vista de rightsizing de Cost Explorer muestra el ahorro estimado por recomendación, sin el ciclo de seguimiento/objetivos que sí documenta Cost Optimization Hub. | J61: https://docs.aws.amazon.com/cost-management/latest/userguide/ce-rightsizing.html | K61: 2026-09-16
A62: E5 | B62: Cloud nativa | C62: AWS Cost Explorer | D62: Automatizacion | E62: AU1 | F62: ¿Ejecuta o bloquea acciones/políticas de costo con control verificable? | G62: NE | H62: Pendiente | I62: AWS Budgets puede ejecutar "budget actions" (política IAM Deny, SCP, detener instancias EC2/RDS) "either automatically or after your manual approval". | J62: https://docs.aws.amazon.com/cost-management/latest/userguide/budgets-controls.html | K62: 2026-09-16 | L62: Celda heredada FP-180 (2026-09-16): el valor 2 proviene de la investigacion del escenario E1 y no cuenta con evidencia propia de E5. Segun FP-177 el indicador AU1 depende del escenario, por lo que pasa a NE (no evidenciado, reduce cobertura) hasta investigarlo. La evidencia y la fuente originales se conservan como referencia del escenario de origen.
A63: E5 | B63: Cloud nativa | C63: AWS Cost Explorer | D63: Automatizacion | E63: AU2 | F63: ¿Ofrece aprobación, reversión, registro o límites antes de actuar? | G63: 2 | H63: Oficial | I63: Las budget actions permiten exigir aprobación manual antes de ejecutarse. La documentación revisada no detalla registro de auditoría ni mecanismo de reversión explícito (limitación registrada). | J63: https://docs.aws.amazon.com/cost-management/latest/userguide/budgets-controls.html | K63: 2026-09-16
A64: E5 | B64: Cloud nativa | C64: AWS Cost Explorer | D64: Multicloud | E64: M1 | F64: ¿Consolida al menos dos proveedores bajo el mismo esquema declarado? | G64: 0 | H64: Oficial | I64: Cost Explorer y el CUR cubren exclusivamente cuentas y facturación de AWS; no ingieren ni consolidan datos de Azure o GCP. | J64: https://docs.aws.amazon.com/cur/latest/userguide/what-is-cur.html | K64: 2026-09-16
A65: E5 | B65: Cloud nativa | C65: AWS Cost Explorer | D65: Multicloud | E65: M2 | F65: ¿Hace visibles proveedor, cobertura y diferencias semánticas? | G65: 0 | H65: Oficial | I65: Al no consolidar otros proveedores, la herramienta no expone diferencias de cobertura o semántica entre nubes. | J65: https://docs.aws.amazon.com/cur/latest/userguide/what-is-cur.html | K65: 2026-09-16
A66: E5 | B66: Cloud nativa | C66: AWS Cost Explorer | D66: Integracion | E66: I1 | F66: ¿Integra datos requeridos (facturación, uso, clúster o IaC) del escenario? | G66: NE | H66: Pendiente | I66: El CUR/la API de Cost Explorer ingieren datos de facturación y uso de forma automatizada; para EKS, "Split Cost Allocation Data" añade métricas de clúster a nivel de pod/namespace al CUR. | J66: https://aws.amazon.com/about-aws/whats-new/2024/04/aws-split-cost-allocation-data-amazon-eks/ | K66: 2026-09-16 | L66: Celda heredada FP-180 (2026-09-16): el valor 2 proviene de la investigacion del escenario E1 y no cuenta con evidencia propia de E5. Segun FP-177 el indicador I1 depende del escenario, por lo que pasa a NE (no evidenciado, reduce cobertura) hasta investigarlo. La evidencia y la fuente originales se conservan como referencia del escenario de origen.
A67: E5 | B67: Cloud nativa | C67: AWS Cost Explorer | D67: Integracion | E67: I2 | F67: ¿Se integra con el flujo de trabajo relevante (alerta, ticket, CI/CD o reporte)? | G67: NE | H67: Pendiente | I67: AWS Cost Anomaly Detection y Budgets envían alertas (p. ej., a SNS/correo) integradas a un flujo operativo de revisión. | J67: https://docs.aws.amazon.com/cost-management/latest/userguide/budgets-controls.html | K67: 2026-09-16 | L67: Celda heredada FP-180 (2026-09-16): el valor 2 proviene de la investigacion del escenario E1 y no cuenta con evidencia propia de E5. Segun FP-177 el indicador I2 depende del escenario, por lo que pasa a NE (no evidenciado, reduce cobertura) hasta investigarlo. La evidencia y la fuente originales se conservan como referencia del escenario de origen.
A68: E5 | B68: Cloud nativa | C68: AWS Cost Explorer | D68: Adopcion | E68: AD1 | F68: ¿Soporta acceso/entrega para los roles del escenario? | G68: NE | H68: Pendiente | I68: El acceso a Cost Explorer/Budgets se controla mediante políticas de IAM por usuario/rol (control de acceso estándar de AWS Billing). | J68: https://docs.aws.amazon.com/awsaccountbilling/latest/aboutv2/cost-alloc-tags.html | K68: 2026-09-16 | L68: Celda heredada FP-180 (2026-09-16): el valor 2 proviene de la investigacion del escenario E1 y no cuenta con evidencia propia de E5. Segun FP-177 el indicador AD1 depende del escenario, por lo que pasa a NE (no evidenciado, reduce cobertura) hasta investigarlo. La evidencia y la fuente originales se conservan como referencia del escenario de origen.
A69: E5 | B69: Cloud nativa | C69: AWS Cost Explorer | D69: Adopcion | E69: AD2 | F69: ¿Ofrece guías, ownership o mecanismos de seguimiento para uso sostenido? | G69: 2 | H69: Oficial | I69: AWS publica guías oficiales de adopción, entre ellas el whitepaper de mejores prácticas de etiquetado y estrategia de asignación de costos. | J69: https://docs.aws.amazon.com/whitepapers/latest/tagging-best-practices/building-a-cost-allocation-strategy.html | K69: 2026-09-16 | L69: Contexto académico (no usado para puntuar): Manurung y Aji (2025) entrevistaron a 6 organizaciones que usan explícitamente esta herramienta ("We use AWS Cost Explorer, cast.ai, and infracost.", P2) y encontraron que el 100% (6/6) carece de showback/chargeback pese a ello ("[Gap] Cost ownership is centralized, no showback/chargeback", Tabla 4). Es evidencia de brecha organizacional, no de una limitación verificada del producto; se deja como insumo para el análisis de sensibilidad/limitaciones de FP-181, no como ajuste de este puntaje.
A70: E5 | B70: Cloud nativa | C70: AWS Cost Explorer | D70: Precio | E70: P1 | F70: ¿Expone precio, moneda, región, unidad, período y supuestos relevantes? | G70: 2 | H70: Oficial | I70: El CUR y los Data Exports FOCUS 1.0/1.2 exponen moneda, período, servicio y columnas estandarizadas de costo (ListCost, ContractedCost, BilledCost, EffectiveCost). | J70: https://aws.amazon.com/about-aws/whats-new/2024/11/aws-billing-cost-management-data-exports-focus-1-0 | K70: 2026-09-16
A71: E5 | B71: Cloud nativa | C71: AWS Cost Explorer | D71: Precio | E71: P2 | F71: ¿Permite estimar o comparar componentes sin ocultar límites de equivalencia? | G71: NE | H71: Pendiente | I71: Cost Explorer ofrece pronóstico de costo futuro basado en tendencia histórica; no es una calculadora de estimación de componentes antes del despliegue (esa función es de AWS Pricing Calculator, evaluada aparte). | J71: https://docs.aws.amazon.com/cost-management/latest/userguide/ce-what-is.html | K71: 2026-09-16 | L71: Celda heredada FP-180 (2026-09-16): el valor 1 proviene de la investigacion del escenario E1 y no cuenta con evidencia propia de E5. Segun FP-177 el indicador P2 depende del escenario, por lo que pasa a NE (no evidenciado, reduce cobertura) hasta investigarlo. La evidencia y la fuente originales se conservan como referencia del escenario de origen.
A72: E5 | B72: Cloud nativa | C72: AWS Cost Explorer | D72: Dependencia | E72: D1 | F72: ¿Exporta datos/resultados en formato utilizable y documentado? | G72: 2 | H72: Oficial | I72: El CUR exporta a S3 en CSV/Parquet y, desde 2024-2025, también en el estándar abierto FOCUS 1.0/1.2. | J72: https://aws.amazon.com/about-aws/whats-new/2024/11/aws-billing-cost-management-data-exports-focus-1-0 | K72: 2026-09-16
A73: E5 | B73: Cloud nativa | C73: AWS Cost Explorer | D73: Dependencia | E73: D2 | F73: ¿Documenta dependencias propietarias y un camino de salida/configuración reversible? | G73: 1 | H73: Oficial | I73: No se encontró documentación específica de un "camino de salida" dedicado. El riesgo de dependencia es menor porque los datos son exportables en formato estándar (FOCUS) y el servicio no tiene costo propio, pero no hay guía de reversibilidad dedicada (limitación registrada). | J73: https://aws.amazon.com/about-aws/whats-new/2024/11/aws-billing-cost-management-data-exports-focus-1-0 | K73: 2026-09-16
A74: E6 | B74: Cloud nativa | C74: AWS Cost Explorer | D74: Visibilidad | E74: V1 | F74: ¿Desagrega costo y uso por cuenta/proyecto, servicio y período? | G74: NE | H74: Pendiente | I74: Las etiquetas de asignación de costos y las Cost Categories desglosan el gasto por cuenta/proyecto y servicio, y son filtrables en Cost Explorer ("You can also use tags to filter views in Cost Explorer"). La actualización tiene hasta 24 h de latencia, no es en tiempo real. | J74: https://docs.aws.amazon.com/awsaccountbilling/latest/aboutv2/cost-alloc-tags.html | K74: 2026-09-16 | L74: Celda heredada FP-180 (2026-09-16): el valor 2 proviene de la investigacion del escenario E1 y no cuenta con evidencia propia de E6. Segun FP-177 el indicador V1 depende del escenario, por lo que pasa a NE (no evidenciado, reduce cobertura) hasta investigarlo. La evidencia y la fuente originales se conservan como referencia del escenario de origen.
A75: E6 | B75: Cloud nativa | C75: AWS Cost Explorer | D75: Visibilidad | E75: V2 | F75: ¿Permite rastrear un total hasta registros o fuente de facturación? | G75: 2 | H75: Oficial | I75: El Cost and Usage Report (CUR) entrega detalle por línea de facturación y "reconciles with the total charges on your Bills page", permitiendo rastrear un total hasta el registro fuente. | J75: https://docs.aws.amazon.com/cur/latest/userguide/what-is-cur.html | K75: 2026-09-16
A76: E6 | B76: Cloud nativa | C76: AWS Cost Explorer | D76: Asignacion | E76: A1 | F76: ¿Calcula gasto asignado/no asignado por responsable, centro o entidad? | G76: NE | H76: Pendiente | I76: Cost Categories es "a cost allocation service to help you map your AWS costs to your unique internal business structures" mediante reglas; expone una categoría de costos no mapeados. | J76: https://docs.aws.amazon.com/awsaccountbilling/latest/aboutv2/manage-cost-categories.html | K76: 2026-09-16 | L76: Contexto académico (no usado para puntuar): Manurung y Aji (2025) entrevistaron a 6 organizaciones que usan explícitamente esta herramienta ("We use AWS Cost Explorer, cast.ai, and infracost.", P2) y encontraron que el 100% (6/6) carece de showback/chargeback pese a ello ("[Gap] Cost ownership is centralized, no showback/chargeback", Tabla 4). Es evidencia de brecha organizacional, no de una limitación verificada del producto; se deja como insumo para el análisis de sensibilidad/limitaciones de FP-181, no como ajuste de este puntaje. | Celda heredada FP-180 (2026-09-16): el valor 2 proviene de la investigacion del escenario E1 y no cuenta con evidencia propia de E6. Segun FP-177 el indicador A1 depende del escenario, por lo que pasa a NE (no evidenciado, reduce cobertura) hasta investigarlo. La evidencia y la fuente originales se conservan como referencia del escenario de origen.
A77: E6 | B77: Cloud nativa | C77: AWS Cost Explorer | D77: Asignacion | E77: A2 | F77: ¿Explicita y aplica reglas para costo compartido/multi-tenant? | G77: NE | H77: Pendiente | I77: Cost Categories admite "Splitting charges within cost categories" (split charge rules) para repartir costos compartidos entre categorías/equipos. | J77: https://docs.aws.amazon.com/awsaccountbilling/latest/aboutv2/manage-cost-categories.html | K77: 2026-09-16 | L77: Celda heredada FP-180 (2026-09-16): el valor 2 proviene de la investigacion del escenario E1 y no cuenta con evidencia propia de E6. Segun FP-177 el indicador A2 depende del escenario, por lo que pasa a NE (no evidenciado, reduce cobertura) hasta investigarlo. La evidencia y la fuente originales se conservan como referencia del escenario de origen.
A78: E6 | B78: Cloud nativa | C78: AWS Cost Explorer | D78: Optimizacion | E78: O1 | F78: ¿Detecta desperdicio, rightsizing o compromiso relevante al escenario? | G78: NE | H78: Pendiente | I78: Cost Explorer conserva una vista propia de "rightsizing recommendations" (principalmente EC2), de alcance más acotado que Cost Optimization Hub. | J78: https://docs.aws.amazon.com/cost-management/latest/userguide/ce-rightsizing.html | K78: 2026-09-16 | L78: Celda heredada FP-180 (2026-09-16): el valor 1 proviene de la investigacion del escenario E1 y no cuenta con evidencia propia de E6. Segun FP-177 el indicador O1 depende del escenario, por lo que pasa a NE (no evidenciado, reduce cobertura) hasta investigarlo. La evidencia y la fuente originales se conservan como referencia del escenario de origen.
A79: E6 | B79: Cloud nativa | C79: AWS Cost Explorer | D79: Optimizacion | E79: O2 | F79: ¿Explica supuesto/impacto y permite seguir una recomendación? | G79: 1 | H79: Oficial | I79: La vista de rightsizing de Cost Explorer muestra el ahorro estimado por recomendación, sin el ciclo de seguimiento/objetivos que sí documenta Cost Optimization Hub. | J79: https://docs.aws.amazon.com/cost-management/latest/userguide/ce-rightsizing.html | K79: 2026-09-16
A80: E6 | B80: Cloud nativa | C80: AWS Cost Explorer | D80: Automatizacion | E80: AU1 | F80: ¿Ejecuta o bloquea acciones/políticas de costo con control verificable? | G80: NE | H80: Pendiente | I80: AWS Budgets puede ejecutar "budget actions" (política IAM Deny, SCP, detener instancias EC2/RDS) "either automatically or after your manual approval". | J80: https://docs.aws.amazon.com/cost-management/latest/userguide/budgets-controls.html | K80: 2026-09-16 | L80: Celda heredada FP-180 (2026-09-16): el valor 2 proviene de la investigacion del escenario E1 y no cuenta con evidencia propia de E6. Segun FP-177 el indicador AU1 depende del escenario, por lo que pasa a NE (no evidenciado, reduce cobertura) hasta investigarlo. La evidencia y la fuente originales se conservan como referencia del escenario de origen.
A81: E6 | B81: Cloud nativa | C81: AWS Cost Explorer | D81: Automatizacion | E81: AU2 | F81: ¿Ofrece aprobación, reversión, registro o límites antes de actuar? | G81: 2 | H81: Oficial | I81: Las budget actions permiten exigir aprobación manual antes de ejecutarse. La documentación revisada no detalla registro de auditoría ni mecanismo de reversión explícito (limitación registrada). | J81: https://docs.aws.amazon.com/cost-management/latest/userguide/budgets-controls.html | K81: 2026-09-16
A82: E6 | B82: Cloud nativa | C82: AWS Cost Explorer | D82: Multicloud | E82: M1 | F82: ¿Consolida al menos dos proveedores bajo el mismo esquema declarado? | G82: 0 | H82: Oficial | I82: Cost Explorer y el CUR cubren exclusivamente cuentas y facturación de AWS; no ingieren ni consolidan datos de Azure o GCP. | J82: https://docs.aws.amazon.com/cur/latest/userguide/what-is-cur.html | K82: 2026-09-16
A83: E6 | B83: Cloud nativa | C83: AWS Cost Explorer | D83: Multicloud | E83: M2 | F83: ¿Hace visibles proveedor, cobertura y diferencias semánticas? | G83: 0 | H83: Oficial | I83: Al no consolidar otros proveedores, la herramienta no expone diferencias de cobertura o semántica entre nubes. | J83: https://docs.aws.amazon.com/cur/latest/userguide/what-is-cur.html | K83: 2026-09-16
A84: E6 | B84: Cloud nativa | C84: AWS Cost Explorer | D84: Integracion | E84: I1 | F84: ¿Integra datos requeridos (facturación, uso, clúster o IaC) del escenario? | G84: NE | H84: Pendiente | I84: El CUR/la API de Cost Explorer ingieren datos de facturación y uso de forma automatizada; para EKS, "Split Cost Allocation Data" añade métricas de clúster a nivel de pod/namespace al CUR. | J84: https://aws.amazon.com/about-aws/whats-new/2024/04/aws-split-cost-allocation-data-amazon-eks/ | K84: 2026-09-16 | L84: Celda heredada FP-180 (2026-09-16): el valor 2 proviene de la investigacion del escenario E1 y no cuenta con evidencia propia de E6. Segun FP-177 el indicador I1 depende del escenario, por lo que pasa a NE (no evidenciado, reduce cobertura) hasta investigarlo. La evidencia y la fuente originales se conservan como referencia del escenario de origen.
A85: E6 | B85: Cloud nativa | C85: AWS Cost Explorer | D85: Integracion | E85: I2 | F85: ¿Se integra con el flujo de trabajo relevante (alerta, ticket, CI/CD o reporte)? | G85: NE | H85: Pendiente | I85: AWS Cost Anomaly Detection y Budgets envían alertas (p. ej., a SNS/correo) integradas a un flujo operativo de revisión. | J85: https://docs.aws.amazon.com/cost-management/latest/userguide/budgets-controls.html | K85: 2026-09-16 | L85: Celda heredada FP-180 (2026-09-16): el valor 2 proviene de la investigacion del escenario E1 y no cuenta con evidencia propia de E6. Segun FP-177 el indicador I2 depende del escenario, por lo que pasa a NE (no evidenciado, reduce cobertura) hasta investigarlo. La evidencia y la fuente originales se conservan como referencia del escenario de origen.
A86: E6 | B86: Cloud nativa | C86: AWS Cost Explorer | D86: Adopcion | E86: AD1 | F86: ¿Soporta acceso/entrega para los roles del escenario? | G86: NE | H86: Pendiente | I86: El acceso a Cost Explorer/Budgets se controla mediante políticas de IAM por usuario/rol (control de acceso estándar de AWS Billing). | J86: https://docs.aws.amazon.com/awsaccountbilling/latest/aboutv2/cost-alloc-tags.html | K86: 2026-09-16 | L86: Celda heredada FP-180 (2026-09-16): el valor 2 proviene de la investigacion del escenario E1 y no cuenta con evidencia propia de E6. Segun FP-177 el indicador AD1 depende del escenario, por lo que pasa a NE (no evidenciado, reduce cobertura) hasta investigarlo. La evidencia y la fuente originales se conservan como referencia del escenario de origen.
A87: E6 | B87: Cloud nativa | C87: AWS Cost Explorer | D87: Adopcion | E87: AD2 | F87: ¿Ofrece guías, ownership o mecanismos de seguimiento para uso sostenido? | G87: 2 | H87: Oficial | I87: AWS publica guías oficiales de adopción, entre ellas el whitepaper de mejores prácticas de etiquetado y estrategia de asignación de costos. | J87: https://docs.aws.amazon.com/whitepapers/latest/tagging-best-practices/building-a-cost-allocation-strategy.html | K87: 2026-09-16 | L87: Contexto académico (no usado para puntuar): Manurung y Aji (2025) entrevistaron a 6 organizaciones que usan explícitamente esta herramienta ("We use AWS Cost Explorer, cast.ai, and infracost.", P2) y encontraron que el 100% (6/6) carece de showback/chargeback pese a ello ("[Gap] Cost ownership is centralized, no showback/chargeback", Tabla 4). Es evidencia de brecha organizacional, no de una limitación verificada del producto; se deja como insumo para el análisis de sensibilidad/limitaciones de FP-181, no como ajuste de este puntaje.
A88: E6 | B88: Cloud nativa | C88: AWS Cost Explorer | D88: Precio | E88: P1 | F88: ¿Expone precio, moneda, región, unidad, período y supuestos relevantes? | G88: 2 | H88: Oficial | I88: El CUR y los Data Exports FOCUS 1.0/1.2 exponen moneda, período, servicio y columnas estandarizadas de costo (ListCost, ContractedCost, BilledCost, EffectiveCost). | J88: https://aws.amazon.com/about-aws/whats-new/2024/11/aws-billing-cost-management-data-exports-focus-1-0 | K88: 2026-09-16
A89: E6 | B89: Cloud nativa | C89: AWS Cost Explorer | D89: Precio | E89: P2 | F89: ¿Permite estimar o comparar componentes sin ocultar límites de equivalencia? | G89: NE | H89: Pendiente | I89: Cost Explorer ofrece pronóstico de costo futuro basado en tendencia histórica; no es una calculadora de estimación de componentes antes del despliegue (esa función es de AWS Pricing Calculator, evaluada aparte). | J89: https://docs.aws.amazon.com/cost-management/latest/userguide/ce-what-is.html | K89: 2026-09-16 | L89: Celda heredada FP-180 (2026-09-16): el valor 1 proviene de la investigacion del escenario E1 y no cuenta con evidencia propia de E6. Segun FP-177 el indicador P2 depende del escenario, por lo que pasa a NE (no evidenciado, reduce cobertura) hasta investigarlo. La evidencia y la fuente originales se conservan como referencia del escenario de origen.
A90: E6 | B90: Cloud nativa | C90: AWS Cost Explorer | D90: Dependencia | E90: D1 | F90: ¿Exporta datos/resultados en formato utilizable y documentado? | G90: 2 | H90: Oficial | I90: El CUR exporta a S3 en CSV/Parquet y, desde 2024-2025, también en el estándar abierto FOCUS 1.0/1.2. | J90: https://aws.amazon.com/about-aws/whats-new/2024/11/aws-billing-cost-management-data-exports-focus-1-0 | K90: 2026-09-16
A91: E6 | B91: Cloud nativa | C91: AWS Cost Explorer | D91: Dependencia | E91: D2 | F91: ¿Documenta dependencias propietarias y un camino de salida/configuración reversible? | G91: 1 | H91: Oficial | I91: No se encontró documentación específica de un "camino de salida" dedicado. El riesgo de dependencia es menor porque los datos son exportables en formato estándar (FOCUS) y el servicio no tiene costo propio, pero no hay guía de reversibilidad dedicada (limitación registrada). | J91: https://aws.amazon.com/about-aws/whats-new/2024/11/aws-billing-cost-management-data-exports-focus-1-0 | K91: 2026-09-16
A92: E1 | B92: Cloud nativa | C92: AWS Cost Optimization Hub | D92: Visibilidad | E92: V1 | F92: ¿Desagrega costo y uso por cuenta/proyecto, servicio y período? | G92: 0 | H92: Oficial (ausencia verificada) | I92: Cost Optimization Hub no ofrece un desglose general de costo/uso por cuenta-servicio-período; su función documentada es consolidar y priorizar recomendaciones, no la visibilidad general de gasto (esa función corresponde a Cost Explorer). | J92: https://docs.aws.amazon.com/cost-management/latest/userguide/cost-optimization-hub.html | K92: 2026-09-16 | L92: Corrección de alcance FP-180 (2026-09-16): el valor pasa de NA a 0. La justificación registrada afirma una ausencia verificada contra documentación oficial, no una inaplicabilidad: en FP-177 eso corresponde al valor 0, no a NA. La evidencia y la fuente originales no se modifican.
A93: E1 | B93: Cloud nativa | C93: AWS Cost Optimization Hub | D93: Visibilidad | E93: V2 | F93: ¿Permite rastrear un total hasta registros o fuente de facturación? | G93: 0 | H93: Oficial (ausencia verificada) | I93: Mismo alcance de diseño que V1: no es una herramienta de trazabilidad de gasto. | J93: https://docs.aws.amazon.com/cost-management/latest/userguide/cost-optimization-hub.html | K93: 2026-09-16 | L93: Corrección de alcance FP-180 (2026-09-16): el valor pasa de NA a 0. La justificación registrada afirma una ausencia verificada contra documentación oficial, no una inaplicabilidad: en FP-177 eso corresponde al valor 0, no a NA. La evidencia y la fuente originales no se modifican.
A94: E1 | B94: Cloud nativa | C94: AWS Cost Optimization Hub | D94: Asignacion | E94: A1 | F94: ¿Calcula gasto asignado/no asignado por responsable, centro o entidad? | G94: 0 | H94: Oficial (ausencia verificada) | I94: No calcula asignación de gasto por responsable/centro de costo; opera sobre recomendaciones de optimización, no sobre asignación. | J94: https://docs.aws.amazon.com/cost-management/latest/userguide/cost-optimization-hub.html | K94: 2026-09-16 | L94: Corrección de alcance FP-180 (2026-09-16): el valor pasa de NA a 0. La justificación registrada afirma una ausencia verificada contra documentación oficial, no una inaplicabilidad: en FP-177 eso corresponde al valor 0, no a NA. La evidencia y la fuente originales no se modifican.
A95: E1 | B95: Cloud nativa | C95: AWS Cost Optimization Hub | D95: Asignacion | E95: A2 | F95: ¿Explicita y aplica reglas para costo compartido/multi-tenant? | G95: 0 | H95: Oficial (ausencia verificada) | I95: No define reglas de reparto de costo compartido. | J95: https://docs.aws.amazon.com/cost-management/latest/userguide/cost-optimization-hub.html | K95: 2026-09-16 | L95: Corrección de alcance FP-180 (2026-09-16): el valor pasa de NA a 0. La justificación registrada afirma una ausencia verificada contra documentación oficial, no una inaplicabilidad: en FP-177 eso corresponde al valor 0, no a NA. La evidencia y la fuente originales no se modifican.
A96: E1 | B96: Cloud nativa | C96: AWS Cost Optimization Hub | D96: Optimizacion | E96: O1 | F96: ¿Detecta desperdicio, rightsizing o compromiso relevante al escenario? | G96: 2 | H96: Oficial | I96: "It makes recommendations on resource rightsizing, idle resource deletion, Savings Plans, and Reserved Instances" y permite "filtering, sorting, and grouping" para priorizar oportunidades. | J96: https://docs.aws.amazon.com/cost-management/latest/userguide/cost-optimization-hub.html | K96: 2026-09-16
A97: E1 | B97: Cloud nativa | C97: AWS Cost Optimization Hub | D97: Optimizacion | E97: O2 | F97: ¿Explica supuesto/impacto y permite seguir una recomendación? | G97: 2 | H97: Oficial | I97: "Quantify estimated savings that incorporate your AWS pricing and discounts" y "track progress to maximize your return on cloud investments", con posibilidad de fijar objetivos de ahorro. | J97: https://docs.aws.amazon.com/cost-management/latest/userguide/cost-optimization-hub.html | K97: 2026-09-16
A98: E1 | B98: Cloud nativa | C98: AWS Cost Optimization Hub | D98: Automatizacion | E98: AU1 | F98: ¿Ejecuta o bloquea acciones/políticas de costo con control verificable? | G98: 0 | H98: Oficial (ausencia verificada) | I98: Cost Optimization Hub recomienda pero no ejecuta acciones; la ejecución/control automatizado corresponde a AWS Budgets (evaluado dentro de Cost Explorer en este trabajo). | J98: https://docs.aws.amazon.com/cost-management/latest/userguide/cost-optimization-hub.html | K98: 2026-09-16 | L98: Corrección de alcance FP-180 (2026-09-16): el valor pasa de NA a 0. La justificación registrada afirma una ausencia verificada contra documentación oficial, no una inaplicabilidad: en FP-177 eso corresponde al valor 0, no a NA. La evidencia y la fuente originales no se modifican.
A99: E1 | B99: Cloud nativa | C99: AWS Cost Optimization Hub | D99: Automatizacion | E99: AU2 | F99: ¿Ofrece aprobación, reversión, registro o límites antes de actuar? | G99: NA | H99: Justificación de alcance | I99: Mismo alcance de diseño que AU1: no ejecuta, por lo que no aplica evaluar salvaguardas de ejecución. | J99: https://docs.aws.amazon.com/cost-management/latest/userguide/cost-optimization-hub.html | K99: 2026-09-16
A100: E1 | B100: Cloud nativa | C100: AWS Cost Optimization Hub | D100: Multicloud | E100: M1 | F100: ¿Consolida al menos dos proveedores bajo el mismo esquema declarado? | G100: 0 | H100: Oficial (ausencia verificada) | I100: Cubre exclusivamente cuentas de AWS; no está diseñada para consolidar Azure/GCP. | J100: https://docs.aws.amazon.com/cost-management/latest/userguide/cost-optimization-hub.html | K100: 2026-09-16 | L100: Corrección de alcance FP-180 (2026-09-16): el valor pasa de NA a 0. La justificación registrada afirma una ausencia verificada contra documentación oficial, no una inaplicabilidad: en FP-177 eso corresponde al valor 0, no a NA. La evidencia y la fuente originales no se modifican.
...

Sheet Calculo
A1: Escenario | B1: Categoria | C1: Producto | D1: Visibilidad - Aplicable | E1: Visibilidad - Evidenciado | F1: Visibilidad - C_c | G1: Asignación - Aplicable | H1: Asignación - Evidenciado | I1: Asignación - C_c | J1: Optimización - Aplicable | K1: Optimización - Evidenciado | L1: Optimización - C_c | M1: Automatización - Aplicable | N1: Automatización - Evidenciado | O1: Automatización - C_c | P1: Multicloud - Aplicable | Q1: Multicloud - Evidenciado | R1: Multicloud - C_c | S1: Integración - Aplicable | T1: Integración - Evidenciado | U1: Integración - C_c | V1: Adopción - Aplicable | W1: Adopción - Evidenciado | X1: Adopción - C_c | Y1: Precio - Aplicable | Z1: Precio - Evidenciado | AA1: Precio - C_c | AB1: Dependencia - Aplicable | AC1: Dependencia - Evidenciado | AD1: Dependencia - C_c | AE1: Cobertura base (%) | AF1: Cobertura sensibilidad (%) | AG1: S linea base (0-100) | AH1: S sensibilidad (0-100) | AI1: Banda linea base | AJ1: Banda sensibilidad | AK1: Criterios criticos incumplidos (C_c<1)
A2: E1 | B2: Cloud nativa | C2: AWS Cost Explorer | D2: =IF(COUNTIFS(Puntuacion!$A:$A,$A2,Puntuacion!$C:$C,$C2,Puntuacion!$D:$D,"Visibilidad",Puntuacion!$G:$G,"<>NA")>0,1,0) | E2: =IF(AND(D2=1,COUNTIFS(Puntuacion!$A:$A,$A2,Puntuacion!$C:$C,$C2,Puntuacion!$D:$D,"Visibilidad",Puntuacion!$G:$G,"NE")=0),1,0) | F2: =IF(D2=0,"NA",IF(E2=0,"NE",AVERAGEIFS(Puntuacion!$G:$G,Puntuacion!$A:$A,$A2,Puntuacion!$C:$C,$C2,Puntuacion!$D:$D,"Visibilidad",Puntuacion!$G:$G,"<>NA",Puntuacion!$G:$G,"<>NE"))) | G2: =IF(COUNTIFS(Puntuacion!$A:$A,$A2,Puntuacion!$C:$C,$C2,Puntuacion!$D:$D,"Asignacion",Puntuacion!$G:$G,"<>NA")>0,1,0) | H2: =IF(AND(G2=1,COUNTIFS(Puntuacion!$A:$A,$A2,Puntuacion!$C:$C,$C2,Puntuacion!$D:$D,"Asignacion",Puntuacion!$G:$G,"NE")=0),1,0) | I2: =IF(G2=0,"NA",IF(H2=0,"NE",AVERAGEIFS(Puntuacion!$G:$G,Puntuacion!$A:$A,$A2,Puntuacion!$C:$C,$C2,Puntuacion!$D:$D,"Asignacion",Puntuacion!$G:$G,"<>NA",Puntuacion!$G:$G,"<>NE"))) | J2: =IF(COUNTIFS(Puntuacion!$A:$A,$A2,Puntuacion!$C:$C,$C2,Puntuacion!$D:$D,"Optimizacion",Puntuacion!$G:$G,"<>NA")>0,1,0) | K2: =IF(AND(J2=1,COUNTIFS(Puntuacion!$A:$A,$A2,Puntuacion!$C:$C,$C2,Puntuacion!$D:$D,"Optimizacion",Puntuacion!$G:$G,"NE")=0),1,0) | L2: =IF(J2=0,"NA",IF(K2=0,"NE",AVERAGEIFS(Puntuacion!$G:$G,Puntuacion!$A:$A,$A2,Puntuacion!$C:$C,$C2,Puntuacion!$D:$D,"Optimizacion",Puntuacion!$G:$G,"<>NA",Puntuacion!$G:$G,"<>NE"))) | M2: =IF(COUNTIFS(Puntuacion!$A:$A,$A2,Puntuacion!$C:$C,$C2,Puntuacion!$D:$D,"Automatizacion",Puntuacion!$G:$G,"<>NA")>0,1,0) | N2: =IF(AND(M2=1,COUNTIFS(Puntuacion!$A:$A,$A2,Puntuacion!$C:$C,$C2,Puntuacion!$D:$D,"Automatizacion",Puntuacion!$G:$G,"NE")=0),1,0) | O2: =IF(M2=0,"NA",IF(N2=0,"NE",AVERAGEIFS(Puntuacion!$G:$G,Puntuacion!$A:$A,$A2,Puntuacion!$C:$C,$C2,Puntuacion!$D:$D,"Automatizacion",Puntuacion!$G:$G,"<>NA",Puntuacion!$G:$G,"<>NE"))) | P2: =IF(COUNTIFS(Puntuacion!$A:$A,$A2,Puntuacion!$C:$C,$C2,Puntuacion!$D:$D,"Multicloud",Puntuacion!$G:$G,"<>NA")>0,1,0) | Q2: =IF(AND(P2=1,COUNTIFS(Puntuacion!$A:$A,$A2,Puntuacion!$C:$C,$C2,Puntuacion!$D:$D,"Multicloud",Puntuacion!$G:$G,"NE")=0),1,0) | R2: =IF(P2=0,"NA",IF(Q2=0,"NE",AVERAGEIFS(Puntuacion!$G:$G,Puntuacion!$A:$A,$A2,Puntuacion!$C:$C,$C2,Puntuacion!$D:$D,"Multicloud",Puntuacion!$G:$G,"<>NA",Puntuacion!$G:$G,"<>NE"))) | S2: =IF(COUNTIFS(Puntuacion!$A:$A,$A2,Puntuacion!$C:$C,$C2,Puntuacion!$D:$D,"Integracion",Puntuacion!$G:$G,"<>NA")>0,1,0) | T2: =IF(AND(S2=1,COUNTIFS(Puntuacion!$A:$A,$A2,Puntuacion!$C:$C,$C2,Puntuacion!$D:$D,"Integracion",Puntuacion!$G:$G,"NE")=0),1,0) | U2: =IF(S2=0,"NA",IF(T2=0,"NE",AVERAGEIFS(Puntuacion!$G:$G,Puntuacion!$A:$A,$A2,Puntuacion!$C:$C,$C2,Puntuacion!$D:$D,"Integracion",Puntuacion!$G:$G,"<>NA",Puntuacion!$G:$G,"<>NE"))) | V2: =IF(COUNTIFS(Puntuacion!$A:$A,$A2,Puntuacion!$C:$C,$C2,Puntuacion!$D:$D,"Adopcion",Puntuacion!$G:$G,"<>NA")>0,1,0) | W2: =IF(AND(V2=1,COUNTIFS(Puntuacion!$A:$A,$A2,Puntuacion!$C:$C,$C2,Puntuacion!$D:$D,"Adopcion",Puntuacion!$G:$G,"NE")=0),1,0) | X2: =IF(V2=0,"NA",IF(W2=0,"NE",AVERAGEIFS(Puntuacion!$G:$G,Puntuacion!$A:$A,$A2,Puntuacion!$C:$C,$C2,Puntuacion!$D:$D,"Adopcion",Puntuacion!$G:$G,"<>NA",Puntuacion!$G:$G,"<>NE"))) | Y2: =IF(COUNTIFS(Puntuacion!$A:$A,$A2,Puntuacion!$C:$C,$C2,Puntuacion!$D:$D,"Precio",Puntuacion!$G:$G,"<>NA")>0,1,0) | Z2: =IF(AND(Y2=1,COUNTIFS(Puntuacion!$A:$A,$A2,Puntuacion!$C:$C,$C2,Puntuacion!$D:$D,"Precio",Puntuacion!$G:$G,"NE")=0),1,0) | AA2: =IF(Y2=0,"NA",IF(Z2=0,"NE",AVERAGEIFS(Puntuacion!$G:$G,Puntuacion!$A:$A,$A2,Puntuacion!$C:$C,$C2,Puntuacion!$D:$D,"Precio",Puntuacion!$G:$G,"<>NA",Puntuacion!$G:$G,"<>NE"))) | AB2: =IF(COUNTIFS(Puntuacion!$A:$A,$A2,Puntuacion!$C:$C,$C2,Puntuacion!$D:$D,"Dependencia",Puntuacion!$G:$G,"<>NA")>0,1,0) | AC2: =IF(AND(AB2=1,COUNTIFS(Puntuacion!$A:$A,$A2,Puntuacion!$C:$C,$C2,Puntuacion!$D:$D,"Dependencia",Puntuacion!$G:$G,"NE")=0),1,0) | AD2: =IF(AB2=0,"NA",IF(AC2=0,"NE",AVERAGEIFS(Puntuacion!$G:$G,Puntuacion!$A:$A,$A2,Puntuacion!$C:$C,$C2,Puntuacion!$D:$D,"Dependencia",Puntuacion!$G:$G,"<>NA",Puntuacion!$G:$G,"<>NE"))) | AE2: =IFERROR(100*(E2*Pesos!$B$2+H2*Pesos!$B$3+K2*Pesos!$B$4+N2*Pesos!$B$5+Q2*Pesos!$B$6+T2*Pesos!$B$7+W2*Pesos!$B$8+Z2*Pesos!$B$9+AC2*Pesos!$B$10)/(D2*Pesos!$B$2+G2*Pesos!$B$3+J2*Pesos!$B$4+M2*Pesos!$B$5+P2*Pesos!$B$6+S2*Pesos!$B$7+V2*Pesos!$B$8+Y2*Pesos!$B$9+AB2*Pesos!$B$10),"Sin criterios aplicables") | AF2: =IFERROR(100*(E2*Pesos!$C$2+H2*Pesos!$C$3+K2*Pesos!$C$4+N2*Pesos!$C$5+Q2*Pesos!$C$6+T2*Pesos!$C$7+W2*Pesos!$C$8+Z2*Pesos!$C$9+AC2*Pesos!$C$10)/(D2*Pesos!$C$2+G2*Pesos!$C$3+J2*Pesos!$C$4+M2*Pesos!$C$5+P2*Pesos!$C$6+S2*Pesos!$C$7+V2*Pesos!$C$8+Y2*Pesos!$C$9+AB2*Pesos!$C$10),"Sin criterios aplicables") | AG2: =IF(OR(AE2="Sin criterios aplicables",AE2<70),"Insufficient evidence",100*(Pesos!$B$2*IF(E2=1,F2,0)+Pesos!$B$3*IF(H2=1,I2,0)+Pesos!$B$4*IF(K2=1,L2,0)+Pesos!$B$5*IF(N2=1,O2,0)+Pesos!$B$6*IF(Q2=1,R2,0)+Pesos!$B$7*IF(T2=1,U2,0)+Pesos!$B$8*IF(W2=1,X2,0)+Pesos!$B$9*IF(Z2=1,AA2,0)+Pesos!$B$10*IF(AC2=1,AD2,0))/(3*(Pesos!$B$2*E2+Pesos!$B$3*H2+Pesos!$B$4*K2+Pesos!$B$5*N2+Pesos!$B$6*Q2+Pesos!$B$7*T2+Pesos!$B$8*W2+Pesos!$B$9*Z2+Pesos!$B$10*AC2))) | AH2: =IF(OR(AF2="Sin criterios aplicables",AF2<70),"Insufficient evidence",100*(Pesos!$C$2*IF(E2=1,F2,0)+Pesos!$C$3*IF(H2=1,I2,0)+Pesos!$C$4*IF(K2=1,L2,0)+Pesos!$C$5*IF(N2=1,O2,0)+Pesos!$C$6*IF(Q2=1,R2,0)+Pesos!$C$7*IF(T2=1,U2,0)+Pesos!$C$8*IF(W2=1,X2,0)+Pesos!$C$9*IF(Z2=1,AA2,0)+Pesos!$C$10*IF(AC2=1,AD2,0))/(3*(Pesos!$C$2*E2+Pesos!$C$3*H2+Pesos!$C$4*K2+Pesos!$C$5*N2+Pesos!$C$6*Q2+Pesos!$C$7*T2+Pesos!$C$8*W2+Pesos!$C$9*Z2+Pesos!$C$10*AC2))) | AI2: =IF(AG2="Insufficient evidence","Insufficient evidence (cobertura<70%)",IF(AG2<50/3,"Insufficient",IF(AG2<50,"Basic",IF(AG2<250/3,"Solid","Advanced")))) | AJ2: =IF(AH2="Insufficient evidence","Insufficient evidence (cobertura<70%)",IF(AH2<50/3,"Insufficient",IF(AH2<50,"Basic",IF(AH2<250/3,"Solid","Advanced")))) | AK2: =IF(TRIM(IF(AND(ISNUMBER(F2),F2<1),"Visibilidad","") & " " & IF(AND(ISNUMBER(I2),I2<1),"Asignación",""))="","Ninguno",TRIM(IF(AND(ISNUMBER(F2),F2<1),"Visibilidad","") & " " & IF(AND(ISNUMBER(I2),I2<1),"Asignación","")))
A3: E1 | B3: Cloud nativa | C3: AWS Cost Optimization Hub | D3: =IF(COUNTIFS(Puntuacion!$A:$A,$A3,Puntuacion!$C:$C,$C3,Puntuacion!$D:$D,"Visibilidad",Puntuacion!$G:$G,"<>NA")>0,1,0) | E3: =IF(AND(D3=1,COUNTIFS(Puntuacion!$A:$A,$A3,Puntuacion!$C:$C,$C3,Puntuacion!$D:$D,"Visibilidad",Puntuacion!$G:$G,"NE")=0),1,0) | F3: =IF(D3=0,"NA",IF(E3=0,"NE",AVERAGEIFS(Puntuacion!$G:$G,Puntuacion!$A:$A,$A3,Puntuacion!$C:$C,$C3,Puntuacion!$D:$D,"Visibilidad",Puntuacion!$G:$G,"<>NA",Puntuacion!$G:$G,"<>NE"))) | G3: =IF(COUNTIFS(Puntuacion!$A:$A,$A3,Puntuacion!$C:$C,$C3,Puntuacion!$D:$D,"Asignacion",Puntuacion!$G:$G,"<>NA")>0,1,0) | H3: =IF(AND(G3=1,COUNTIFS(Puntuacion!$A:$A,$A3,Puntuacion!$C:$C,$C3,Puntuacion!$D:$D,"Asignacion",Puntuacion!$G:$G,"NE")=0),1,0) | I3: =IF(G3=0,"NA",IF(H3=0,"NE",AVERAGEIFS(Puntuacion!$G:$G,Puntuacion!$A:$A,$A3,Puntuacion!$C:$C,$C3,Puntuacion!$D:$D,"Asignacion",Puntuacion!$G:$G,"<>NA",Puntuacion!$G:$G,"<>NE"))) | J3: =IF(COUNTIFS(Puntuacion!$A:$A,$A3,Puntuacion!$C:$C,$C3,Puntuacion!$D:$D,"Optimizacion",Puntuacion!$G:$G,"<>NA")>0,1,0) | K3: =IF(AND(J3=1,COUNTIFS(Puntuacion!$A:$A,$A3,Puntuacion!$C:$C,$C3,Puntuacion!$D:$D,"Optimizacion",Puntuacion!$G:$G,"NE")=0),1,0) | L3: =IF(J3=0,"NA",IF(K3=0,"NE",AVERAGEIFS(Puntuacion!$G:$G,Puntuacion!$A:$A,$A3,Puntuacion!$C:$C,$C3,Puntuacion!$D:$D,"Optimizacion",Puntuacion!$G:$G,"<>NA",Puntuacion!$G:$G,"<>NE"))) | M3: =IF(COUNTIFS(Puntuacion!$A:$A,$A3,Puntuacion!$C:$C,$C3,Puntuacion!$D:$D,"Automatizacion",Puntuacion!$G:$G,"<>NA")>0,1,0) | N3: =IF(AND(M3=1,COUNTIFS(Puntuacion!$A:$A,$A3,Puntuacion!$C:$C,$C3,Puntuacion!$D:$D,"Automatizacion",Puntuacion!$G:$G,"NE")=0),1,0) | O3: =IF(M3=0,"NA",IF(N3=0,"NE",AVERAGEIFS(Puntuacion!$G:$G,Puntuacion!$A:$A,$A3,Puntuacion!$C:$C,$C3,Puntuacion!$D:$D,"Automatizacion",Puntuacion!$G:$G,"<>NA",Puntuacion!$G:$G,"<>NE"))) | P3: =IF(COUNTIFS(Puntuacion!$A:$A,$A3,Puntuacion!$C:$C,$C3,Puntuacion!$D:$D,"Multicloud",Puntuacion!$G:$G,"<>NA")>0,1,0) | Q3: =IF(AND(P3=1,COUNTIFS(Puntuacion!$A:$A,$A3,Puntuacion!$C:$C,$C3,Puntuacion!$D:$D,"Multicloud",Puntuacion!$G:$G,"NE")=0),1,0) | R3: =IF(P3=0,"NA",IF(Q3=0,"NE",AVERAGEIFS(Puntuacion!$G:$G,Puntuacion!$A:$A,$A3,Puntuacion!$C:$C,$C3,Puntuacion!$D:$D,"Multicloud",Puntuacion!$G:$G,"<>NA",Puntuacion!$G:$G,"<>NE"))) | S3: =IF(COUNTIFS(Puntuacion!$A:$A,$A3,Puntuacion!$C:$C,$C3,Puntuacion!$D:$D,"Integracion",Puntuacion!$G:$G,"<>NA")>0,1,0) | T3: =IF(AND(S3=1,COUNTIFS(Puntuacion!$A:$A,$A3,Puntuacion!$C:$C,$C3,Puntuacion!$D:$D,"Integracion",Puntuacion!$G:$G,"NE")=0),1,0) | U3: =IF(S3=0,"NA",IF(T3=0,"NE",AVERAGEIFS(Puntuacion!$G:$G,Puntuacion!$A:$A,$A3,Puntuacion!$C:$C,$C3,Puntuacion!$D:$D,"Integracion",Puntuacion!$G:$G,"<>NA",Puntuacion!$G:$G,"<>NE"))) | V3: =IF(COUNTIFS(Puntuacion!$A:$A,$A3,Puntuacion!$C:$C,$C3,Puntuacion!$D:$D,"Adopcion",Puntuacion!$G:$G,"<>NA")>0,1,0) | W3: =IF(AND(V3=1,COUNTIFS(Puntuacion!$A:$A,$A3,Puntuacion!$C:$C,$C3,Puntuacion!$D:$D,"Adopcion",Puntuacion!$G:$G,"NE")=0),1,0) | X3: =IF(V3=0,"NA",IF(W3=0,"NE",AVERAGEIFS(Puntuacion!$G:$G,Puntuacion!$A:$A,$A3,Puntuacion!$C:$C,$C3,Puntuacion!$D:$D,"Adopcion",Puntuacion!$G:$G,"<>NA",Puntuacion!$G:$G,"<>NE"))) | Y3: =IF(COUNTIFS(Puntuacion!$A:$A,$A3,Puntuacion!$C:$C,$C3,Puntuacion!$D:$D,"Precio",Puntuacion!$G:$G,"<>NA")>0,1,0) | Z3: =IF(AND(Y3=1,COUNTIFS(Puntuacion!$A:$A,$A3,Puntuacion!$C:$C,$C3,Puntuacion!$D:$D,"Precio",Puntuacion!$G:$G,"NE")=0),1,0) | AA3: =IF(Y3=0,"NA",IF(Z3=0,"NE",AVERAGEIFS(Puntuacion!$G:$G,Puntuacion!$A:$A,$A3,Puntuacion!$C:$C,$C3,Puntuacion!$D:$D,"Precio",Puntuacion!$G:$G,"<>NA",Puntuacion!$G:$G,"<>NE"))) | AB3: =IF(COUNTIFS(Puntuacion!$A:$A,$A3,Puntuacion!$C:$C,$C3,Puntuacion!$D:$D,"Dependencia",Puntuacion!$G:$G,"<>NA")>0,1,0) | AC3: =IF(AND(AB3=1,COUNTIFS(Puntuacion!$A:$A,$A3,Puntuacion!$C:$C,$C3,Puntuacion!$D:$D,"Dependencia",Puntuacion!$G:$G,"NE")=0),1,0) | AD3: =IF(AB3=0,"NA",IF(AC3=0,"NE",AVERAGEIFS(Puntuacion!$G:$G,Puntuacion!$A:$A,$A3,Puntuacion!$C:$C,$C3,Puntuacion!$D:$D,"Dependencia",Puntuacion!$G:$G,"<>NA",Puntuacion!$G:$G,"<>NE"))) | AE3: =IFERROR(100*(E3*Pesos!$B$2+H3*Pesos!$B$3+K3*Pesos!$B$4+N3*Pesos!$B$5+Q3*Pesos!$B$6+T3*Pesos!$B$7+W3*Pesos!$B$8+Z3*Pesos!$B$9+AC3*Pesos!$B$10)/(D3*Pesos!$B$2+G3*Pesos!$B$3+J3*Pesos!$B$4+M3*Pesos!$B$5+P3*Pesos!$B$6+S3*Pesos!$B$7+V3*Pesos!$B$8+Y3*Pesos!$B$9+AB3*Pesos!$B$10),"Sin criterios aplicables") | AF3: =IFERROR(100*(E3*Pesos!$C$2+H3*Pesos!$C$3+K3*Pesos!$C$4+N3*Pesos!$C$5+Q3*Pesos!$C$6+T3*Pesos!$C$7+W3*Pesos!$C$8+Z3*Pesos!$C$9+AC3*Pesos!$C$10)/(D3*Pesos!$C$2+G3*Pesos!$C$3+J3*Pesos!$C$4+M3*Pesos!$C$5+P3*Pesos!$C$6+S3*Pesos!$C$7+V3*Pesos!$C$8+Y3*Pesos!$C$9+AB3*Pesos!$C$10),"Sin criterios aplicables") | AG3: =IF(OR(AE3="Sin criterios aplicables",AE3<70),"Insufficient evidence",100*(Pesos!$B$2*IF(E3=1,F3,0)+Pesos!$B$3*IF(H3=1,I3,0)+Pesos!$B$4*IF(K3=1,L3,0)+Pesos!$B$5*IF(N3=1,O3,0)+Pesos!$B$6*IF(Q3=1,R3,0)+Pesos!$B$7*IF(T3=1,U3,0)+Pesos!$B$8*IF(W3=1,X3,0)+Pesos!$B$9*IF(Z3=1,AA3,0)+Pesos!$B$10*IF(AC3=1,AD3,0))/(3*(Pesos!$B$2*E3+Pesos!$B$3*H3+Pesos!$B$4*K3+Pesos!$B$5*N3+Pesos!$B$6*Q3+Pesos!$B$7*T3+Pesos!$B$8*W3+Pesos!$B$9*Z3+Pesos!$B$10*AC3))) | AH3: =IF(OR(AF3="Sin criterios aplicables",AF3<70),"Insufficient evidence",100*(Pesos!$C$2*IF(E3=1,F3,0)+Pesos!$C$3*IF(H3=1,I3,0)+Pesos!$C$4*IF(K3=1,L3,0)+Pesos!$C$5*IF(N3=1,O3,0)+Pesos!$C$6*IF(Q3=1,R3,0)+Pesos!$C$7*IF(T3=1,U3,0)+Pesos!$C$8*IF(W3=1,X3,0)+Pesos!$C$9*IF(Z3=1,AA3,0)+Pesos!$C$10*IF(AC3=1,AD3,0))/(3*(Pesos!$C$2*E3+Pesos!$C$3*H3+Pesos!$C$4*K3+Pesos!$C$5*N3+Pesos!$C$6*Q3+Pesos!$C$7*T3+Pesos!$C$8*W3+Pesos!$C$9*Z3+Pesos!$C$10*AC3))) | AI3: =IF(AG3="Insufficient evidence","Insufficient evidence (cobertura<70%)",IF(AG3<50/3,"Insufficient",IF(AG3<50,"Basic",IF(AG3<250/3,"Solid","Advanced")))) | AJ3: =IF(AH3="Insufficient evidence","Insufficient evidence (cobertura<70%)",IF(AH3<50/3,"Insufficient",IF(AH3<50,"Basic",IF(AH3<250/3,"Solid","Advanced")))) | AK3: =IF(TRIM(IF(AND(ISNUMBER(F3),F3<1),"Visibilidad","") & " " & IF(AND(ISNUMBER(I3),I3<1),"Asignación",""))="","Ninguno",TRIM(IF(AND(ISNUMBER(F3),F3<1),"Visibilidad","") & " " & IF(AND(ISNUMBER(I3),I3<1),"Asignación","")))
A4: E1 | B4: Cloud nativa | C4: Azure Cost Management | D4: =IF(COUNTIFS(Puntuacion!$A:$A,$A4,Puntuacion!$C:$C,$C4,Puntuacion!$D:$D,"Visibilidad",Puntuacion!$G:$G,"<>NA")>0,1,0) | E4: =IF(AND(D4=1,COUNTIFS(Puntuacion!$A:$A,$A4,Puntuacion!$C:$C,$C4,Puntuacion!$D:$D,"Visibilidad",Puntuacion!$G:$G,"NE")=0),1,0) | F4: =IF(D4=0,"NA",IF(E4=0,"NE",AVERAGEIFS(Puntuacion!$G:$G,Puntuacion!$A:$A,$A4,Puntuacion!$C:$C,$C4,Puntuacion!$D:$D,"Visibilidad",Puntuacion!$G:$G,"<>NA",Puntuacion!$G:$G,"<>NE"))) | G4: =IF(COUNTIFS(Puntuacion!$A:$A,$A4,Puntuacion!$C:$C,$C4,Puntuacion!$D:$D,"Asignacion",Puntuacion!$G:$G,"<>NA")>0,1,0) | H4: =IF(AND(G4=1,COUNTIFS(Puntuacion!$A:$A,$A4,Puntuacion!$C:$C,$C4,Puntuacion!$D:$D,"Asignacion",Puntuacion!$G:$G,"NE")=0),1,0) | I4: =IF(G4=0,"NA",IF(H4=0,"NE",AVERAGEIFS(Puntuacion!$G:$G,Puntuacion!$A:$A,$A4,Puntuacion!$C:$C,$C4,Puntuacion!$D:$D,"Asignacion",Puntuacion!$G:$G,"<>NA",Puntuacion!$G:$G,"<>NE"))) | J4: =IF(COUNTIFS(Puntuacion!$A:$A,$A4,Puntuacion!$C:$C,$C4,Puntuacion!$D:$D,"Optimizacion",Puntuacion!$G:$G,"<>NA")>0,1,0) | K4: =IF(AND(J4=1,COUNTIFS(Puntuacion!$A:$A,$A4,Puntuacion!$C:$C,$C4,Puntuacion!$D:$D,"Optimizacion",Puntuacion!$G:$G,"NE")=0),1,0) | L4: =IF(J4=0,"NA",IF(K4=0,"NE",AVERAGEIFS(Puntuacion!$G:$G,Puntuacion!$A:$A,$A4,Puntuacion!$C:$C,$C4,Puntuacion!$D:$D,"Optimizacion",Puntuacion!$G:$G,"<>NA",Puntuacion!$G:$G,"<>NE"))) | M4: =IF(COUNTIFS(Puntuacion!$A:$A,$A4,Puntuacion!$C:$C,$C4,Puntuacion!$D:$D,"Automatizacion",Puntuacion!$G:$G,"<>NA")>0,1,0) | N4: =IF(AND(M4=1,COUNTIFS(Puntuacion!$A:$A,$A4,Puntuacion!$C:$C,$C4,Puntuacion!$D:$D,"Automatizacion",Puntuacion!$G:$G,"NE")=0),1,0) | O4: =IF(M4=0,"NA",IF(N4=0,"NE",AVERAGEIFS(Puntuacion!$G:$G,Puntuacion!$A:$A,$A4,Puntuacion!$C:$C,$C4,Puntuacion!$D:$D,"Automatizacion",Puntuacion!$G:$G,"<>NA",Puntuacion!$G:$G,"<>NE"))) | P4: =IF(COUNTIFS(Puntuacion!$A:$A,$A4,Puntuacion!$C:$C,$C4,Puntuacion!$D:$D,"Multicloud",Puntuacion!$G:$G,"<>NA")>0,1,0) | Q4: =IF(AND(P4=1,COUNTIFS(Puntuacion!$A:$A,$A4,Puntuacion!$C:$C,$C4,Puntuacion!$D:$D,"Multicloud",Puntuacion!$G:$G,"NE")=0),1,0) | R4: =IF(P4=0,"NA",IF(Q4=0,"NE",AVERAGEIFS(Puntuacion!$G:$G,Puntuacion!$A:$A,$A4,Puntuacion!$C:$C,$C4,Puntuacion!$D:$D,"Multicloud",Puntuacion!$G:$G,"<>NA",Puntuacion!$G:$G,"<>NE"))) | S4: =IF(COUNTIFS(Puntuacion!$A:$A,$A4,Puntuacion!$C:$C,$C4,Puntuacion!$D:$D,"Integracion",Puntuacion!$G:$G,"<>NA")>0,1,0) | T4: =IF(AND(S4=1,COUNTIFS(Puntuacion!$A:$A,$A4,Puntuacion!$C:$C,$C4,Puntuacion!$D:$D,"Integracion",Puntuacion!$G:$G,"NE")=0),1,0) | U4: =IF(S4=0,"NA",IF(T4=0,"NE",AVERAGEIFS(Puntuacion!$G:$G,Puntuacion!$A:$A,$A4,Puntuacion!$C:$C,$C4,Puntuacion!$D:$D,"Integracion",Puntuacion!$G:$G,"<>NA",Puntuacion!$G:$G,"<>NE"))) | V4: =IF(COUNTIFS(Puntuacion!$A:$A,$A4,Puntuacion!$C:$C,$C4,Puntuacion!$D:$D,"Adopcion",Puntuacion!$G:$G,"<>NA")>0,1,0) | W4: =IF(AND(V4=1,COUNTIFS(Puntuacion!$A:$A,$A4,Puntuacion!$C:$C,$C4,Puntuacion!$D:$D,"Adopcion",Puntuacion!$G:$G,"NE")=0),1,0) | X4: =IF(V4=0,"NA",IF(W4=0,"NE",AVERAGEIFS(Puntuacion!$G:$G,Puntuacion!$A:$A,$A4,Puntuacion!$C:$C,$C4,Puntuacion!$D:$D,"Adopcion",Puntuacion!$G:$G,"<>NA",Puntuacion!$G:$G,"<>NE"))) | Y4: =IF(COUNTIFS(Puntuacion!$A:$A,$A4,Puntuacion!$C:$C,$C4,Puntuacion!$D:$D,"Precio",Puntuacion!$G:$G,"<>NA")>0,1,0) | Z4: =IF(AND(Y4=1,COUNTIFS(Puntuacion!$A:$A,$A4,Puntuacion!$C:$C,$C4,Puntuacion!$D:$D,"Precio",Puntuacion!$G:$G,"NE")=0),1,0) | AA4: =IF(Y4=0,"NA",IF(Z4=0,"NE",AVERAGEIFS(Puntuacion!$G:$G,Puntuacion!$A:$A,$A4,Puntuacion!$C:$C,$C4,Puntuacion!$D:$D,"Precio",Puntuacion!$G:$G,"<>NA",Puntuacion!$G:$G,"<>NE"))) | AB4: =IF(COUNTIFS(Puntuacion!$A:$A,$A4,Puntuacion!$C:$C,$C4,Puntuacion!$D:$D,"Dependencia",Puntuacion!$G:$G,"<>NA")>0,1,0) | AC4: =IF(AND(AB4=1,COUNTIFS(Puntuacion!$A:$A,$A4,Puntuacion!$C:$C,$C4,Puntuacion!$D:$D,"Dependencia",Puntuacion!$G:$G,"NE")=0),1,0) | AD4: =IF(AB4=0,"NA",IF(AC4=0,"NE",AVERAGEIFS(Puntuacion!$G:$G,Puntuacion!$A:$A,$A4,Puntuacion!$C:$C,$C4,Puntuacion!$D:$D,"Dependencia",Puntuacion!$G:$G,"<>NA",Puntuacion!$G:$G,"<>NE"))) | AE4: =IFERROR(100*(E4*Pesos!$B$2+H4*Pesos!$B$3+K4*Pesos!$B$4+N4*Pesos!$B$5+Q4*Pesos!$B$6+T4*Pesos!$B$7+W4*Pesos!$B$8+Z4*Pesos!$B$9+AC4*Pesos!$B$10)/(D4*Pesos!$B$2+G4*Pesos!$B$3+J4*Pesos!$B$4+M4*Pesos!$B$5+P4*Pesos!$B$6+S4*Pesos!$B$7+V4*Pesos!$B$8+Y4*Pesos!$B$9+AB4*Pesos!$B$10),"Sin criterios aplicables") | AF4: =IFERROR(100*(E4*Pesos!$C$2+H4*Pesos!$C$3+K4*Pesos!$C$4+N4*Pesos!$C$5+Q4*Pesos!$C$6+T4*Pesos!$C$7+W4*Pesos!$C$8+Z4*Pesos!$C$9+AC4*Pesos!$C$10)/(D4*Pesos!$C$2+G4*Pesos!$C$3+J4*Pesos!$C$4+M4*Pesos!$C$5+P4*Pesos!$C$6+S4*Pesos!$C$7+V4*Pesos!$C$8+Y4*Pesos!$C$9+AB4*Pesos!$C$10),"Sin criterios aplicables") | AG4: =IF(OR(AE4="Sin criterios aplicables",AE4<70),"Insufficient evidence",100*(Pesos!$B$2*IF(E4=1,F4,0)+Pesos!$B$3*IF(H4=1,I4,0)+Pesos!$B$4*IF(K4=1,L4,0)+Pesos!$B$5*IF(N4=1,O4,0)+Pesos!$B$6*IF(Q4=1,R4,0)+Pesos!$B$7*IF(T4=1,U4,0)+Pesos!$B$8*IF(W4=1,X4,0)+Pesos!$B$9*IF(Z4=1,AA4,0)+Pesos!$B$10*IF(AC4=1,AD4,0))/(3*(Pesos!$B$2*E4+Pesos!$B$3*H4+Pesos!$B$4*K4+Pesos!$B$5*N4+Pesos!$B$6*Q4+Pesos!$B$7*T4+Pesos!$B$8*W4+Pesos!$B$9*Z4+Pesos!$B$10*AC4))) | AH4: =IF(OR(AF4="Sin criterios aplicables",AF4<70),"Insufficient evidence",100*(Pesos!$C$2*IF(E4=1,F4,0)+Pesos!$C$3*IF(H4=1,I4,0)+Pesos!$C$4*IF(K4=1,L4,0)+Pesos!$C$5*IF(N4=1,O4,0)+Pesos!$C$6*IF(Q4=1,R4,0)+Pesos!$C$7*IF(T4=1,U4,0)+Pesos!$C$8*IF(W4=1,X4,0)+Pesos!$C$9*IF(Z4=1,AA4,0)+Pesos!$C$10*IF(AC4=1,AD4,0))/(3*(Pesos!$C$2*E4+Pesos!$C$3*H4+Pesos!$C$4*K4+Pesos!$C$5*N4+Pesos!$C$6*Q4+Pesos!$C$7*T4+Pesos!$C$8*W4+Pesos!$C$9*Z4+Pesos!$C$10*AC4))) | AI4: =IF(AG4="Insufficient evidence","Insufficient evidence (cobertura<70%)",IF(AG4<50/3,"Insufficient",IF(AG4<50,"Basic",IF(AG4<250/3,"Solid","Advanced")))) | AJ4: =IF(AH4="Insufficient evidence","Insufficient evidence (cobertura<70%)",IF(AH4<50/3,"Insufficient",IF(AH4<50,"Basic",IF(AH4<250/3,"Solid","Advanced")))) | AK4: =IF(TRIM(IF(AND(ISNUMBER(F4),F4<1),"Visibilidad","") & " " & IF(AND(ISNUMBER(I4),I4<1),"Asignación",""))="","Ninguno",TRIM(IF(AND(ISNUMBER(F4),F4<1),"Visibilidad","") & " " & IF(AND(ISNUMBER(I4),I4<1),"Asignación","")))
A5: E1 | B5: Cloud nativa | C5: Google Cloud Billing | D5: =IF(COUNTIFS(Puntuacion!$A:$A,$A5,Puntuacion!$C:$C,$C5,Puntuacion!$D:$D,"Visibilidad",Puntuacion!$G:$G,"<>NA")>0,1,0) | E5: =IF(AND(D5=1,COUNTIFS(Puntuacion!$A:$A,$A5,Puntuacion!$C:$C,$C5,Puntuacion!$D:$D,"Visibilidad",Puntuacion!$G:$G,"NE")=0),1,0) | F5: =IF(D5=0,"NA",IF(E5=0,"NE",AVERAGEIFS(Puntuacion!$G:$G,Puntuacion!$A:$A,$A5,Puntuacion!$C:$C,$C5,Puntuacion!$D:$D,"Visibilidad",Puntuacion!$G:$G,"<>NA",Puntuacion!$G:$G,"<>NE"))) | G5: =IF(COUNTIFS(Puntuacion!$A:$A,$A5,Puntuacion!$C:$C,$C5,Puntuacion!$D:$D,"Asignacion",Puntuacion!$G:$G,"<>NA")>0,1,0) | H5: =IF(AND(G5=1,COUNTIFS(Puntuacion!$A:$A,$A5,Puntuacion!$C:$C,$C5,Puntuacion!$D:$D,"Asignacion",Puntuacion!$G:$G,"NE")=0),1,0) | I5: =IF(G5=0,"NA",IF(H5=0,"NE",AVERAGEIFS(Puntuacion!$G:$G,Puntuacion!$A:$A,$A5,Puntuacion!$C:$C,$C5,Puntuacion!$D:$D,"Asignacion",Puntuacion!$G:$G,"<>NA",Puntuacion!$G:$G,"<>NE"))) | J5: =IF(COUNTIFS(Puntuacion!$A:$A,$A5,Puntuacion!$C:$C,$C5,Puntuacion!$D:$D,"Optimizacion",Puntuacion!$G:$G,"<>NA")>0,1,0) | K5: =IF(AND(J5=1,COUNTIFS(Puntuacion!$A:$A,$A5,Puntuacion!$C:$C,$C5,Puntuacion!$D:$D,"Optimizacion",Puntuacion!$G:$G,"NE")=0),1,0) | L5: =IF(J5=0,"NA",IF(K5=0,"NE",AVERAGEIFS(Puntuacion!$G:$G,Puntuacion!$A:$A,$A5,Puntuacion!$C:$C,$C5,Puntuacion!$D:$D,"Optimizacion",Puntuacion!$G:$G,"<>NA",Puntuacion!$G:$G,"<>NE"))) | M5: =IF(COUNTIFS(Puntuacion!$A:$A,$A5,Puntuacion!$C:$C,$C5,Puntuacion!$D:$D,"Automatizacion",Puntuacion!$G:$G,"<>NA")>0,1,0) | N5: =IF(AND(M5=1,COUNTIFS(Puntuacion!$A:$A,$A5,Puntuacion!$C:$C,$C5,Puntuacion!$D:$D,"Automatizacion",Puntuacion!$G:$G,"NE")=0),1,0) | O5: =IF(M5=0,"NA",IF(N5=0,"NE",AVERAGEIFS(Puntuacion!$G:$G,Puntuacion!$A:$A,$A5,Puntuacion!$C:$C,$C5,Puntuacion!$D:$D,"Automatizacion",Puntuacion!$G:$G,"<>NA",Puntuacion!$G:$G,"<>NE"))) | P5: =IF(COUNTIFS(Puntuacion!$A:$A,$A5,Puntuacion!$C:$C,$C5,Puntuacion!$D:$D,"Multicloud",Puntuacion!$G:$G,"<>NA")>0,1,0) | Q5: =IF(AND(P5=1,COUNTIFS(Puntuacion!$A:$A,$A5,Puntuacion!$C:$C,$C5,Puntuacion!$D:$D,"Multicloud",Puntuacion!$G:$G,"NE")=0),1,0) | R5: =IF(P5=0,"NA",IF(Q5=0,"NE",AVERAGEIFS(Puntuacion!$G:$G,Puntuacion!$A:$A,$A5,Puntuacion!$C:$C,$C5,Puntuacion!$D:$D,"Multicloud",Puntuacion!$G:$G,"<>NA",Puntuacion!$G:$G,"<>NE"))) | S5: =IF(COUNTIFS(Puntuacion!$A:$A,$A5,Puntuacion!$C:$C,$C5,Puntuacion!$D:$D,"Integracion",Puntuacion!$G:$G,"<>NA")>0,1,0) | T5: =IF(AND(S5=1,COUNTIFS(Puntuacion!$A:$A,$A5,Puntuacion!$C:$C,$C5,Puntuacion!$D:$D,"Integracion",Puntuacion!$G:$G,"NE")=0),1,0) | U5: =IF(S5=0,"NA",IF(T5=0,"NE",AVERAGEIFS(Puntuacion!$G:$G,Puntuacion!$A:$A,$A5,Puntuacion!$C:$C,$C5,Puntuacion!$D:$D,"Integracion",Puntuacion!$G:$G,"<>NA",Puntuacion!$G:$G,"<>NE"))) | V5: =IF(COUNTIFS(Puntuacion!$A:$A,$A5,Puntuacion!$C:$C,$C5,Puntuacion!$D:$D,"Adopcion",Puntuacion!$G:$G,"<>NA")>0,1,0) | W5: =IF(AND(V5=1,COUNTIFS(Puntuacion!$A:$A,$A5,Puntuacion!$C:$C,$C5,Puntuacion!$D:$D,"Adopcion",Puntuacion!$G:$G,"NE")=0),1,0) | X5: =IF(V5=0,"NA",IF(W5=0,"NE",AVERAGEIFS(Puntuacion!$G:$G,Puntuacion!$A:$A,$A5,Puntuacion!$C:$C,$C5,Puntuacion!$D:$D,"Adopcion",Puntuacion!$G:$G,"<>NA",Puntuacion!$G:$G,"<>NE"))) | Y5: =IF(COUNTIFS(Puntuacion!$A:$A,$A5,Puntuacion!$C:$C,$C5,Puntuacion!$D:$D,"Precio",Puntuacion!$G:$G,"<>NA")>0,1,0) | Z5: =IF(AND(Y5=1,COUNTIFS(Puntuacion!$A:$A,$A5,Puntuacion!$C:$C,$C5,Puntuacion!$D:$D,"Precio",Puntuacion!$G:$G,"NE")=0),1,0) | AA5: =IF(Y5=0,"NA",IF(Z5=0,"NE",AVERAGEIFS(Puntuacion!$G:$G,Puntuacion!$A:$A,$A5,Puntuacion!$C:$C,$C5,Puntuacion!$D:$D,"Precio",Puntuacion!$G:$G,"<>NA",Puntuacion!$G:$G,"<>NE"))) | AB5: =IF(COUNTIFS(Puntuacion!$A:$A,$A5,Puntuacion!$C:$C,$C5,Puntuacion!$D:$D,"Dependencia",Puntuacion!$G:$G,"<>NA")>0,1,0) | AC5: =IF(AND(AB5=1,COUNTIFS(Puntuacion!$A:$A,$A5,Puntuacion!$C:$C,$C5,Puntuacion!$D:$D,"Dependencia",Puntuacion!$G:$G,"NE")=0),1,0) | AD5: =IF(AB5=0,"NA",IF(AC5=0,"NE",AVERAGEIFS(Puntuacion!$G:$G,Puntuacion!$A:$A,$A5,Puntuacion!$C:$C,$C5,Puntuacion!$D:$D,"Dependencia",Puntuacion!$G:$G,"<>NA",Puntuacion!$G:$G,"<>NE"))) | AE5: =IFERROR(100*(E5*Pesos!$B$2+H5*Pesos!$B$3+K5*Pesos!$B$4+N5*Pesos!$B$5+Q5*Pesos!$B$6+T5*Pesos!$B$7+W5*Pesos!$B$8+Z5*Pesos!$B$9+AC5*Pesos!$B$10)/(D5*Pesos!$B$2+G5*Pesos!$B$3+J5*Pesos!$B$4+M5*Pesos!$B$5+P5*Pesos!$B$6+S5*Pesos!$B$7+V5*Pesos!$B$8+Y5*Pesos!$B$9+AB5*Pesos!$B$10),"Sin criterios aplicables") | AF5: =IFERROR(100*(E5*Pesos!$C$2+H5*Pesos!$C$3+K5*Pesos!$C$4+N5*Pesos!$C$5+Q5*Pesos!$C$6+T5*Pesos!$C$7+W5*Pesos!$C$8+Z5*Pesos!$C$9+AC5*Pesos!$C$10)/(D5*Pesos!$C$2+G5*Pesos!$C$3+J5*Pesos!$C$4+M5*Pesos!$C$5+P5*Pesos!$C$6+S5*Pesos!$C$7+V5*Pesos!$C$8+Y5*Pesos!$C$9+AB5*Pesos!$C$10),"Sin criterios aplicables") | AG5: =IF(OR(AE5="Sin criterios aplicables",AE5<70),"Insufficient evidence",100*(Pesos!$B$2*IF(E5=1,F5,0)+Pesos!$B$3*IF(H5=1,I5,0)+Pesos!$B$4*IF(K5=1,L5,0)+Pesos!$B$5*IF(N5=1,O5,0)+Pesos!$B$6*IF(Q5=1,R5,0)+Pesos!$B$7*IF(T5=1,U5,0)+Pesos!$B$8*IF(W5=1,X5,0)+Pesos!$B$9*IF(Z5=1,AA5,0)+Pesos!$B$10*IF(AC5=1,AD5,0))/(3*(Pesos!$B$2*E5+Pesos!$B$3*H5+Pesos!$B$4*K5+Pesos!$B$5*N5+Pesos!$B$6*Q5+Pesos!$B$7*T5+Pesos!$B$8*W5+Pesos!$B$9*Z5+Pesos!$B$10*AC5))) | AH5: =IF(OR(AF5="Sin criterios aplicables",AF5<70),"Insufficient evidence",100*(Pesos!$C$2*IF(E5=1,F5,0)+Pesos!$C$3*IF(H5=1,I5,0)+Pesos!$C$4*IF(K5=1,L5,0)+Pesos!$C$5*IF(N5=1,O5,0)+Pesos!$C$6*IF(Q5=1,R5,0)+Pesos!$C$7*IF(T5=1,U5,0)+Pesos!$C$8*IF(W5=1,X5,0)+Pesos!$C$9*IF(Z5=1,AA5,0)+Pesos!$C$10*IF(AC5=1,AD5,0))/(3*(Pesos!$C$2*E5+Pesos!$C$3*H5+Pesos!$C$4*K5+Pesos!$C$5*N5+Pesos!$C$6*Q5+Pesos!$C$7*T5+Pesos!$C$8*W5+Pesos!$C$9*Z5+Pesos!$C$10*AC5))) | AI5: =IF(AG5="Insufficient evidence","Insufficient evidence (cobertura<70%)",IF(AG5<50/3,"Insufficient",IF(AG5<50,"Basic",IF(AG5<250/3,"Solid","Advanced")))) | AJ5: =IF(AH5="Insufficient evidence","Insufficient evidence (cobertura<70%)",IF(AH5<50/3,"Insufficient",IF(AH5<50,"Basic",IF(AH5<250/3,"Solid","Advanced")))) | AK5: =IF(TRIM(IF(AND(ISNUMBER(F5),F5<1),"Visibilidad","") & " " & IF(AND(ISNUMBER(I5),I5<1),"Asignación",""))="","Ninguno",TRIM(IF(AND(ISNUMBER(F5),F5<1),"Visibilidad","") & " " & IF(AND(ISNUMBER(I5),I5<1),"Asignación","")))
A6: E1 | B6: Cloud nativa | C6: Google Cloud FinOps Hub | D6: =IF(COUNTIFS(Puntuacion!$A:$A,$A6,Puntuacion!$C:$C,$C6,Puntuacion!$D:$D,"Visibilidad",Puntuacion!$G:$G,"<>NA")>0,1,0) | E6: =IF(AND(D6=1,COUNTIFS(Puntuacion!$A:$A,$A6,Puntuacion!$C:$C,$C6,Puntuacion!$D:$D,"Visibilidad",Puntuacion!$G:$G,"NE")=0),1,0) | F6: =IF(D6=0,"NA",IF(E6=0,"NE",AVERAGEIFS(Puntuacion!$G:$G,Puntuacion!$A:$A,$A6,Puntuacion!$C:$C,$C6,Puntuacion!$D:$D,"Visibilidad",Puntuacion!$G:$G,"<>NA",Puntuacion!$G:$G,"<>NE"))) | G6: =IF(COUNTIFS(Puntuacion!$A:$A,$A6,Puntuacion!$C:$C,$C6,Puntuacion!$D:$D,"Asignacion",Puntuacion!$G:$G,"<>NA")>0,1,0) | H6: =IF(AND(G6=1,COUNTIFS(Puntuacion!$A:$A,$A6,Puntuacion!$C:$C,$C6,Puntuacion!$D:$D,"Asignacion",Puntuacion!$G:$G,"NE")=0),1,0) | I6: =IF(G6=0,"NA",IF(H6=0,"NE",AVERAGEIFS(Puntuacion!$G:$G,Puntuacion!$A:$A,$A6,Puntuacion!$C:$C,$C6,Puntuacion!$D:$D,"Asignacion",Puntuacion!$G:$G,"<>NA",Puntuacion!$G:$G,"<>NE"))) | J6: =IF(COUNTIFS(Puntuacion!$A:$A,$A6,Puntuacion!$C:$C,$C6,Puntuacion!$D:$D,"Optimizacion",Puntuacion!$G:$G,"<>NA")>0,1,0) | K6: =IF(AND(J6=1,COUNTIFS(Puntuacion!$A:$A,$A6,Puntuacion!$C:$C,$C6,Puntuacion!$D:$D,"Optimizacion",Puntuacion!$G:$G,"NE")=0),1,0) | L6: =IF(J6=0,"NA",IF(K6=0,"NE",AVERAGEIFS(Puntuacion!$G:$G,Puntuacion!$A:$A,$A6,Puntuacion!$C:$C,$C6,Puntuacion!$D:$D,"Optimizacion",Puntuacion!$G:$G,"<>NA",Puntuacion!$G:$G,"<>NE"))) | M6: =IF(COUNTIFS(Puntuacion!$A:$A,$A6,Puntuacion!$C:$C,$C6,Puntuacion!$D:$D,"Automatizacion",Puntuacion!$G:$G,"<>NA")>0,1,0) | N6: =IF(AND(M6=1,COUNTIFS(Puntuacion!$A:$A,$A6,Puntuacion!$C:$C,$C6,Puntuacion!$D:$D,"Automatizacion",Puntuacion!$G:$G,"NE")=0),1,0) | O6: =IF(M6=0,"NA",IF(N6=0,"NE",AVERAGEIFS(Puntuacion!$G:$G,Puntuacion!$A:$A,$A6,Puntuacion!$C:$C,$C6,Puntuacion!$D:$D,"Automatizacion",Puntuacion!$G:$G,"<>NA",Puntuacion!$G:$G,"<>NE"))) | P6: =IF(COUNTIFS(Puntuacion!$A:$A,$A6,Puntuacion!$C:$C,$C6,Puntuacion!$D:$D,"Multicloud",Puntuacion!$G:$G,"<>NA")>0,1,0) | Q6: =IF(AND(P6=1,COUNTIFS(Puntuacion!$A:$A,$A6,Puntuacion!$C:$C,$C6,Puntuacion!$D:$D,"Multicloud",Puntuacion!$G:$G,"NE")=0),1,0) | R6: =IF(P6=0,"NA",IF(Q6=0,"NE",AVERAGEIFS(Puntuacion!$G:$G,Puntuacion!$A:$A,$A6,Puntuacion!$C:$C,$C6,Puntuacion!$D:$D,"Multicloud",Puntuacion!$G:$G,"<>NA",Puntuacion!$G:$G,"<>NE"))) | S6: =IF(COUNTIFS(Puntuacion!$A:$A,$A6,Puntuacion!$C:$C,$C6,Puntuacion!$D:$D,"Integracion",Puntuacion!$G:$G,"<>NA")>0,1,0) | T6: =IF(AND(S6=1,COUNTIFS(Puntuacion!$A:$A,$A6,Puntuacion!$C:$C,$C6,Puntuacion!$D:$D,"Integracion",Puntuacion!$G:$G,"NE")=0),1,0) | U6: =IF(S6=0,"NA",IF(T6=0,"NE",AVERAGEIFS(Puntuacion!$G:$G,Puntuacion!$A:$A,$A6,Puntuacion!$C:$C,$C6,Puntuacion!$D:$D,"Integracion",Puntuacion!$G:$G,"<>NA",Puntuacion!$G:$G,"<>NE"))) | V6: =IF(COUNTIFS(Puntuacion!$A:$A,$A6,Puntuacion!$C:$C,$C6,Puntuacion!$D:$D,"Adopcion",Puntuacion!$G:$G,"<>NA")>0,1,0) | W6: =IF(AND(V6=1,COUNTIFS(Puntuacion!$A:$A,$A6,Puntuacion!$C:$C,$C6,Puntuacion!$D:$D,"Adopcion",Puntuacion!$G:$G,"NE")=0),1,0) | X6: =IF(V6=0,"NA",IF(W6=0,"NE",AVERAGEIFS(Puntuacion!$G:$G,Puntuacion!$A:$A,$A6,Puntuacion!$C:$C,$C6,Puntuacion!$D:$D,"Adopcion",Puntuacion!$G:$G,"<>NA",Puntuacion!$G:$G,"<>NE"))) | Y6: =IF(COUNTIFS(Puntuacion!$A:$A,$A6,Puntuacion!$C:$C,$C6,Puntuacion!$D:$D,"Precio",Puntuacion!$G:$G,"<>NA")>0,1,0) | Z6: =IF(AND(Y6=1,COUNTIFS(Puntuacion!$A:$A,$A6,Puntuacion!$C:$C,$C6,Puntuacion!$D:$D,"Precio",Puntuacion!$G:$G,"NE")=0),1,0) | AA6: =IF(Y6=0,"NA",IF(Z6=0,"NE",AVERAGEIFS(Puntuacion!$G:$G,Puntuacion!$A:$A,$A6,Puntuacion!$C:$C,$C6,Puntuacion!$D:$D,"Precio",Puntuacion!$G:$G,"<>NA",Puntuacion!$G:$G,"<>NE"))) | AB6: =IF(COUNTIFS(Puntuacion!$A:$A,$A6,Puntuacion!$C:$C,$C6,Puntuacion!$D:$D,"Dependencia",Puntuacion!$G:$G,"<>NA")>0,1,0) | AC6: =IF(AND(AB6=1,COUNTIFS(Puntuacion!$A:$A,$A6,Puntuacion!$C:$C,$C6,Puntuacion!$D:$D,"Dependencia",Puntuacion!$G:$G,"NE")=0),1,0) | AD6: =IF(AB6=0,"NA",IF(AC6=0,"NE",AVERAGEIFS(Puntuacion!$G:$G,Puntuacion!$A:$A,$A6,Puntuacion!$C:$C,$C6,Puntuacion!$D:$D,"Dependencia",Puntuacion!$G:$G,"<>NA",Puntuacion!$G:$G,"<>NE"))) | AE6: =IFERROR(100*(E6*Pesos!$B$2+H6*Pesos!$B$3+K6*Pesos!$B$4+N6*Pesos!$B$5+Q6*Pesos!$B$6+T6*Pesos!$B$7+W6*Pesos!$B$8+Z6*Pesos!$B$9+AC6*Pesos!$B$10)/(D6*Pesos!$B$2+G6*Pesos!$B$3+J6*Pesos!$B$4+M6*Pesos!$B$5+P6*Pesos!$B$6+S6*Pesos!$B$7+V6*Pesos!$B$8+Y6*Pesos!$B$9+AB6*Pesos!$B$10),"Sin criterios aplicables") | AF6: =IFERROR(100*(E6*Pesos!$C$2+H6*Pesos!$C$3+K6*Pesos!$C$4+N6*Pesos!$C$5+Q6*Pesos!$C$6+T6*Pesos!$C$7+W6*Pesos!$C$8+Z6*Pesos!$C$9+AC6*Pesos!$C$10)/(D6*Pesos!$C$2+G6*Pesos!$C$3+J6*Pesos!$C$4+M6*Pesos!$C$5+P6*Pesos!$C$6+S6*Pesos!$C$7+V6*Pesos!$C$8+Y6*Pesos!$C$9+AB6*Pesos!$C$10),"Sin criterios aplicables") | AG6: =IF(OR(AE6="Sin criterios aplicables",AE6<70),"Insufficient evidence",100*(Pesos!$B$2*IF(E6=1,F6,0)+Pesos!$B$3*IF(H6=1,I6,0)+Pesos!$B$4*IF(K6=1,L6,0)+Pesos!$B$5*IF(N6=1,O6,0)+Pesos!$B$6*IF(Q6=1,R6,0)+Pesos!$B$7*IF(T6=1,U6,0)+Pesos!$B$8*IF(W6=1,X6,0)+Pesos!$B$9*IF(Z6=1,AA6,0)+Pesos!$B$10*IF(AC6=1,AD6,0))/(3*(Pesos!$B$2*E6+Pesos!$B$3*H6+Pesos!$B$4*K6+Pesos!$B$5*N6+Pesos!$B$6*Q6+Pesos!$B$7*T6+Pesos!$B$8*W6+Pesos!$B$9*Z6+Pesos!$B$10*AC6))) | AH6: =IF(OR(AF6="Sin criterios aplicables",AF6<70),"Insufficient evidence",100*(Pesos!$C$2*IF(E6=1,F6,0)+Pesos!$C$3*IF(H6=1,I6,0)+Pesos!$C$4*IF(K6=1,L6,0)+Pesos!$C$5*IF(N6=1,O6,0)+Pesos!$C$6*IF(Q6=1,R6,0)+Pesos!$C$7*IF(T6=1,U6,0)+Pesos!$C$8*IF(W6=1,X6,0)+Pesos!$C$9*IF(Z6=1,AA6,0)+Pesos!$C$10*IF(AC6=1,AD6,0))/(3*(Pesos!$C$2*E6+Pesos!$C$3*H6+Pesos!$C$4*K6+Pesos!$C$5*N6+Pesos!$C$6*Q6+Pesos!$C$7*T6+Pesos!$C$8*W6+Pesos!$C$9*Z6+Pesos!$C$10*AC6))) | AI6: =IF(AG6="Insufficient evidence","Insufficient evidence (cobertura<70%)",IF(AG6<50/3,"Insufficient",IF(AG6<50,"Basic",IF(AG6<250/3,"Solid","Advanced")))) | AJ6: =IF(AH6="Insufficient evidence","Insufficient evidence (cobertura<70%)",IF(AH6<50/3,"Insufficient",IF(AH6<50,"Basic",IF(AH6<250/3,"Solid","Advanced")))) | AK6: =IF(TRIM(IF(AND(ISNUMBER(F6),F6<1),"Visibilidad","") & " " & IF(AND(ISNUMBER(I6),I6<1),"Asignación",""))="","Ninguno",TRIM(IF(AND(ISNUMBER(F6),F6<1),"Visibilidad","") & " " & IF(AND(ISNUMBER(I6),I6<1),"Asignación","")))
A7: E1 | B7: Multicloud | C7: CloudHealth | D7: =IF(COUNTIFS(Puntuacion!$A:$A,$A7,Puntuacion!$C:$C,$C7,Puntuacion!$D:$D,"Visibilidad",Puntuacion!$G:$G,"<>NA")>0,1,0) | E7: =IF(AND(D7=1,COUNTIFS(Puntuacion!$A:$A,$A7,Puntuacion!$C:$C,$C7,Puntuacion!$D:$D,"Visibilidad",Puntuacion!$G:$G,"NE")=0),1,0) | F7: =IF(D7=0,"NA",IF(E7=0,"NE",AVERAGEIFS(Puntuacion!$G:$G,Puntuacion!$A:$A,$A7,Puntuacion!$C:$C,$C7,Puntuacion!$D:$D,"Visibilidad",Puntuacion!$G:$G,"<>NA",Puntuacion!$G:$G,"<>NE"))) | G7: =IF(COUNTIFS(Puntuacion!$A:$A,$A7,Puntuacion!$C:$C,$C7,Puntuacion!$D:$D,"Asignacion",Puntuacion!$G:$G,"<>NA")>0,1,0) | H7: =IF(AND(G7=1,COUNTIFS(Puntuacion!$A:$A,$A7,Puntuacion!$C:$C,$C7,Puntuacion!$D:$D,"Asignacion",Puntuacion!$G:$G,"NE")=0),1,0) | I7: =IF(G7=0,"NA",IF(H7=0,"NE",AVERAGEIFS(Puntuacion!$G:$G,Puntuacion!$A:$A,$A7,Puntuacion!$C:$C,$C7,Puntuacion!$D:$D,"Asignacion",Puntuacion!$G:$G,"<>NA",Puntuacion!$G:$G,"<>NE"))) | J7: =IF(COUNTIFS(Puntuacion!$A:$A,$A7,Puntuacion!$C:$C,$C7,Puntuacion!$D:$D,"Optimizacion",Puntuacion!$G:$G,"<>NA")>0,1,0) | K7: =IF(AND(J7=1,COUNTIFS(Puntuacion!$A:$A,$A7,Puntuacion!$C:$C,$C7,Puntuacion!$D:$D,"Optimizacion",Puntuacion!$G:$G,"NE")=0),1,0) | L7: =IF(J7=0,"NA",IF(K7=0,"NE",AVERAGEIFS(Puntuacion!$G:$G,Puntuacion!$A:$A,$A7,Puntuacion!$C:$C,$C7,Puntuacion!$D:$D,"Optimizacion",Puntuacion!$G:$G,"<>NA",Puntuacion!$G:$G,"<>NE"))) | M7: =IF(COUNTIFS(Puntuacion!$A:$A,$A7,Puntuacion!$C:$C,$C7,Puntuacion!$D:$D,"Automatizacion",Puntuacion!$G:$G,"<>NA")>0,1,0) | N7: =IF(AND(M7=1,COUNTIFS(Puntuacion!$A:$A,$A7,Puntuacion!$C:$C,$C7,Puntuacion!$D:$D,"Automatizacion",Puntuacion!$G:$G,"NE")=0),1,0) | O7: =IF(M7=0,"NA",IF(N7=0,"NE",AVERAGEIFS(Puntuacion!$G:$G,Puntuacion!$A:$A,$A7,Puntuacion!$C:$C,$C7,Puntuacion!$D:$D,"Automatizacion",Puntuacion!$G:$G,"<>NA",Puntuacion!$G:$G,"<>NE"))) | P7: =IF(COUNTIFS(Puntuacion!$A:$A,$A7,Puntuacion!$C:$C,$C7,Puntuacion!$D:$D,"Multicloud",Puntuacion!$G:$G,"<>NA")>0,1,0) | Q7: =IF(AND(P7=1,COUNTIFS(Puntuacion!$A:$A,$A7,Puntuacion!$C:$C,$C7,Puntuacion!$D:$D,"Multicloud",Puntuacion!$G:$G,"NE")=0),1,0) | R7: =IF(P7=0,"NA",IF(Q7=0,"NE",AVERAGEIFS(Puntuacion!$G:$G,Puntuacion!$A:$A,$A7,Puntuacion!$C:$C,$C7,Puntuacion!$D:$D,"Multicloud",Puntuacion!$G:$G,"<>NA",Puntuacion!$G:$G,"<>NE"))) | S7: =IF(COUNTIFS(Puntuacion!$A:$A,$A7,Puntuacion!$C:$C,$C7,Puntuacion!$D:$D,"Integracion",Puntuacion!$G:$G,"<>NA")>0,1,0) | T7: =IF(AND(S7=1,COUNTIFS(Puntuacion!$A:$A,$A7,Puntuacion!$C:$C,$C7,Puntuacion!$D:$D,"Integracion",Puntuacion!$G:$G,"NE")=0),1,0) | U7: =IF(S7=0,"NA",IF(T7=0,"NE",AVERAGEIFS(Puntuacion!$G:$G,Puntuacion!$A:$A,$A7,Puntuacion!$C:$C,$C7,Puntuacion!$D:$D,"Integracion",Puntuacion!$G:$G,"<>NA",Puntuacion!$G:$G,"<>NE"))) | V7: =IF(COUNTIFS(Puntuacion!$A:$A,$A7,Puntuacion!$C:$C,$C7,Puntuacion!$D:$D,"Adopcion",Puntuacion!$G:$G,"<>NA")>0,1,0) | W7: =IF(AND(V7=1,COUNTIFS(Puntuacion!$A:$A,$A7,Puntuacion!$C:$C,$C7,Puntuacion!$D:$D,"Adopcion",Puntuacion!$G:$G,"NE")=0),1,0) | X7: =IF(V7=0,"NA",IF(W7=0,"NE",AVERAGEIFS(Puntuacion!$G:$G,Puntuacion!$A:$A,$A7,Puntuacion!$C:$C,$C7,Puntuacion!$D:$D,"Adopcion",Puntuacion!$G:$G,"<>NA",Puntuacion!$G:$G,"<>NE"))) | Y7: =IF(COUNTIFS(Puntuacion!$A:$A,$A7,Puntuacion!$C:$C,$C7,Puntuacion!$D:$D,"Precio",Puntuacion!$G:$G,"<>NA")>0,1,0) | Z7: =IF(AND(Y7=1,COUNTIFS(Puntuacion!$A:$A,$A7,Puntuacion!$C:$C,$C7,Puntuacion!$D:$D,"Precio",Puntuacion!$G:$G,"NE")=0),1,0) | AA7: =IF(Y7=0,"NA",IF(Z7=0,"NE",AVERAGEIFS(Puntuacion!$G:$G,Puntuacion!$A:$A,$A7,Puntuacion!$C:$C,$C7,Puntuacion!$D:$D,"Precio",Puntuacion!$G:$G,"<>NA",Puntuacion!$G:$G,"<>NE"))) | AB7: =IF(COUNTIFS(Puntuacion!$A:$A,$A7,Puntuacion!$C:$C,$C7,Puntuacion!$D:$D,"Dependencia",Puntuacion!$G:$G,"<>NA")>0,1,0) | AC7: =IF(AND(AB7=1,COUNTIFS(Puntuacion!$A:$A,$A7,Puntuacion!$C:$C,$C7,Puntuacion!$D:$D,"Dependencia",Puntuacion!$G:$G,"NE")=0),1,0) | AD7: =IF(AB7=0,"NA",IF(AC7=0,"NE",AVERAGEIFS(Puntuacion!$G:$G,Puntuacion!$A:$A,$A7,Puntuacion!$C:$C,$C7,Puntuacion!$D:$D,"Dependencia",Puntuacion!$G:$G,"<>NA",Puntuacion!$G:$G,"<>NE"))) | AE7: =IFERROR(100*(E7*Pesos!$B$2+H7*Pesos!$B$3+K7*Pesos!$B$4+N7*Pesos!$B$5+Q7*Pesos!$B$6+T7*Pesos!$B$7+W7*Pesos!$B$8+Z7*Pesos!$B$9+AC7*Pesos!$B$10)/(D7*Pesos!$B$2+G7*Pesos!$B$3+J7*Pesos!$B$4+M7*Pesos!$B$5+P7*Pesos!$B$6+S7*Pesos!$B$7+V7*Pesos!$B$8+Y7*Pesos!$B$9+AB7*Pesos!$B$10),"Sin criterios aplicables") | AF7: =IFERROR(100*(E7*Pesos!$C$2+H7*Pesos!$C$3+K7*Pesos!$C$4+N7*Pesos!$C$5+Q7*Pesos!$C$6+T7*Pesos!$C$7+W7*Pesos!$C$8+Z7*Pesos!$C$9+AC7*Pesos!$C$10)/(D7*Pesos!$C$2+G7*Pesos!$C$3+J7*Pesos!$C$4+M7*Pesos!$C$5+P7*Pesos!$C$6+S7*Pesos!$C$7+V7*Pesos!$C$8+Y7*Pesos!$C$9+AB7*Pesos!$C$10),"Sin criterios aplicables") | AG7: =IF(OR(AE7="Sin criterios aplicables",AE7<70),"Insufficient evidence",100*(Pesos!$B$2*IF(E7=1,F7,0)+Pesos!$B$3*IF(H7=1,I7,0)+Pesos!$B$4*IF(K7=1,L7,0)+Pesos!$B$5*IF(N7=1,O7,0)+Pesos!$B$6*IF(Q7=1,R7,0)+Pesos!$B$7*IF(T7=1,U7,0)+Pesos!$B$8*IF(W7=1,X7,0)+Pesos!$B$9*IF(Z7=1,AA7,0)+Pesos!$B$10*IF(AC7=1,AD7,0))/(3*(Pesos!$B$2*E7+Pesos!$B$3*H7+Pesos!$B$4*K7+Pesos!$B$5*N7+Pesos!$B$6*Q7+Pesos!$B$7*T7+Pesos!$B$8*W7+Pesos!$B$9*Z7+Pesos!$B$10*AC7))) | AH7: =IF(OR(AF7="Sin criterios aplicables",AF7<70),"Insufficient evidence",100*(Pesos!$C$2*IF(E7=1,F7,0)+Pesos!$C$3*IF(H7=1,I7,0)+Pesos!$C$4*IF(K7=1,L7,0)+Pesos!$C$5*IF(N7=1,O7,0)+Pesos!$C$6*IF(Q7=1,R7,0)+Pesos!$C$7*IF(T7=1,U7,0)+Pesos!$C$8*IF(W7=1,X7,0)+Pesos!$C$9*IF(Z7=1,AA7,0)+Pesos!$C$10*IF(AC7=1,AD7,0))/(3*(Pesos!$C$2*E7+Pesos!$C$3*H7+Pesos!$C$4*K7+Pesos!$C$5*N7+Pesos!$C$6*Q7+Pesos!$C$7*T7+Pesos!$C$8*W7+Pesos!$C$9*Z7+Pesos!$C$10*AC7))) | AI7: =IF(AG7="Insufficient evidence","Insufficient evidence (cobertura<70%)",IF(AG7<50/3,"Insufficient",IF(AG7<50,"Basic",IF(AG7<250/3,"Solid","Advanced")))) | AJ7: =IF(AH7="Insufficient evidence","Insufficient evidence (cobertura<70%)",IF(AH7<50/3,"Insufficient",IF(AH7<50,"Basic",IF(AH7<250/3,"Solid","Advanced")))) | AK7: =IF(TRIM(IF(AND(ISNUMBER(F7),F7<1),"Visibilidad","") & " " & IF(AND(ISNUMBER(I7),I7<1),"Asignación",""))="","Ninguno",TRIM(IF(AND(ISNUMBER(F7),F7<1),"Visibilidad","") & " " & IF(AND(ISNUMBER(I7),I7<1),"Asignación","")))
A8: E1 | B8: Multicloud | C8: CloudZero | D8: =IF(COUNTIFS(Puntuacion!$A:$A,$A8,Puntuacion!$C:$C,$C8,Puntuacion!$D:$D,"Visibilidad",Puntuacion!$G:$G,"<>NA")>0,1,0) | E8: =IF(AND(D8=1,COUNTIFS(Puntuacion!$A:$A,$A8,Puntuacion!$C:$C,$C8,Puntuacion!$D:$D,"Visibilidad",Puntuacion!$G:$G,"NE")=0),1,0) | F8: =IF(D8=0,"NA",IF(E8=0,"NE",AVERAGEIFS(Puntuacion!$G:$G,Puntuacion!$A:$A,$A8,Puntuacion!$C:$C,$C8,Puntuacion!$D:$D,"Visibilidad",Puntuacion!$G:$G,"<>NA",Puntuacion!$G:$G,"<>NE"))) | G8: =IF(COUNTIFS(Puntuacion!$A:$A,$A8,Puntuacion!$C:$C,$C8,Puntuacion!$D:$D,"Asignacion",Puntuacion!$G:$G,"<>NA")>0,1,0) | H8: =IF(AND(G8=1,COUNTIFS(Puntuacion!$A:$A,$A8,Puntuacion!$C:$C,$C8,Puntuacion!$D:$D,"Asignacion",Puntuacion!$G:$G,"NE")=0),1,0) | I8: =IF(G8=0,"NA",IF(H8=0,"NE",AVERAGEIFS(Puntuacion!$G:$G,Puntuacion!$A:$A,$A8,Puntuacion!$C:$C,$C8,Puntuacion!$D:$D,"Asignacion",Puntuacion!$G:$G,"<>NA",Puntuacion!$G:$G,"<>NE"))) | J8: =IF(COUNTIFS(Puntuacion!$A:$A,$A8,Puntuacion!$C:$C,$C8,Puntuacion!$D:$D,"Optimizacion",Puntuacion!$G:$G,"<>NA")>0,1,0) | K8: =IF(AND(J8=1,COUNTIFS(Puntuacion!$A:$A,$A8,Puntuacion!$C:$C,$C8,Puntuacion!$D:$D,"Optimizacion",Puntuacion!$G:$G,"NE")=0),1,0) | L8: =IF(J8=0,"NA",IF(K8=0,"NE",AVERAGEIFS(Puntuacion!$G:$G,Puntuacion!$A:$A,$A8,Puntuacion!$C:$C,$C8,Puntuacion!$D:$D,"Optimizacion",Puntuacion!$G:$G,"<>NA",Puntuacion!$G:$G,"<>NE"))) | M8: =IF(COUNTIFS(Puntuacion!$A:$A,$A8,Puntuacion!$C:$C,$C8,Puntuacion!$D:$D,"Automatizacion",Puntuacion!$G:$G,"<>NA")>0,1,0) | N8: =IF(AND(M8=1,COUNTIFS(Puntuacion!$A:$A,$A8,Puntuacion!$C:$C,$C8,Puntuacion!$D:$D,"Automatizacion",Puntuacion!$G:$G,"NE")=0),1,0) | O8: =IF(M8=0,"NA",IF(N8=0,"NE",AVERAGEIFS(Puntuacion!$G:$G,Puntuacion!$A:$A,$A8,Puntuacion!$C:$C,$C8,Puntuacion!$D:$D,"Automatizacion",Puntuacion!$G:$G,"<>NA",Puntuacion!$G:$G,"<>NE"))) | P8: =IF(COUNTIFS(Puntuacion!$A:$A,$A8,Puntuacion!$C:$C,$C8,Puntuacion!$D:$D,"Multicloud",Puntuacion!$G:$G,"<>NA")>0,1,0) | Q8: =IF(AND(P8=1,COUNTIFS(Puntuacion!$A:$A,$A8,Puntuacion!$C:$C,$C8,Puntuacion!$D:$D,"Multicloud",Puntuacion!$G:$G,"NE")=0),1,0) | R8: =IF(P8=0,"NA",IF(Q8=0,"NE",AVERAGEIFS(Puntuacion!$G:$G,Puntuacion!$A:$A,$A8,Puntuacion!$C:$C,$C8,Puntuacion!$D:$D,"Multicloud",Puntuacion!$G:$G,"<>NA",Puntuacion!$G:$G,"<>NE"))) | S8: =IF(COUNTIFS(Puntuacion!$A:$A,$A8,Puntuacion!$C:$C,$C8,Puntuacion!$D:$D,"Integracion",Puntuacion!$G:$G,"<>NA")>0,1,0) | T8: =IF(AND(S8=1,COUNTIFS(Puntuacion!$A:$A,$A8,Puntuacion!$C:$C,$C8,Puntuacion!$D:$D,"Integracion",Puntuacion!$G:$G,"NE")=0),1,0) | U8: =IF(S8=0,"NA",IF(T8=0,"NE",AVERAGEIFS(Puntuacion!$G:$G,Puntuacion!$A:$A,$A8,Puntuacion!$C:$C,$C8,Puntuacion!$D:$D,"Integracion",Puntuacion!$G:$G,"<>NA",Puntuacion!$G:$G,"<>NE"))) | V8: =IF(COUNTIFS(Puntuacion!$A:$A,$A8,Puntuacion!$C:$C,$C8,Puntuacion!$D:$D,"Adopcion",Puntuacion!$G:$G,"<>NA")>0,1,0) | W8: =IF(AND(V8=1,COUNTIFS(Puntuacion!$A:$A,$A8,Puntuacion!$C:$C,$C8,Puntuacion!$D:$D,"Adopcion",Puntuacion!$G:$G,"NE")=0),1,0) | X8: =IF(V8=0,"NA",IF(W8=0,"NE",AVERAGEIFS(Puntuacion!$G:$G,Puntuacion!$A:$A,$A8,Puntuacion!$C:$C,$C8,Puntuacion!$D:$D,"Adopcion",Puntuacion!$G:$G,"<>NA",Puntuacion!$G:$G,"<>NE"))) | Y8: =IF(COUNTIFS(Puntuacion!$A:$A,$A8,Puntuacion!$C:$C,$C8,Puntuacion!$D:$D,"Precio",Puntuacion!$G:$G,"<>NA")>0,1,0) | Z8: =IF(AND(Y8=1,COUNTIFS(Puntuacion!$A:$A,$A8,Puntuacion!$C:$C,$C8,Puntuacion!$D:$D,"Precio",Puntuacion!$G:$G,"NE")=0),1,0) | AA8: =IF(Y8=0,"NA",IF(Z8=0,"NE",AVERAGEIFS(Puntuacion!$G:$G,Puntuacion!$A:$A,$A8,Puntuacion!$C:$C,$C8,Puntuacion!$D:$D,"Precio",Puntuacion!$G:$G,"<>NA",Puntuacion!$G:$G,"<>NE"))) | AB8: =IF(COUNTIFS(Puntuacion!$A:$A,$A8,Puntuacion!$C:$C,$C8,Puntuacion!$D:$D,"Dependencia",Puntuacion!$G:$G,"<>NA")>0,1,0) | AC8: =IF(AND(AB8=1,COUNTIFS(Puntuacion!$A:$A,$A8,Puntuacion!$C:$C,$C8,Puntuacion!$D:$D,"Dependencia",Puntuacion!$G:$G,"NE")=0),1,0) | AD8: =IF(AB8=0,"NA",IF(AC8=0,"NE",AVERAGEIFS(Puntuacion!$G:$G,Puntuacion!$A:$A,$A8,Puntuacion!$C:$C,$C8,Puntuacion!$D:$D,"Dependencia",Puntuacion!$G:$G,"<>NA",Puntuacion!$G:$G,"<>NE"))) | AE8: =IFERROR(100*(E8*Pesos!$B$2+H8*Pesos!$B$3+K8*Pesos!$B$4+N8*Pesos!$B$5+Q8*Pesos!$B$6+T8*Pesos!$B$7+W8*Pesos!$B$8+Z8*Pesos!$B$9+AC8*Pesos!$B$10)/(D8*Pesos!$B$2+G8*Pesos!$B$3+J8*Pesos!$B$4+M8*Pesos!$B$5+P8*Pesos!$B$6+S8*Pesos!$B$7+V8*Pesos!$B$8+Y8*Pesos!$B$9+AB8*Pesos!$B$10),"Sin criterios aplicables") | AF8: =IFERROR(100*(E8*Pesos!$C$2+H8*Pesos!$C$3+K8*Pesos!$C$4+N8*Pesos!$C$5+Q8*Pesos!$C$6+T8*Pesos!$C$7+W8*Pesos!$C$8+Z8*Pesos!$C$9+AC8*Pesos!$C$10)/(D8*Pesos!$C$2+G8*Pesos!$C$3+J8*Pesos!$C$4+M8*Pesos!$C$5+P8*Pesos!$C$6+S8*Pesos!$C$7+V8*Pesos!$C$8+Y8*Pesos!$C$9+AB8*Pesos!$C$10),"Sin criterios aplicables") | AG8: =IF(OR(AE8="Sin criterios aplicables",AE8<70),"Insufficient evidence",100*(Pesos!$B$2*IF(E8=1,F8,0)+Pesos!$B$3*IF(H8=1,I8,0)+Pesos!$B$4*IF(K8=1,L8,0)+Pesos!$B$5*IF(N8=1,O8,0)+Pesos!$B$6*IF(Q8=1,R8,0)+Pesos!$B$7*IF(T8=1,U8,0)+Pesos!$B$8*IF(W8=1,X8,0)+Pesos!$B$9*IF(Z8=1,AA8,0)+Pesos!$B$10*IF(AC8=1,AD8,0))/(3*(Pesos!$B$2*E8+Pesos!$B$3*H8+Pesos!$B$4*K8+Pesos!$B$5*N8+Pesos!$B$6*Q8+Pesos!$B$7*T8+Pesos!$B$8*W8+Pesos!$B$9*Z8+Pesos!$B$10*AC8))) | AH8: =IF(OR(AF8="Sin criterios aplicables",AF8<70),"Insufficient evidence",100*(Pesos!$C$2*IF(E8=1,F8,0)+Pesos!$C$3*IF(H8=1,I8,0)+Pesos!$C$4*IF(K8=1,L8,0)+Pesos!$C$5*IF(N8=1,O8,0)+Pesos!$C$6*IF(Q8=1,R8,0)+Pesos!$C$7*IF(T8=1,U8,0)+Pesos!$C$8*IF(W8=1,X8,0)+Pesos!$C$9*IF(Z8=1,AA8,0)+Pesos!$C$10*IF(AC8=1,AD8,0))/(3*(Pesos!$C$2*E8+Pesos!$C$3*H8+Pesos!$C$4*K8+Pesos!$C$5*N8+Pesos!$C$6*Q8+Pesos!$C$7*T8+Pesos!$C$8*W8+Pesos!$C$9*Z8+Pesos!$C$10*AC8))) | AI8: =IF(AG8="Insufficient evidence","Insufficient evidence (cobertura<70%)",IF(AG8<50/3,"Insufficient",IF(AG8<50,"Basic",IF(AG8<250/3,"Solid","Advanced")))) | AJ8: =IF(AH8="Insufficient evidence","Insufficient evidence (cobertura<70%)",IF(AH8<50/3,"Insufficient",IF(AH8<50,"Basic",IF(AH8<250/3,"Solid","Advanced")))) | AK8: =IF(TRIM(IF(AND(ISNUMBER(F8),F8<1),"Visibilidad","") & " " & IF(AND(ISNUMBER(I8),I8<1),"Asignación",""))="","Ninguno",TRIM(IF(AND(ISNUMBER(F8),F8<1),"Visibilidad","") & " " & IF(AND(ISNUMBER(I8),I8<1),"Asignación","")))
A9: E1 | B9: Multicloud | C9: Cloudability | D9: =IF(COUNTIFS(Puntuacion!$A:$A,$A9,Puntuacion!$C:$C,$C9,Puntuacion!$D:$D,"Visibilidad",Puntuacion!$G:$G,"<>NA")>0,1,0) | E9: =IF(AND(D9=1,COUNTIFS(Puntuacion!$A:$A,$A9,Puntuacion!$C:$C,$C9,Puntuacion!$D:$D,"Visibilidad",Puntuacion!$G:$G,"NE")=0),1,0) | F9: =IF(D9=0,"NA",IF(E9=0,"NE",AVERAGEIFS(Puntuacion!$G:$G,Puntuacion!$A:$A,$A9,Puntuacion!$C:$C,$C9,Puntuacion!$D:$D,"Visibilidad",Puntuacion!$G:$G,"<>NA",Puntuacion!$G:$G,"<>NE"))) | G9: =IF(COUNTIFS(Puntuacion!$A:$A,$A9,Puntuacion!$C:$C,$C9,Puntuacion!$D:$D,"Asignacion",Puntuacion!$G:$G,"<>NA")>0,1,0) | H9: =IF(AND(G9=1,COUNTIFS(Puntuacion!$A:$A,$A9,Puntuacion!$C:$C,$C9,Puntuacion!$D:$D,"Asignacion",Puntuacion!$G:$G,"NE")=0),1,0) | I9: =IF(G9=0,"NA",IF(H9=0,"NE",AVERAGEIFS(Puntuacion!$G:$G,Puntuacion!$A:$A,$A9,Puntuacion!$C:$C,$C9,Puntuacion!$D:$D,"Asignacion",Puntuacion!$G:$G,"<>NA",Puntuacion!$G:$G,"<>NE"))) | J9: =IF(COUNTIFS(Puntuacion!$A:$A,$A9,Puntuacion!$C:$C,$C9,Puntuacion!$D:$D,"Optimizacion",Puntuacion!$G:$G,"<>NA")>0,1,0) | K9: =IF(AND(J9=1,COUNTIFS(Puntuacion!$A:$A,$A9,Puntuacion!$C:$C,$C9,Puntuacion!$D:$D,"Optimizacion",Puntuacion!$G:$G,"NE")=0),1,0) | L9: =IF(J9=0,"NA",IF(K9=0,"NE",AVERAGEIFS(Puntuacion!$G:$G,Puntuacion!$A:$A,$A9,Puntuacion!$C:$C,$C9,Puntuacion!$D:$D,"Optimizacion",Puntuacion!$G:$G,"<>NA",Puntuacion!$G:$G,"<>NE"))) | M9: =IF(COUNTIFS(Puntuacion!$A:$A,$A9,Puntuacion!$C:$C,$C9,Puntuacion!$D:$D,"Automatizacion",Puntuacion!$G:$G,"<>NA")>0,1,0) | N9: =IF(AND(M9=1,COUNTIFS(Puntuacion!$A:$A,$A9,Puntuacion!$C:$C,$C9,Puntuacion!$D:$D,"Automatizacion",Puntuacion!$G:$G,"NE")=0),1,0) | O9: =IF(M9=0,"NA",IF(N9=0,"NE",AVERAGEIFS(Puntuacion!$G:$G,Puntuacion!$A:$A,$A9,Puntuacion!$C:$C,$C9,Puntuacion!$D:$D,"Automatizacion",Puntuacion!$G:$G,"<>NA",Puntuacion!$G:$G,"<>NE"))) | P9: =IF(COUNTIFS(Puntuacion!$A:$A,$A9,Puntuacion!$C:$C,$C9,Puntuacion!$D:$D,"Multicloud",Puntuacion!$G:$G,"<>NA")>0,1,0) | Q9: =IF(AND(P9=1,COUNTIFS(Puntuacion!$A:$A,$A9,Puntuacion!$C:$C,$C9,Puntuacion!$D:$D,"Multicloud",Puntuacion!$G:$G,"NE")=0),1,0) | R9: =IF(P9=0,"NA",IF(Q9=0,"NE",AVERAGEIFS(Puntuacion!$G:$G,Puntuacion!$A:$A,$A9,Puntuacion!$C:$C,$C9,Puntuacion!$D:$D,"Multicloud",Puntuacion!$G:$G,"<>NA",Puntuacion!$G:$G,"<>NE"))) | S9: =IF(COUNTIFS(Puntuacion!$A:$A,$A9,Puntuacion!$C:$C,$C9,Puntuacion!$D:$D,"Integracion",Puntuacion!$G:$G,"<>NA")>0,1,0) | T9: =IF(AND(S9=1,COUNTIFS(Puntuacion!$A:$A,$A9,Puntuacion!$C:$C,$C9,Puntuacion!$D:$D,"Integracion",Puntuacion!$G:$G,"NE")=0),1,0) | U9: =IF(S9=0,"NA",IF(T9=0,"NE",AVERAGEIFS(Puntuacion!$G:$G,Puntuacion!$A:$A,$A9,Puntuacion!$C:$C,$C9,Puntuacion!$D:$D,"Integracion",Puntuacion!$G:$G,"<>NA",Puntuacion!$G:$G,"<>NE"))) | V9: =IF(COUNTIFS(Puntuacion!$A:$A,$A9,Puntuacion!$C:$C,$C9,Puntuacion!$D:$D,"Adopcion",Puntuacion!$G:$G,"<>NA")>0,1,0) | W9: =IF(AND(V9=1,COUNTIFS(Puntuacion!$A:$A,$A9,Puntuacion!$C:$C,$C9,Puntuacion!$D:$D,"Adopcion",Puntuacion!$G:$G,"NE")=0),1,0) | X9: =IF(V9=0,"NA",IF(W9=0,"NE",AVERAGEIFS(Puntuacion!$G:$G,Puntuacion!$A:$A,$A9,Puntuacion!$C:$C,$C9,Puntuacion!$D:$D,"Adopcion",Puntuacion!$G:$G,"<>NA",Puntuacion!$G:$G,"<>NE"))) | Y9: =IF(COUNTIFS(Puntuacion!$A:$A,$A9,Puntuacion!$C:$C,$C9,Puntuacion!$D:$D,"Precio",Puntuacion!$G:$G,"<>NA")>0,1,0) | Z9: =IF(AND(Y9=1,COUNTIFS(Puntuacion!$A:$A,$A9,Puntuacion!$C:$C,$C9,Puntuacion!$D:$D,"Precio",Puntuacion!$G:$G,"NE")=0),1,0) | AA9: =IF(Y9=0,"NA",IF(Z9=0,"NE",AVERAGEIFS(Puntuacion!$G:$G,Puntuacion!$A:$A,$A9,Puntuacion!$C:$C,$C9,Puntuacion!$D:$D,"Precio",Puntuacion!$G:$G,"<>NA",Puntuacion!$G:$G,"<>NE"))) | AB9: =IF(COUNTIFS(Puntuacion!$A:$A,$A9,Puntuacion!$C:$C,$C9,Puntuacion!$D:$D,"Dependencia",Puntuacion!$G:$G,"<>NA")>0,1,0) | AC9: =IF(AND(AB9=1,COUNTIFS(Puntuacion!$A:$A,$A9,Puntuacion!$C:$C,$C9,Puntuacion!$D:$D,"Dependencia",Puntuacion!$G:$G,"NE")=0),1,0) | AD9: =IF(AB9=0,"NA",IF(AC9=0,"NE",AVERAGEIFS(Puntuacion!$G:$G,Puntuacion!$A:$A,$A9,Puntuacion!$C:$C,$C9,Puntuacion!$D:$D,"Dependencia",Puntuacion!$G:$G,"<>NA",Puntuacion!$G:$G,"<>NE"))) | AE9: =IFERROR(100*(E9*Pesos!$B$2+H9*Pesos!$B$3+K9*Pesos!$B$4+N9*Pesos!$B$5+Q9*Pesos!$B$6+T9*Pesos!$B$7+W9*Pesos!$B$8+Z9*Pesos!$B$9+AC9*Pesos!$B$10)/(D9*Pesos!$B$2+G9*Pesos!$B$3+J9*Pesos!$B$4+M9*Pesos!$B$5+P9*Pesos!$B$6+S9*Pesos!$B$7+V9*Pesos!$B$8+Y9*Pesos!$B$9+AB9*Pesos!$B$10),"Sin criterios aplicables") | AF9: =IFERROR(100*(E9*Pesos!$C$2+H9*Pesos!$C$3+K9*Pesos!$C$4+N9*Pesos!$C$5+Q9*Pesos!$C$6+T9*Pesos!$C$7+W9*Pesos!$C$8+Z9*Pesos!$C$9+AC9*Pesos!$C$10)/(D9*Pesos!$C$2+G9*Pesos!$C$3+J9*Pesos!$C$4+M9*Pesos!$C$5+P9*Pesos!$C$6+S9*Pesos!$C$7+V9*Pesos!$C$8+Y9*Pesos!$C$9+AB9*Pesos!$C$10),"Sin criterios aplicables") | AG9: =IF(OR(AE9="Sin criterios aplicables",AE9<70),"Insufficient evidence",100*(Pesos!$B$2*IF(E9=1,F9,0)+Pesos!$B$3*IF(H9=1,I9,0)+Pesos!$B$4*IF(K9=1,L9,0)+Pesos!$B$5*IF(N9=1,O9,0)+Pesos!$B$6*IF(Q9=1,R9,0)+Pesos!$B$7*IF(T9=1,U9,0)+Pesos!$B$8*IF(W9=1,X9,0)+Pesos!$B$9*IF(Z9=1,AA9,0)+Pesos!$B$10*IF(AC9=1,AD9,0))/(3*(Pesos!$B$2*E9+Pesos!$B$3*H9+Pesos!$B$4*K9+Pesos!$B$5*N9+Pesos!$B$6*Q9+Pesos!$B$7*T9+Pesos!$B$8*W9+Pesos!$B$9*Z9+Pesos!$B$10*AC9))) | AH9: =IF(OR(AF9="Sin criterios aplicables",AF9<70),"Insufficient evidence",100*(Pesos!$C$2*IF(E9=1,F9,0)+Pesos!$C$3*IF(H9=1,I9,0)+Pesos!$C$4*IF(K9=1,L9,0)+Pesos!$C$5*IF(N9=1,O9,0)+Pesos!$C$6*IF(Q9=1,R9,0)+Pesos!$C$7*IF(T9=1,U9,0)+Pesos!$C$8*IF(W9=1,X9,0)+Pesos!$C$9*IF(Z9=1,AA9,0)+Pesos!$C$10*IF(AC9=1,AD9,0))/(3*(Pesos!$C$2*E9+Pesos!$C$3*H9+Pesos!$C$4*K9+Pesos!$C$5*N9+Pesos!$C$6*Q9+Pesos!$C$7*T9+Pesos!$C$8*W9+Pesos!$C$9*Z9+Pesos!$C$10*AC9))) | AI9: =IF(AG9="Insufficient evidence","Insufficient evidence (cobertura<70%)",IF(AG9<50/3,"Insufficient",IF(AG9<50,"Basic",IF(AG9<250/3,"Solid","Advanced")))) | AJ9: =IF(AH9="Insufficient evidence","Insufficient evidence (cobertura<70%)",IF(AH9<50/3,"Insufficient",IF(AH9<50,"Basic",IF(AH9<250/3,"Solid","Advanced")))) | AK9: =IF(TRIM(IF(AND(ISNUMBER(F9),F9<1),"Visibilidad","") & " " & IF(AND(ISNUMBER(I9),I9<1),"Asignación",""))="","Ninguno",TRIM(IF(AND(ISNUMBER(F9),F9<1),"Visibilidad","") & " " & IF(AND(ISNUMBER(I9),I9<1),"Asignación","")))
A10: E1 | B10: Multicloud | C10: Finout | D10: =IF(COUNTIFS(Puntuacion!$A:$A,$A10,Puntuacion!$C:$C,$C10,Puntuacion!$D:$D,"Visibilidad",Puntuacion!$G:$G,"<>NA")>0,1,0) | E10: =IF(AND(D10=1,COUNTIFS(Puntuacion!$A:$A,$A10,Puntuacion!$C:$C,$C10,Puntuacion!$D:$D,"Visibilidad",Puntuacion!$G:$G,"NE")=0),1,0) | F10: =IF(D10=0,"NA",IF(E10=0,"NE",AVERAGEIFS(Puntuacion!$G:$G,Puntuacion!$A:$A,$A10,Puntuacion!$C:$C,$C10,Puntuacion!$D:$D,"Visibilidad",Puntuacion!$G:$G,"<>NA",Puntuacion!$G:$G,"<>NE"))) | G10: =IF(COUNTIFS(Puntuacion!$A:$A,$A10,Puntuacion!$C:$C,$C10,Puntuacion!$D:$D,"Asignacion",Puntuacion!$G:$G,"<>NA")>0,1,0) | H10: =IF(AND(G10=1,COUNTIFS(Puntuacion!$A:$A,$A10,Puntuacion!$C:$C,$C10,Puntuacion!$D:$D,"Asignacion",Puntuacion!$G:$G,"NE")=0),1,0) | I10: =IF(G10=0,"NA",IF(H10=0,"NE",AVERAGEIFS(Puntuacion!$G:$G,Puntuacion!$A:$A,$A10,Puntuacion!$C:$C,$C10,Puntuacion!$D:$D,"Asignacion",Puntuacion!$G:$G,"<>NA",Puntuacion!$G:$G,"<>NE"))) | J10: =IF(COUNTIFS(Puntuacion!$A:$A,$A10,Puntuacion!$C:$C,$C10,Puntuacion!$D:$D,"Optimizacion",Puntuacion!$G:$G,"<>NA")>0,1,0) | K10: =IF(AND(J10=1,COUNTIFS(Puntuacion!$A:$A,$A10,Puntuacion!$C:$C,$C10,Puntuacion!$D:$D,"Optimizacion",Puntuacion!$G:$G,"NE")=0),1,0) | L10: =IF(J10=0,"NA",IF(K10=0,"NE",AVERAGEIFS(Puntuacion!$G:$G,Puntuacion!$A:$A,$A10,Puntuacion!$C:$C,$C10,Puntuacion!$D:$D,"Optimizacion",Puntuacion!$G:$G,"<>NA",Puntuacion!$G:$G,"<>NE"))) | M10: =IF(COUNTIFS(Puntuacion!$A:$A,$A10,Puntuacion!$C:$C,$C10,Puntuacion!$D:$D,"Automatizacion",Puntuacion!$G:$G,"<>NA")>0,1,0) | N10: =IF(AND(M10=1,COUNTIFS(Puntuacion!$A:$A,$A10,Puntuacion!$C:$C,$C10,Puntuacion!$D:$D,"Automatizacion",Puntuacion!$G:$G,"NE")=0),1,0) | O10: =IF(M10=0,"NA",IF(N10=0,"NE",AVERAGEIFS(Puntuacion!$G:$G,Puntuacion!$A:$A,$A10,Puntuacion!$C:$C,$C10,Puntuacion!$D:$D,"Automatizacion",Puntuacion!$G:$G,"<>NA",Puntuacion!$G:$G,"<>NE"))) | P10: =IF(COUNTIFS(Puntuacion!$A:$A,$A10,Puntuacion!$C:$C,$C10,Puntuacion!$D:$D,"Multicloud",Puntuacion!$G:$G,"<>NA")>0,1,0) | Q10: =IF(AND(P10=1,COUNTIFS(Puntuacion!$A:$A,$A10,Puntuacion!$C:$C,$C10,Puntuacion!$D:$D,"Multicloud",Puntuacion!$G:$G,"NE")=0),1,0) | R10: =IF(P10=0,"NA",IF(Q10=0,"NE",AVERAGEIFS(Puntuacion!$G:$G,Puntuacion!$A:$A,$A10,Puntuacion!$C:$C,$C10,Puntuacion!$D:$D,"Multicloud",Puntuacion!$G:$G,"<>NA",Puntuacion!$G:$G,"<>NE"))) | S10: =IF(COUNTIFS(Puntuacion!$A:$A,$A10,Puntuacion!$C:$C,$C10,Puntuacion!$D:$D,"Integracion",Puntuacion!$G:$G,"<>NA")>0,1,0) | T10: =IF(AND(S10=1,COUNTIFS(Puntuacion!$A:$A,$A10,Puntuacion!$C:$C,$C10,Puntuacion!$D:$D,"Integracion",Puntuacion!$G:$G,"NE")=0),1,0) | U10: =IF(S10=0,"NA",IF(T10=0,"NE",AVERAGEIFS(Puntuacion!$G:$G,Puntuacion!$A:$A,$A10,Puntuacion!$C:$C,$C10,Puntuacion!$D:$D,"Integracion",Puntuacion!$G:$G,"<>NA",Puntuacion!$G:$G,"<>NE"))) | V10: =IF(COUNTIFS(Puntuacion!$A:$A,$A10,Puntuacion!$C:$C,$C10,Puntuacion!$D:$D,"Adopcion",Puntuacion!$G:$G,"<>NA")>0,1,0) | W10: =IF(AND(V10=1,COUNTIFS(Puntuacion!$A:$A,$A10,Puntuacion!$C:$C,$C10,Puntuacion!$D:$D,"Adopcion",Puntuacion!$G:$G,"NE")=0),1,0) | X10: =IF(V10=0,"NA",IF(W10=0,"NE",AVERAGEIFS(Puntuacion!$G:$G,Puntuacion!$A:$A,$A10,Puntuacion!$C:$C,$C10,Puntuacion!$D:$D,"Adopcion",Puntuacion!$G:$G,"<>NA",Puntuacion!$G:$G,"<>NE"))) | Y10: =IF(COUNTIFS(Puntuacion!$A:$A,$A10,Puntuacion!$C:$C,$C10,Puntuacion!$D:$D,"Precio",Puntuacion!$G:$G,"<>NA")>0,1,0) | Z10: =IF(AND(Y10=1,COUNTIFS(Puntuacion!$A:$A,$A10,Puntuacion!$C:$C,$C10,Puntuacion!$D:$D,"Precio",Puntuacion!$G:$G,"NE")=0),1,0) | AA10: =IF(Y10=0,"NA",IF(Z10=0,"NE",AVERAGEIFS(Puntuacion!$G:$G,Puntuacion!$A:$A,$A10,Puntuacion!$C:$C,$C10,Puntuacion!$D:$D,"Precio",Puntuacion!$G:$G,"<>NA",Puntuacion!$G:$G,"<>NE"))) | AB10: =IF(COUNTIFS(Puntuacion!$A:$A,$A10,Puntuacion!$C:$C,$C10,Puntuacion!$D:$D,"Dependencia",Puntuacion!$G:$G,"<>NA")>0,1,0) | AC10: =IF(AND(AB10=1,COUNTIFS(Puntuacion!$A:$A,$A10,Puntuacion!$C:$C,$C10,Puntuacion!$D:$D,"Dependencia",Puntuacion!$G:$G,"NE")=0),1,0) | AD10: =IF(AB10=0,"NA",IF(AC10=0,"NE",AVERAGEIFS(Puntuacion!$G:$G,Puntuacion!$A:$A,$A10,Puntuacion!$C:$C,$C10,Puntuacion!$D:$D,"Dependencia",Puntuacion!$G:$G,"<>NA",Puntuacion!$G:$G,"<>NE"))) | AE10: =IFERROR(100*(E10*Pesos!$B$2+H10*Pesos!$B$3+K10*Pesos!$B$4+N10*Pesos!$B$5+Q10*Pesos!$B$6+T10*Pesos!$B$7+W10*Pesos!$B$8+Z10*Pesos!$B$9+AC10*Pesos!$B$10)/(D10*Pesos!$B$2+G10*Pesos!$B$3+J10*Pesos!$B$4+M10*Pesos!$B$5+P10*Pesos!$B$6+S10*Pesos!$B$7+V10*Pesos!$B$8+Y10*Pesos!$B$9+AB10*Pesos!$B$10),"Sin criterios aplicables") | AF10: =IFERROR(100*(E10*Pesos!$C$2+H10*Pesos!$C$3+K10*Pesos!$C$4+N10*Pesos!$C$5+Q10*Pesos!$C$6+T10*Pesos!$C$7+W10*Pesos!$C$8+Z10*Pesos!$C$9+AC10*Pesos!$C$10)/(D10*Pesos!$C$2+G10*Pesos!$C$3+J10*Pesos!$C$4+M10*Pesos!$C$5+P10*Pesos!$C$6+S10*Pesos!$C$7+V10*Pesos!$C$8+Y10*Pesos!$C$9+AB10*Pesos!$C$10),"Sin criterios aplicables") | AG10: =IF(OR(AE10="Sin criterios aplicables",AE10<70),"Insufficient evidence",100*(Pesos!$B$2*IF(E10=1,F10,0)+Pesos!$B$3*IF(H10=1,I10,0)+Pesos!$B$4*IF(K10=1,L10,0)+Pesos!$B$5*IF(N10=1,O10,0)+Pesos!$B$6*IF(Q10=1,R10,0)+Pesos!$B$7*IF(T10=1,U10,0)+Pesos!$B$8*IF(W10=1,X10,0)+Pesos!$B$9*IF(Z10=1,AA10,0)+Pesos!$B$10*IF(AC10=1,AD10,0))/(3*(Pesos!$B$2*E10+Pesos!$B$3*H10+Pesos!$B$4*K10+Pesos!$B$5*N10+Pesos!$B$6*Q10+Pesos!$B$7*T10+Pesos!$B$8*W10+Pesos!$B$9*Z10+Pesos!$B$10*AC10))) | AH10: =IF(OR(AF10="Sin criterios aplicables",AF10<70),"Insufficient evidence",100*(Pesos!$C$2*IF(E10=1,F10,0)+Pesos!$C$3*IF(H10=1,I10,0)+Pesos!$C$4*IF(K10=1,L10,0)+Pesos!$C$5*IF(N10=1,O10,0)+Pesos!$C$6*IF(Q10=1,R10,0)+Pesos!$C$7*IF(T10=1,U10,0)+Pesos!$C$8*IF(W10=1,X10,0)+Pesos!$C$9*IF(Z10=1,AA10,0)+Pesos!$C$10*IF(AC10=1,AD10,0))/(3*(Pesos!$C$2*E10+Pesos!$C$3*H10+Pesos!$C$4*K10+Pesos!$C$5*N10+Pesos!$C$6*Q10+Pesos!$C$7*T10+Pesos!$C$8*W10+Pesos!$C$9*Z10+Pesos!$C$10*AC10))) | AI10: =IF(AG10="Insufficient evidence","Insufficient evidence (cobertura<70%)",IF(AG10<50/3,"Insufficient",IF(AG10<50,"Basic",IF(AG10<250/3,"Solid","Advanced")))) | AJ10: =IF(AH10="Insufficient evidence","Insufficient evidence (cobertura<70%)",IF(AH10<50/3,"Insufficient",IF(AH10<50,"Basic",IF(AH10<250/3,"Solid","Advanced")))) | AK10: =IF(TRIM(IF(AND(ISNUMBER(F10),F10<1),"Visibilidad","") & " " & IF(AND(ISNUMBER(I10),I10<1),"Asignación",""))="","Ninguno",TRIM(IF(AND(ISNUMBER(F10),F10<1),"Visibilidad","") & " " & IF(AND(ISNUMBER(I10),I10<1),"Asignación","")))
A11: E1 | B11: Multicloud | C11: Vantage | D11: =IF(COUNTIFS(Puntuacion!$A:$A,$A11,Puntuacion!$C:$C,$C11,Puntuacion!$D:$D,"Visibilidad",Puntuacion!$G:$G,"<>NA")>0,1,0) | E11: =IF(AND(D11=1,COUNTIFS(Puntuacion!$A:$A,$A11,Puntuacion!$C:$C,$C11,Puntuacion!$D:$D,"Visibilidad",Puntuacion!$G:$G,"NE")=0),1,0) | F11: =IF(D11=0,"NA",IF(E11=0,"NE",AVERAGEIFS(Puntuacion!$G:$G,Puntuacion!$A:$A,$A11,Puntuacion!$C:$C,$C11,Puntuacion!$D:$D,"Visibilidad",Puntuacion!$G:$G,"<>NA",Puntuacion!$G:$G,"<>NE"))) | G11: =IF(COUNTIFS(Puntuacion!$A:$A,$A11,Puntuacion!$C:$C,$C11,Puntuacion!$D:$D,"Asignacion",Puntuacion!$G:$G,"<>NA")>0,1,0) | H11: =IF(AND(G11=1,COUNTIFS(Puntuacion!$A:$A,$A11,Puntuacion!$C:$C,$C11,Puntuacion!$D:$D,"Asignacion",Puntuacion!$G:$G,"NE")=0),1,0) | I11: =IF(G11=0,"NA",IF(H11=0,"NE",AVERAGEIFS(Puntuacion!$G:$G,Puntuacion!$A:$A,$A11,Puntuacion!$C:$C,$C11,Puntuacion!$D:$D,"Asignacion",Puntuacion!$G:$G,"<>NA",Puntuacion!$G:$G,"<>NE"))) | J11: =IF(COUNTIFS(Puntuacion!$A:$A,$A11,Puntuacion!$C:$C,$C11,Puntuacion!$D:$D,"Optimizacion",Puntuacion!$G:$G,"<>NA")>0,1,0) | K11: =IF(AND(J11=1,COUNTIFS(Puntuacion!$A:$A,$A11,Puntuacion!$C:$C,$C11,Puntuacion!$D:$D,"Optimizacion",Puntuacion!$G:$G,"NE")=0),1,0) | L11: =IF(J11=0,"NA",IF(K11=0,"NE",AVERAGEIFS(Puntuacion!$G:$G,Puntuacion!$A:$A,$A11,Puntuacion!$C:$C,$C11,Puntuacion!$D:$D,"Optimizacion",Puntuacion!$G:$G,"<>NA",Puntuacion!$G:$G,"<>NE"))) | M11: =IF(COUNTIFS(Puntuacion!$A:$A,$A11,Puntuacion!$C:$C,$C11,Puntuacion!$D:$D,"Automatizacion",Puntuacion!$G:$G,"<>NA")>0,1,0) | N11: =IF(AND(M11=1,COUNTIFS(Puntuacion!$A:$A,$A11,Puntuacion!$C:$C,$C11,Puntuacion!$D:$D,"Automatizacion",Puntuacion!$G:$G,"NE")=0),1,0) | O11: =IF(M11=0,"NA",IF(N11=0,"NE",AVERAGEIFS(Puntuacion!$G:$G,Puntuacion!$A:$A,$A11,Puntuacion!$C:$C,$C11,Puntuacion!$D:$D,"Automatizacion",Puntuacion!$G:$G,"<>NA",Puntuacion!$G:$G,"<>NE"))) | P11: =IF(COUNTIFS(Puntuacion!$A:$A,$A11,Puntuacion!$C:$C,$C11,Puntuacion!$D:$D,"Multicloud",Puntuacion!$G:$G,"<>NA")>0,1,0) | Q11: =IF(AND(P11=1,COUNTIFS(Puntuacion!$A:$A,$A11,Puntuacion!$C:$C,$C11,Puntuacion!$D:$D,"Multicloud",Puntuacion!$G:$G,"NE")=0),1,0) | R11: =IF(P11=0,"NA",IF(Q11=0,"NE",AVERAGEIFS(Puntuacion!$G:$G,Puntuacion!$A:$A,$A11,Puntuacion!$C:$C,$C11,Puntuacion!$D:$D,"Multicloud",Puntuacion!$G:$G,"<>NA",Puntuacion!$G:$G,"<>NE"))) | S11: =IF(COUNTIFS(Puntuacion!$A:$A,$A11,Puntuacion!$C:$C,$C11,Puntuacion!$D:$D,"Integracion",Puntuacion!$G:$G,"<>NA")>0,1,0) | T11: =IF(AND(S11=1,COUNTIFS(Puntuacion!$A:$A,$A11,Puntuacion!$C:$C,$C11,Puntuacion!$D:$D,"Integracion",Puntuacion!$G:$G,"NE")=0),1,0) | U11: =IF(S11=0,"NA",IF(T11=0,"NE",AVERAGEIFS(Puntuacion!$G:$G,Puntuacion!$A:$A,$A11,Puntuacion!$C:$C,$C11,Puntuacion!$D:$D,"Integracion",Puntuacion!$G:$G,"<>NA",Puntuacion!$G:$G,"<>NE"))) | V11: =IF(COUNTIFS(Puntuacion!$A:$A,$A11,Puntuacion!$C:$C,$C11,Puntuacion!$D:$D,"Adopcion",Puntuacion!$G:$G,"<>NA")>0,1,0) | W11: =IF(AND(V11=1,COUNTIFS(Puntuacion!$A:$A,$A11,Puntuacion!$C:$C,$C11,Puntuacion!$D:$D,"Adopcion",Puntuacion!$G:$G,"NE")=0),1,0) | X11: =IF(V11=0,"NA",IF(W11=0,"NE",AVERAGEIFS(Puntuacion!$G:$G,Puntuacion!$A:$A,$A11,Puntuacion!$C:$C,$C11,Puntuacion!$D:$D,"Adopcion",Puntuacion!$G:$G,"<>NA",Puntuacion!$G:$G,"<>NE"))) | Y11: =IF(COUNTIFS(Puntuacion!$A:$A,$A11,Puntuacion!$C:$C,$C11,Puntuacion!$D:$D,"Precio",Puntuacion!$G:$G,"<>NA")>0,1,0) | Z11: =IF(AND(Y11=1,COUNTIFS(Puntuacion!$A:$A,$A11,Puntuacion!$C:$C,$C11,Puntuacion!$D:$D,"Precio",Puntuacion!$G:$G,"NE")=0),1,0) | AA11: =IF(Y11=0,"NA",IF(Z11=0,"NE",AVERAGEIFS(Puntuacion!$G:$G,Puntuacion!$A:$A,$A11,Puntuacion!$C:$C,$C11,Puntuacion!$D:$D,"Precio",Puntuacion!$G:$G,"<>NA",Puntuacion!$G:$G,"<>NE"))) | AB11: =IF(COUNTIFS(Puntuacion!$A:$A,$A11,Puntuacion!$C:$C,$C11,Puntuacion!$D:$D,"Dependencia",Puntuacion!$G:$G,"<>NA")>0,1,0) | AC11: =IF(AND(AB11=1,COUNTIFS(Puntuacion!$A:$A,$A11,Puntuacion!$C:$C,$C11,Puntuacion!$D:$D,"Dependencia",Puntuacion!$G:$G,"NE")=0),1,0) | AD11: =IF(AB11=0,"NA",IF(AC11=0,"NE",AVERAGEIFS(Puntuacion!$G:$G,Puntuacion!$A:$A,$A11,Puntuacion!$C:$C,$C11,Puntuacion!$D:$D,"Dependencia",Puntuacion!$G:$G,"<>NA",Puntuacion!$G:$G,"<>NE"))) | AE11: =IFERROR(100*(E11*Pesos!$B$2+H11*Pesos!$B$3+K11*Pesos!$B$4+N11*Pesos!$B$5+Q11*Pesos!$B$6+T11*Pesos!$B$7+W11*Pesos!$B$8+Z11*Pesos!$B$9+AC11*Pesos!$B$10)/(D11*Pesos!$B$2+G11*Pesos!$B$3+J11*Pesos!$B$4+M11*Pesos!$B$5+P11*Pesos!$B$6+S11*Pesos!$B$7+V11*Pesos!$B$8+Y11*Pesos!$B$9+AB11*Pesos!$B$10),"Sin criterios aplicables") | AF11: =IFERROR(100*(E11*Pesos!$C$2+H11*Pesos!$C$3+K11*Pesos!$C$4+N11*Pesos!$C$5+Q11*Pesos!$C$6+T11*Pesos!$C$7+W11*Pesos!$C$8+Z11*Pesos!$C$9+AC11*Pesos!$C$10)/(D11*Pesos!$C$2+G11*Pesos!$C$3+J11*Pesos!$C$4+M11*Pesos!$C$5+P11*Pesos!$C$6+S11*Pesos!$C$7+V11*Pesos!$C$8+Y11*Pesos!$C$9+AB11*Pesos!$C$10),"Sin criterios aplicables") | AG11: =IF(OR(AE11="Sin criterios aplicables",AE11<70),"Insufficient evidence",100*(Pesos!$B$2*IF(E11=1,F11,0)+Pesos!$B$3*IF(H11=1,I11,0)+Pesos!$B$4*IF(K11=1,L11,0)+Pesos!$B$5*IF(N11=1,O11,0)+Pesos!$B$6*IF(Q11=1,R11,0)+Pesos!$B$7*IF(T11=1,U11,0)+Pesos!$B$8*IF(W11=1,X11,0)+Pesos!$B$9*IF(Z11=1,AA11,0)+Pesos!$B$10*IF(AC11=1,AD11,0))/(3*(Pesos!$B$2*E11+Pesos!$B$3*H11+Pesos!$B$4*K11+Pesos!$B$5*N11+Pesos!$B$6*Q11+Pesos!$B$7*T11+Pesos!$B$8*W11+Pesos!$B$9*Z11+Pesos!$B$10*AC11))) | AH11: =IF(OR(AF11="Sin criterios aplicables",AF11<70),"Insufficient evidence",100*(Pesos!$C$2*IF(E11=1,F11,0)+Pesos!$C$3*IF(H11=1,I11,0)+Pesos!$C$4*IF(K11=1,L11,0)+Pesos!$C$5*IF(N11=1,O11,0)+Pesos!$C$6*IF(Q11=1,R11,0)+Pesos!$C$7*IF(T11=1,U11,0)+Pesos!$C$8*IF(W11=1,X11,0)+Pesos!$C$9*IF(Z11=1,AA11,0)+Pesos!$C$10*IF(AC11=1,AD11,0))/(3*(Pesos!$C$2*E11+Pesos!$C$3*H11+Pesos!$C$4*K11+Pesos!$C$5*N11+Pesos!$C$6*Q11+Pesos!$C$7*T11+Pesos!$C$8*W11+Pesos!$C$9*Z11+Pesos!$C$10*AC11))) | AI11: =IF(AG11="Insufficient evidence","Insufficient evidence (cobertura<70%)",IF(AG11<50/3,"Insufficient",IF(AG11<50,"Basic",IF(AG11<250/3,"Solid","Advanced")))) | AJ11: =IF(AH11="Insufficient evidence","Insufficient evidence (cobertura<70%)",IF(AH11<50/3,"Insufficient",IF(AH11<50,"Basic",IF(AH11<250/3,"Solid","Advanced")))) | AK11: =IF(TRIM(IF(AND(ISNUMBER(F11),F11<1),"Visibilidad","") & " " & IF(AND(ISNUMBER(I11),I11<1),"Asignación",""))="","Ninguno",TRIM(IF(AND(ISNUMBER(F11),F11<1),"Visibilidad","") & " " & IF(AND(ISNUMBER(I11),I11<1),"Asignación","")))
A12: E1 | B12: Multicloud | C12: nOps | D12: =IF(COUNTIFS(Puntuacion!$A:$A,$A12,Puntuacion!$C:$C,$C12,Puntuacion!$D:$D,"Visibilidad",Puntuacion!$G:$G,"<>NA")>0,1,0) | E12: =IF(AND(D12=1,COUNTIFS(Puntuacion!$A:$A,$A12,Puntuacion!$C:$C,$C12,Puntuacion!$D:$D,"Visibilidad",Puntuacion!$G:$G,"NE")=0),1,0) | F12: =IF(D12=0,"NA",IF(E12=0,"NE",AVERAGEIFS(Puntuacion!$G:$G,Puntuacion!$A:$A,$A12,Puntuacion!$C:$C,$C12,Puntuacion!$D:$D,"Visibilidad",Puntuacion!$G:$G,"<>NA",Puntuacion!$G:$G,"<>NE"))) | G12: =IF(COUNTIFS(Puntuacion!$A:$A,$A12,Puntuacion!$C:$C,$C12,Puntuacion!$D:$D,"Asignacion",Puntuacion!$G:$G,"<>NA")>0,1,0) | H12: =IF(AND(G12=1,COUNTIFS(Puntuacion!$A:$A,$A12,Puntuacion!$C:$C,$C12,Puntuacion!$D:$D,"Asignacion",Puntuacion!$G:$G,"NE")=0),1,0) | I12: =IF(G12=0,"NA",IF(H12=0,"NE",AVERAGEIFS(Puntuacion!$G:$G,Puntuacion!$A:$A,$A12,Puntuacion!$C:$C,$C12,Puntuacion!$D:$D,"Asignacion",Puntuacion!$G:$G,"<>NA",Puntuacion!$G:$G,"<>NE"))) | J12: =IF(COUNTIFS(Puntuacion!$A:$A,$A12,Puntuacion!$C:$C,$C12,Puntuacion!$D:$D,"Optimizacion",Puntuacion!$G:$G,"<>NA")>0,1,0) | K12: =IF(AND(J12=1,COUNTIFS(Puntuacion!$A:$A,$A12,Puntuacion!$C:$C,$C12,Puntuacion!$D:$D,"Optimizacion",Puntuacion!$G:$G,"NE")=0),1,0) | L12: =IF(J12=0,"NA",IF(K12=0,"NE",AVERAGEIFS(Puntuacion!$G:$G,Puntuacion!$A:$A,$A12,Puntuacion!$C:$C,$C12,Puntuacion!$D:$D,"Optimizacion",Puntuacion!$G:$G,"<>NA",Puntuacion!$G:$G,"<>NE"))) | M12: =IF(COUNTIFS(Puntuacion!$A:$A,$A12,Puntuacion!$C:$C,$C12,Puntuacion!$D:$D,"Automatizacion",Puntuacion!$G:$G,"<>NA")>0,1,0) | N12: =IF(AND(M12=1,COUNTIFS(Puntuacion!$A:$A,$A12,Puntuacion!$C:$C,$C12,Puntuacion!$D:$D,"Automatizacion",Puntuacion!$G:$G,"NE")=0),1,0) | O12: =IF(M12=0,"NA",IF(N12=0,"NE",AVERAGEIFS(Puntuacion!$G:$G,Puntuacion!$A:$A,$A12,Puntuacion!$C:$C,$C12,Puntuacion!$D:$D,"Automatizacion",Puntuacion!$G:$G,"<>NA",Puntuacion!$G:$G,"<>NE"))) | P12: =IF(COUNTIFS(Puntuacion!$A:$A,$A12,Puntuacion!$C:$C,$C12,Puntuacion!$D:$D,"Multicloud",Puntuacion!$G:$G,"<>NA")>0,1,0) | Q12: =IF(AND(P12=1,COUNTIFS(Puntuacion!$A:$A,$A12,Puntuacion!$C:$C,$C12,Puntuacion!$D:$D,"Multicloud",Puntuacion!$G:$G,"NE")=0),1,0) | R12: =IF(P12=0,"NA",IF(Q12=0,"NE",AVERAGEIFS(Puntuacion!$G:$G,Puntuacion!$A:$A,$A12,Puntuacion!$C:$C,$C12,Puntuacion!$D:$D,"Multicloud",Puntuacion!$G:$G,"<>NA",Puntuacion!$G:$G,"<>NE"))) | S12: =IF(COUNTIFS(Puntuacion!$A:$A,$A12,Puntuacion!$C:$C,$C12,Puntuacion!$D:$D,"Integracion",Puntuacion!$G:$G,"<>NA")>0,1,0) | T12: =IF(AND(S12=1,COUNTIFS(Puntuacion!$A:$A,$A12,Puntuacion!$C:$C,$C12,Puntuacion!$D:$D,"Integracion",Puntuacion!$G:$G,"NE")=0),1,0) | U12: =IF(S12=0,"NA",IF(T12=0,"NE",AVERAGEIFS(Puntuacion!$G:$G,Puntuacion!$A:$A,$A12,Puntuacion!$C:$C,$C12,Puntuacion!$D:$D,"Integracion",Puntuacion!$G:$G,"<>NA",Puntuacion!$G:$G,"<>NE"))) | V12: =IF(COUNTIFS(Puntuacion!$A:$A,$A12,Puntuacion!$C:$C,$C12,Puntuacion!$D:$D,"Adopcion",Puntuacion!$G:$G,"<>NA")>0,1,0) | W12: =IF(AND(V12=1,COUNTIFS(Puntuacion!$A:$A,$A12,Puntuacion!$C:$C,$C12,Puntuacion!$D:$D,"Adopcion",Puntuacion!$G:$G,"NE")=0),1,0) | X12: =IF(V12=0,"NA",IF(W12=0,"NE",AVERAGEIFS(Puntuacion!$G:$G,Puntuacion!$A:$A,$A12,Puntuacion!$C:$C,$C12,Puntuacion!$D:$D,"Adopcion",Puntuacion!$G:$G,"<>NA",Puntuacion!$G:$G,"<>NE"))) | Y12: =IF(COUNTIFS(Puntuacion!$A:$A,$A12,Puntuacion!$C:$C,$C12,Puntuacion!$D:$D,"Precio",Puntuacion!$G:$G,"<>NA")>0,1,0) | Z12: =IF(AND(Y12=1,COUNTIFS(Puntuacion!$A:$A,$A12,Puntuacion!$C:$C,$C12,Puntuacion!$D:$D,"Precio",Puntuacion!$G:$G,"NE")=0),1,0) | AA12: =IF(Y12=0,"NA",IF(Z12=0,"NE",AVERAGEIFS(Puntuacion!$G:$G,Puntuacion!$A:$A,$A12,Puntuacion!$C:$C,$C12,Puntuacion!$D:$D,"Precio",Puntuacion!$G:$G,"<>NA",Puntuacion!$G:$G,"<>NE"))) | AB12: =IF(COUNTIFS(Puntuacion!$A:$A,$A12,Puntuacion!$C:$C,$C12,Puntuacion!$D:$D,"Dependencia",Puntuacion!$G:$G,"<>NA")>0,1,0) | AC12: =IF(AND(AB12=1,COUNTIFS(Puntuacion!$A:$A,$A12,Puntuacion!$C:$C,$C12,Puntuacion!$D:$D,"Dependencia",Puntuacion!$G:$G,"NE")=0),1,0) | AD12: =IF(AB12=0,"NA",IF(AC12=0,"NE",AVERAGEIFS(Puntuacion!$G:$G,Puntuacion!$A:$A,$A12,Puntuacion!$C:$C,$C12,Puntuacion!$D:$D,"Dependencia",Puntuacion!$G:$G,"<>NA",Puntuacion!$G:$G,"<>NE"))) | AE12: =IFERROR(100*(E12*Pesos!$B$2+H12*Pesos!$B$3+K12*Pesos!$B$4+N12*Pesos!$B$5+Q12*Pesos!$B$6+T12*Pesos!$B$7+W12*Pesos!$B$8+Z12*Pesos!$B$9+AC12*Pesos!$B$10)/(D12*Pesos!$B$2+G12*Pesos!$B$3+J12*Pesos!$B$4+M12*Pesos!$B$5+P12*Pesos!$B$6+S12*Pesos!$B$7+V12*Pesos!$B$8+Y12*Pesos!$B$9+AB12*Pesos!$B$10),"Sin criterios aplicables") | AF12: =IFERROR(100*(E12*Pesos!$C$2+H12*Pesos!$C$3+K12*Pesos!$C$4+N12*Pesos!$C$5+Q12*Pesos!$C$6+T12*Pesos!$C$7+W12*Pesos!$C$8+Z12*Pesos!$C$9+AC12*Pesos!$C$10)/(D12*Pesos!$C$2+G12*Pesos!$C$3+J12*Pesos!$C$4+M12*Pesos!$C$5+P12*Pesos!$C$6+S12*Pesos!$C$7+V12*Pesos!$C$8+Y12*Pesos!$C$9+AB12*Pesos!$C$10),"Sin criterios aplicables") | AG12: =IF(OR(AE12="Sin criterios aplicables",AE12<70),"Insufficient evidence",100*(Pesos!$B$2*IF(E12=1,F12,0)+Pesos!$B$3*IF(H12=1,I12,0)+Pesos!$B$4*IF(K12=1,L12,0)+Pesos!$B$5*IF(N12=1,O12,0)+Pesos!$B$6*IF(Q12=1,R12,0)+Pesos!$B$7*IF(T12=1,U12,0)+Pesos!$B$8*IF(W12=1,X12,0)+Pesos!$B$9*IF(Z12=1,AA12,0)+Pesos!$B$10*IF(AC12=1,AD12,0))/(3*(Pesos!$B$2*E12+Pesos!$B$3*H12+Pesos!$B$4*K12+Pesos!$B$5*N12+Pesos!$B$6*Q12+Pesos!$B$7*T12+Pesos!$B$8*W12+Pesos!$B$9*Z12+Pesos!$B$10*AC12))) | AH12: =IF(OR(AF12="Sin criterios aplicables",AF12<70),"Insufficient evidence",100*(Pesos!$C$2*IF(E12=1,F12,0)+Pesos!$C$3*IF(H12=1,I12,0)+Pesos!$C$4*IF(K12=1,L12,0)+Pesos!$C$5*IF(N12=1,O12,0)+Pesos!$C$6*IF(Q12=1,R12,0)+Pesos!$C$7*IF(T12=1,U12,0)+Pesos!$C$8*IF(W12=1,X12,0)+Pesos!$C$9*IF(Z12=1,AA12,0)+Pesos!$C$10*IF(AC12=1,AD12,0))/(3*(Pesos!$C$2*E12+Pesos!$C$3*H12+Pesos!$C$4*K12+Pesos!$C$5*N12+Pesos!$C$6*Q12+Pesos!$C$7*T12+Pesos!$C$8*W12+Pesos!$C$9*Z12+Pesos!$C$10*AC12))) | AI12: =IF(AG12="Insufficient evidence","Insufficient evidence (cobertura<70%)",IF(AG12<50/3,"Insufficient",IF(AG12<50,"Basic",IF(AG12<250/3,"Solid","Advanced")))) | AJ12: =IF(AH12="Insufficient evidence","Insufficient evidence (cobertura<70%)",IF(AH12<50/3,"Insufficient",IF(AH12<50,"Basic",IF(AH12<250/3,"Solid","Advanced")))) | AK12: =IF(TRIM(IF(AND(ISNUMBER(F12),F12<1),"Visibilidad","") & " " & IF(AND(ISNUMBER(I12),I12<1),"Asignación",""))="","Ninguno",TRIM(IF(AND(ISNUMBER(F12),F12<1),"Visibilidad","") & " " & IF(AND(ISNUMBER(I12),I12<1),"Asignación","")))
A13: E2 | B13: Cloud nativa | C13: AWS Cost Explorer | D13: =IF(COUNTIFS(Puntuacion!$A:$A,$A13,Puntuacion!$C:$C,$C13,Puntuacion!$D:$D,"Visibilidad",Puntuacion!$G:$G,"<>NA")>0,1,0) | E13: =IF(AND(D13=1,COUNTIFS(Puntuacion!$A:$A,$A13,Puntuacion!$C:$C,$C13,Puntuacion!$D:$D,"Visibilidad",Puntuacion!$G:$G,"NE")=0),1,0) | F13: =IF(D13=0,"NA",IF(E13=0,"NE",AVERAGEIFS(Puntuacion!$G:$G,Puntuacion!$A:$A,$A13,Puntuacion!$C:$C,$C13,Puntuacion!$D:$D,"Visibilidad",Puntuacion!$G:$G,"<>NA",Puntuacion!$G:$G,"<>NE"))) | G13: =IF(COUNTIFS(Puntuacion!$A:$A,$A13,Puntuacion!$C:$C,$C13,Puntuacion!$D:$D,"Asignacion",Puntuacion!$G:$G,"<>NA")>0,1,0) | H13: =IF(AND(G13=1,COUNTIFS(Puntuacion!$A:$A,$A13,Puntuacion!$C:$C,$C13,Puntuacion!$D:$D,"Asignacion",Puntuacion!$G:$G,"NE")=0),1,0) | I13: =IF(G13=0,"NA",IF(H13=0,"NE",AVERAGEIFS(Puntuacion!$G:$G,Puntuacion!$A:$A,$A13,Puntuacion!$C:$C,$C13,Puntuacion!$D:$D,"Asignacion",Puntuacion!$G:$G,"<>NA",Puntuacion!$G:$G,"<>NE"))) | J13: =IF(COUNTIFS(Puntuacion!$A:$A,$A13,Puntuacion!$C:$C,$C13,Puntuacion!$D:$D,"Optimizacion",Puntuacion!$G:$G,"<>NA")>0,1,0) | K13: =IF(AND(J13=1,COUNTIFS(Puntuacion!$A:$A,$A13,Puntuacion!$C:$C,$C13,Puntuacion!$D:$D,"Optimizacion",Puntuacion!$G:$G,"NE")=0),1,0) | L13: =IF(J13=0,"NA",IF(K13=0,"NE",AVERAGEIFS(Puntuacion!$G:$G,Puntuacion!$A:$A,$A13,Puntuacion!$C:$C,$C13,Puntuacion!$D:$D,"Optimizacion",Puntuacion!$G:$G,"<>NA",Puntuacion!$G:$G,"<>NE"))) | M13: =IF(COUNTIFS(Puntuacion!$A:$A,$A13,Puntuacion!$C:$C,$C13,Puntuacion!$D:$D,"Automatizacion",Puntuacion!$G:$G,"<>NA")>0,1,0) | N13: =IF(AND(M13=1,COUNTIFS(Puntuacion!$A:$A,$A13,Puntuacion!$C:$C,$C13,Puntuacion!$D:$D,"Automatizacion",Puntuacion!$G:$G,"NE")=0),1,0) | O13: =IF(M13=0,"NA",IF(N13=0,"NE",AVERAGEIFS(Puntuacion!$G:$G,Puntuacion!$A:$A,$A13,Puntuacion!$C:$C,$C13,Puntuacion!$D:$D,"Automatizacion",Puntuacion!$G:$G,"<>NA",Puntuacion!$G:$G,"<>NE"))) | P13: =IF(COUNTIFS(Puntuacion!$A:$A,$A13,Puntuacion!$C:$C,$C13,Puntuacion!$D:$D,"Multicloud",Puntuacion!$G:$G,"<>NA")>0,1,0) | Q13: =IF(AND(P13=1,COUNTIFS(Puntuacion!$A:$A,$A13,Puntuacion!$C:$C,$C13,Puntuacion!$D:$D,"Multicloud",Puntuacion!$G:$G,"NE")=0),1,0) | R13: =IF(P13=0,"NA",IF(Q13=0,"NE",AVERAGEIFS(Puntuacion!$G:$G,Puntuacion!$A:$A,$A13,Puntuacion!$C:$C,$C13,Puntuacion!$D:$D,"Multicloud",Puntuacion!$G:$G,"<>NA",Puntuacion!$G:$G,"<>NE"))) | S13: =IF(COUNTIFS(Puntuacion!$A:$A,$A13,Puntuacion!$C:$C,$C13,Puntuacion!$D:$D,"Integracion",Puntuacion!$G:$G,"<>NA")>0,1,0) | T13: =IF(AND(S13=1,COUNTIFS(Puntuacion!$A:$A,$A13,Puntuacion!$C:$C,$C13,Puntuacion!$D:$D,"Integracion",Puntuacion!$G:$G,"NE")=0),1,0) | U13: =IF(S13=0,"NA",IF(T13=0,"NE",AVERAGEIFS(Puntuacion!$G:$G,Puntuacion!$A:$A,$A13,Puntuacion!$C:$C,$C13,Puntuacion!$D:$D,"Integracion",Puntuacion!$G:$G,"<>NA",Puntuacion!$G:$G,"<>NE"))) | V13: =IF(COUNTIFS(Puntuacion!$A:$A,$A13,Puntuacion!$C:$C,$C13,Puntuacion!$D:$D,"Adopcion",Puntuacion!$G:$G,"<>NA")>0,1,0) | W13: =IF(AND(V13=1,COUNTIFS(Puntuacion!$A:$A,$A13,Puntuacion!$C:$C,$C13,Puntuacion!$D:$D,"Adopcion",Puntuacion!$G:$G,"NE")=0),1,0) | X13: =IF(V13=0,"NA",IF(W13=0,"NE",AVERAGEIFS(Puntuacion!$G:$G,Puntuacion!$A:$A,$A13,Puntuacion!$C:$C,$C13,Puntuacion!$D:$D,"Adopcion",Puntuacion!$G:$G,"<>NA",Puntuacion!$G:$G,"<>NE"))) | Y13: =IF(COUNTIFS(Puntuacion!$A:$A,$A13,Puntuacion!$C:$C,$C13,Puntuacion!$D:$D,"Precio",Puntuacion!$G:$G,"<>NA")>0,1,0) | Z13: =IF(AND(Y13=1,COUNTIFS(Puntuacion!$A:$A,$A13,Puntuacion!$C:$C,$C13,Puntuacion!$D:$D,"Precio",Puntuacion!$G:$G,"NE")=0),1,0) | AA13: =IF(Y13=0,"NA",IF(Z13=0,"NE",AVERAGEIFS(Puntuacion!$G:$G,Puntuacion!$A:$A,$A13,Puntuacion!$C:$C,$C13,Puntuacion!$D:$D,"Precio",Puntuacion!$G:$G,"<>NA",Puntuacion!$G:$G,"<>NE"))) | AB13: =IF(COUNTIFS(Puntuacion!$A:$A,$A13,Puntuacion!$C:$C,$C13,Puntuacion!$D:$D,"Dependencia",Puntuacion!$G:$G,"<>NA")>0,1,0) | AC13: =IF(AND(AB13=1,COUNTIFS(Puntuacion!$A:$A,$A13,Puntuacion!$C:$C,$C13,Puntuacion!$D:$D,"Dependencia",Puntuacion!$G:$G,"NE")=0),1,0) | AD13: =IF(AB13=0,"NA",IF(AC13=0,"NE",AVERAGEIFS(Puntuacion!$G:$G,Puntuacion!$A:$A,$A13,Puntuacion!$C:$C,$C13,Puntuacion!$D:$D,"Dependencia",Puntuacion!$G:$G,"<>NA",Puntuacion!$G:$G,"<>NE"))) | AE13: =IFERROR(100*(E13*Pesos!$B$2+H13*Pesos!$B$3+K13*Pesos!$B$4+N13*Pesos!$B$5+Q13*Pesos!$B$6+T13*Pesos!$B$7+W13*Pesos!$B$8+Z13*Pesos!$B$9+AC13*Pesos!$B$10)/(D13*Pesos!$B$2+G13*Pesos!$B$3+J13*Pesos!$B$4+M13*Pesos!$B$5+P13*Pesos!$B$6+S13*Pesos!$B$7+V13*Pesos!$B$8+Y13*Pesos!$B$9+AB13*Pesos!$B$10),"Sin criterios aplicables") | AF13: =IFERROR(100*(E13*Pesos!$C$2+H13*Pesos!$C$3+K13*Pesos!$C$4+N13*Pesos!$C$5+Q13*Pesos!$C$6+T13*Pesos!$C$7+W13*Pesos!$C$8+Z13*Pesos!$C$9+AC13*Pesos!$C$10)/(D13*Pesos!$C$2+G13*Pesos!$C$3+J13*Pesos!$C$4+M13*Pesos!$C$5+P13*Pesos!$C$6+S13*Pesos!$C$7+V13*Pesos!$C$8+Y13*Pesos!$C$9+AB13*Pesos!$C$10),"Sin criterios aplicables") | AG13: =IF(OR(AE13="Sin criterios aplicables",AE13<70),"Insufficient evidence",100*(Pesos!$B$2*IF(E13=1,F13,0)+Pesos!$B$3*IF(H13=1,I13,0)+Pesos!$B$4*IF(K13=1,L13,0)+Pesos!$B$5*IF(N13=1,O13,0)+Pesos!$B$6*IF(Q13=1,R13,0)+Pesos!$B$7*IF(T13=1,U13,0)+Pesos!$B$8*IF(W13=1,X13,0)+Pesos!$B$9*IF(Z13=1,AA13,0)+Pesos!$B$10*IF(AC13=1,AD13,0))/(3*(Pesos!$B$2*E13+Pesos!$B$3*H13+Pesos!$B$4*K13+Pesos!$B$5*N13+Pesos!$B$6*Q13+Pesos!$B$7*T13+Pesos!$B$8*W13+Pesos!$B$9*Z13+Pesos!$B$10*AC13))) | AH13: =IF(OR(AF13="Sin criterios aplicables",AF13<70),"Insufficient evidence",100*(Pesos!$C$2*IF(E13=1,F13,0)+Pesos!$C$3*IF(H13=1,I13,0)+Pesos!$C$4*IF(K13=1,L13,0)+Pesos!$C$5*IF(N13=1,O13,0)+Pesos!$C$6*IF(Q13=1,R13,0)+Pesos!$C$7*IF(T13=1,U13,0)+Pesos!$C$8*IF(W13=1,X13,0)+Pesos!$C$9*IF(Z13=1,AA13,0)+Pesos!$C$10*IF(AC13=1,AD13,0))/(3*(Pesos!$C$2*E13+Pesos!$C$3*H13+Pesos!$C$4*K13+Pesos!$C$5*N13+Pesos!$C$6*Q13+Pesos!$C$7*T13+Pesos!$C$8*W13+Pesos!$C$9*Z13+Pesos!$C$10*AC13))) | AI13: =IF(AG13="Insufficient evidence","Insufficient evidence (cobertura<70%)",IF(AG13<50/3,"Insufficient",IF(AG13<50,"Basic",IF(AG13<250/3,"Solid","Advanced")))) | AJ13: =IF(AH13="Insufficient evidence","Insufficient evidence (cobertura<70%)",IF(AH13<50/3,"Insufficient",IF(AH13<50,"Basic",IF(AH13<250/3,"Solid","Advanced")))) | AK13: =IF(TRIM(IF(AND(ISNUMBER(R13),R13<1),"Multicloud","") & " " & IF(AND(ISNUMBER(AA13),AA13<1),"Precio",""))="","Ninguno",TRIM(IF(AND(ISNUMBER(R13),R13<1),"Multicloud","") & " " & IF(AND(ISNUMBER(AA13),AA13<1),"Precio","")))
A14: E2 | B14: Cloud nativa | C14: AWS Cost Optimization Hub | D14: =IF(COUNTIFS(Puntuacion!$A:$A,$A14,Puntuacion!$C:$C,$C14,Puntuacion!$D:$D,"Visibilidad",Puntuacion!$G:$G,"<>NA")>0,1,0) | E14: =IF(AND(D14=1,COUNTIFS(Puntuacion!$A:$A,$A14,Puntuacion!$C:$C,$C14,Puntuacion!$D:$D,"Visibilidad",Puntuacion!$G:$G,"NE")=0),1,0) | F14: =IF(D14=0,"NA",IF(E14=0,"NE",AVERAGEIFS(Puntuacion!$G:$G,Puntuacion!$A:$A,$A14,Puntuacion!$C:$C,$C14,Puntuacion!$D:$D,"Visibilidad",Puntuacion!$G:$G,"<>NA",Puntuacion!$G:$G,"<>NE"))) | G14: =IF(COUNTIFS(Puntuacion!$A:$A,$A14,Puntuacion!$C:$C,$C14,Puntuacion!$D:$D,"Asignacion",Puntuacion!$G:$G,"<>NA")>0,1,0) | H14: =IF(AND(G14=1,COUNTIFS(Puntuacion!$A:$A,$A14,Puntuacion!$C:$C,$C14,Puntuacion!$D:$D,"Asignacion",Puntuacion!$G:$G,"NE")=0),1,0) | I14: =IF(G14=0,"NA",IF(H14=0,"NE",AVERAGEIFS(Puntuacion!$G:$G,Puntuacion!$A:$A,$A14,Puntuacion!$C:$C,$C14,Puntuacion!$D:$D,"Asignacion",Puntuacion!$G:$G,"<>NA",Puntuacion!$G:$G,"<>NE"))) | J14: =IF(COUNTIFS(Puntuacion!$A:$A,$A14,Puntuacion!$C:$C,$C14,Puntuacion!$D:$D,"Optimizacion",Puntuacion!$G:$G,"<>NA")>0,1,0) | K14: =IF(AND(J14=1,COUNTIFS(Puntuacion!$A:$A,$A14,Puntuacion!$C:$C,$C14,Puntuacion!$D:$D,"Optimizacion",Puntuacion!$G:$G,"NE")=0),1,0) | L14: =IF(J14=0,"NA",IF(K14=0,"NE",AVERAGEIFS(Puntuacion!$G:$G,Puntuacion!$A:$A,$A14,Puntuacion!$C:$C,$C14,Puntuacion!$D:$D,"Optimizacion",Puntuacion!$G:$G,"<>NA",Puntuacion!$G:$G,"<>NE"))) | M14: =IF(COUNTIFS(Puntuacion!$A:$A,$A14,Puntuacion!$C:$C,$C14,Puntuacion!$D:$D,"Automatizacion",Puntuacion!$G:$G,"<>NA")>0,1,0) | N14: =IF(AND(M14=1,COUNTIFS(Puntuacion!$A:$A,$A14,Puntuacion!$C:$C,$C14,Puntuacion!$D:$D,"Automatizacion",Puntuacion!$G:$G,"NE")=0),1,0) | O14: =IF(M14=0,"NA",IF(N14=0,"NE",AVERAGEIFS(Puntuacion!$G:$G,Puntuacion!$A:$A,$A14,Puntuacion!$C:$C,$C14,Puntuacion!$D:$D,"Automatizacion",Puntuacion!$G:$G,"<>NA",Puntuacion!$G:$G,"<>NE"))) | P14: =IF(COUNTIFS(Puntuacion!$A:$A,$A14,Puntuacion!$C:$C,$C14,Puntuacion!$D:$D,"Multicloud",Puntuacion!$G:$G,"<>NA")>0,1,0) | Q14: =IF(AND(P14=1,COUNTIFS(Puntuacion!$A:$A,$A14,Puntuacion!$C:$C,$C14,Puntuacion!$D:$D,"Multicloud",Puntuacion!$G:$G,"NE")=0),1,0) | R14: =IF(P14=0,"NA",IF(Q14=0,"NE",AVERAGEIFS(Puntuacion!$G:$G,Puntuacion!$A:$A,$A14,Puntuacion!$C:$C,$C14,Puntuacion!$D:$D,"Multicloud",Puntuacion!$G:$G,"<>NA",Puntuacion!$G:$G,"<>NE"))) | S14: =IF(COUNTIFS(Puntuacion!$A:$A,$A14,Puntuacion!$C:$C,$C14,Puntuacion!$D:$D,"Integracion",Puntuacion!$G:$G,"<>NA")>0,1,0) | T14: =IF(AND(S14=1,COUNTIFS(Puntuacion!$A:$A,$A14,Puntuacion!$C:$C,$C14,Puntuacion!$D:$D,"Integracion",Puntuacion!$G:$G,"NE")=0),1,0) | U14: =IF(S14=0,"NA",IF(T14=0,"NE",AVERAGEIFS(Puntuacion!$G:$G,Puntuacion!$A:$A,$A14,Puntuacion!$C:$C,$C14,Puntuacion!$D:$D,"Integracion",Puntuacion!$G:$G,"<>NA",Puntuacion!$G:$G,"<>NE"))) | V14: =IF(COUNTIFS(Puntuacion!$A:$A,$A14,Puntuacion!$C:$C,$C14,Puntuacion!$D:$D,"Adopcion",Puntuacion!$G:$G,"<>NA")>0,1,0) | W14: =IF(AND(V14=1,COUNTIFS(Puntuacion!$A:$A,$A14,Puntuacion!$C:$C,$C14,Puntuacion!$D:$D,"Adopcion",Puntuacion!$G:$G,"NE")=0),1,0) | X14: =IF(V14=0,"NA",IF(W14=0,"NE",AVERAGEIFS(Puntuacion!$G:$G,Puntuacion!$A:$A,$A14,Puntuacion!$C:$C,$C14,Puntuacion!$D:$D,"Adopcion",Puntuacion!$G:$G,"<>NA",Puntuacion!$G:$G,"<>NE"))) | Y14: =IF(COUNTIFS(Puntuacion!$A:$A,$A14,Puntuacion!$C:$C,$C14,Puntuacion!$D:$D,"Precio",Puntuacion!$G:$G,"<>NA")>0,1,0) | Z14: =IF(AND(Y14=1,COUNTIFS(Puntuacion!$A:$A,$A14,Puntuacion!$C:$C,$C14,Puntuacion!$D:$D,"Precio",Puntuacion!$G:$G,"NE")=0),1,0) | AA14: =IF(Y14=0,"NA",IF(Z14=0,"NE",AVERAGEIFS(Puntuacion!$G:$G,Puntuacion!$A:$A,$A14,Puntuacion!$C:$C,$C14,Puntuacion!$D:$D,"Precio",Puntuacion!$G:$G,"<>NA",Puntuacion!$G:$G,"<>NE"))) | AB14: =IF(COUNTIFS(Puntuacion!$A:$A,$A14,Puntuacion!$C:$C,$C14,Puntuacion!$D:$D,"Dependencia",Puntuacion!$G:$G,"<>NA")>0,1,0) | AC14: =IF(AND(AB14=1,COUNTIFS(Puntuacion!$A:$A,$A14,Puntuacion!$C:$C,$C14,Puntuacion!$D:$D,"Dependencia",Puntuacion!$G:$G,"NE")=0),1,0) | AD14: =IF(AB14=0,"NA",IF(AC14=0,"NE",AVERAGEIFS(Puntuacion!$G:$G,Puntuacion!$A:$A,$A14,Puntuacion!$C:$C,$C14,Puntuacion!$D:$D,"Dependencia",Puntuacion!$G:$G,"<>NA",Puntuacion!$G:$G,"<>NE"))) | AE14: =IFERROR(100*(E14*Pesos!$B$2+H14*Pesos!$B$3+K14*Pesos!$B$4+N14*Pesos!$B$5+Q14*Pesos!$B$6+T14*Pesos!$B$7+W14*Pesos!$B$8+Z14*Pesos!$B$9+AC14*Pesos!$B$10)/(D14*Pesos!$B$2+G14*Pesos!$B$3+J14*Pesos!$B$4+M14*Pesos!$B$5+P14*Pesos!$B$6+S14*Pesos!$B$7+V14*Pesos!$B$8+Y14*Pesos!$B$9+AB14*Pesos!$B$10),"Sin criterios aplicables") | AF14: =IFERROR(100*(E14*Pesos!$C$2+H14*Pesos!$C$3+K14*Pesos!$C$4+N14*Pesos!$C$5+Q14*Pesos!$C$6+T14*Pesos!$C$7+W14*Pesos!$C$8+Z14*Pesos!$C$9+AC14*Pesos!$C$10)/(D14*Pesos!$C$2+G14*Pesos!$C$3+J14*Pesos!$C$4+M14*Pesos!$C$5+P14*Pesos!$C$6+S14*Pesos!$C$7+V14*Pesos!$C$8+Y14*Pesos!$C$9+AB14*Pesos!$C$10),"Sin criterios aplicables") | AG14: =IF(OR(AE14="Sin criterios aplicables",AE14<70),"Insufficient evidence",100*(Pesos!$B$2*IF(E14=1,F14,0)+Pesos!$B$3*IF(H14=1,I14,0)+Pesos!$B$4*IF(K14=1,L14,0)+Pesos!$B$5*IF(N14=1,O14,0)+Pesos!$B$6*IF(Q14=1,R14,0)+Pesos!$B$7*IF(T14=1,U14,0)+Pesos!$B$8*IF(W14=1,X14,0)+Pesos!$B$9*IF(Z14=1,AA14,0)+Pesos!$B$10*IF(AC14=1,AD14,0))/(3*(Pesos!$B$2*E14+Pesos!$B$3*H14+Pesos!$B$4*K14+Pesos!$B$5*N14+Pesos!$B$6*Q14+Pesos!$B$7*T14+Pesos!$B$8*W14+Pesos!$B$9*Z14+Pesos!$B$10*AC14))) | AH14: =IF(OR(AF14="Sin criterios aplicables",AF14<70),"Insufficient evidence",100*(Pesos!$C$2*IF(E14=1,F14,0)+Pesos!$C$3*IF(H14=1,I14,0)+Pesos!$C$4*IF(K14=1,L14,0)+Pesos!$C$5*IF(N14=1,O14,0)+Pesos!$C$6*IF(Q14=1,R14,0)+Pesos!$C$7*IF(T14=1,U14,0)+Pesos!$C$8*IF(W14=1,X14,0)+Pesos!$C$9*IF(Z14=1,AA14,0)+Pesos!$C$10*IF(AC14=1,AD14,0))/(3*(Pesos!$C$2*E14+Pesos!$C$3*H14+Pesos!$C$4*K14+Pesos!$C$5*N14+Pesos!$C$6*Q14+Pesos!$C$7*T14+Pesos!$C$8*W14+Pesos!$C$9*Z14+Pesos!$C$10*AC14))) | AI14: =IF(AG14="Insufficient evidence","Insufficient evidence (cobertura<70%)",IF(AG14<50/3,"Insufficient",IF(AG14<50,"Basic",IF(AG14<250/3,"Solid","Advanced")))) | AJ14: =IF(AH14="Insufficient evidence","Insufficient evidence (cobertura<70%)",IF(AH14<50/3,"Insufficient",IF(AH14<50,"Basic",IF(AH14<250/3,"Solid","Advanced")))) | AK14: =IF(TRIM(IF(AND(ISNUMBER(R14),R14<1),"Multicloud","") & " " & IF(AND(ISNUMBER(AA14),AA14<1),"Precio",""))="","Ninguno",TRIM(IF(AND(ISNUMBER(R14),R14<1),"Multicloud","") & " " & IF(AND(ISNUMBER(AA14),AA14<1),"Precio","")))
A15: E2 | B15: Cloud nativa | C15: Azure Cost Management | D15: =IF(COUNTIFS(Puntuacion!$A:$A,$A15,Puntuacion!$C:$C,$C15,Puntuacion!$D:$D,"Visibilidad",Puntuacion!$G:$G,"<>NA")>0,1,0) | E15: =IF(AND(D15=1,COUNTIFS(Puntuacion!$A:$A,$A15,Puntuacion!$C:$C,$C15,Puntuacion!$D:$D,"Visibilidad",Puntuacion!$G:$G,"NE")=0),1,0) | F15: =IF(D15=0,"NA",IF(E15=0,"NE",AVERAGEIFS(Puntuacion!$G:$G,Puntuacion!$A:$A,$A15,Puntuacion!$C:$C,$C15,Puntuacion!$D:$D,"Visibilidad",Puntuacion!$G:$G,"<>NA",Puntuacion!$G:$G,"<>NE"))) | G15: =IF(COUNTIFS(Puntuacion!$A:$A,$A15,Puntuacion!$C:$C,$C15,Puntuacion!$D:$D,"Asignacion",Puntuacion!$G:$G,"<>NA")>0,1,0) | H15: =IF(AND(G15=1,COUNTIFS(Puntuacion!$A:$A,$A15,Puntuacion!$C:$C,$C15,Puntuacion!$D:$D,"Asignacion",Puntuacion!$G:$G,"NE")=0),1,0) | I15: =IF(G15=0,"NA",IF(H15=0,"NE",AVERAGEIFS(Puntuacion!$G:$G,Puntuacion!$A:$A,$A15,Puntuacion!$C:$C,$C15,Puntuacion!$D:$D,"Asignacion",Puntuacion!$G:$G,"<>NA",Puntuacion!$G:$G,"<>NE"))) | J15: =IF(COUNTIFS(Puntuacion!$A:$A,$A15,Puntuacion!$C:$C,$C15,Puntuacion!$D:$D,"Optimizacion",Puntuacion!$G:$G,"<>NA")>0,1,0) | K15: =IF(AND(J15=1,COUNTIFS(Puntuacion!$A:$A,$A15,Puntuacion!$C:$C,$C15,Puntuacion!$D:$D,"Optimizacion",Puntuacion!$G:$G,"NE")=0),1,0) | L15: =IF(J15=0,"NA",IF(K15=0,"NE",AVERAGEIFS(Puntuacion!$G:$G,Puntuacion!$A:$A,$A15,Puntuacion!$C:$C,$C15,Puntuacion!$D:$D,"Optimizacion",Puntuacion!$G:$G,"<>NA",Puntuacion!$G:$G,"<>NE"))) | M15: =IF(COUNTIFS(Puntuacion!$A:$A,$A15,Puntuacion!$C:$C,$C15,Puntuacion!$D:$D,"Automatizacion",Puntuacion!$G:$G,"<>NA")>0,1,0) | N15: =IF(AND(M15=1,COUNTIFS(Puntuacion!$A:$A,$A15,Puntuacion!$C:$C,$C15,Puntuacion!$D:$D,"Automatizacion",Puntuacion!$G:$G,"NE")=0),1,0) | O15: =IF(M15=0,"NA",IF(N15=0,"NE",AVERAGEIFS(Puntuacion!$G:$G,Puntuacion!$A:$A,$A15,Puntuacion!$C:$C,$C15,Puntuacion!$D:$D,"Automatizacion",Puntuacion!$G:$G,"<>NA",Puntuacion!$G:$G,"<>NE"))) | P15: =IF(COUNTIFS(Puntuacion!$A:$A,$A15,Puntuacion!$C:$C,$C15,Puntuacion!$D:$D,"Multicloud",Puntuacion!$G:$G,"<>NA")>0,1,0) | Q15: =IF(AND(P15=1,COUNTIFS(Puntuacion!$A:$A,$A15,Puntuacion!$C:$C,$C15,Puntuacion!$D:$D,"Multicloud",Puntuacion!$G:$G,"NE")=0),1,0) | R15: =IF(P15=0,"NA",IF(Q15=0,"NE",AVERAGEIFS(Puntuacion!$G:$G,Puntuacion!$A:$A,$A15,Puntuacion!$C:$C,$C15,Puntuacion!$D:$D,"Multicloud",Puntuacion!$G:$G,"<>NA",Puntuacion!$G:$G,"<>NE"))) | S15: =IF(COUNTIFS(Puntuacion!$A:$A,$A15,Puntuacion!$C:$C,$C15,Puntuacion!$D:$D,"Integracion",Puntuacion!$G:$G,"<>NA")>0,1,0) | T15: =IF(AND(S15=1,COUNTIFS(Puntuacion!$A:$A,$A15,Puntuacion!$C:$C,$C15,Puntuacion!$D:$D,"Integracion",Puntuacion!$G:$G,"NE")=0),1,0) | U15: =IF(S15=0,"NA",IF(T15=0,"NE",AVERAGEIFS(Puntuacion!$G:$G,Puntuacion!$A:$A,$A15,Puntuacion!$C:$C,$C15,Puntuacion!$D:$D,"Integracion",Puntuacion!$G:$G,"<>NA",Puntuacion!$G:$G,"<>NE"))) | V15: =IF(COUNTIFS(Puntuacion!$A:$A,$A15,Puntuacion!$C:$C,$C15,Puntuacion!$D:$D,"Adopcion",Puntuacion!$G:$G,"<>NA")>0,1,0) | W15: =IF(AND(V15=1,COUNTIFS(Puntuacion!$A:$A,$A15,Puntuacion!$C:$C,$C15,Puntuacion!$D:$D,"Adopcion",Puntuacion!$G:$G,"NE")=0),1,0) | X15: =IF(V15=0,"NA",IF(W15=0,"NE",AVERAGEIFS(Puntuacion!$G:$G,Puntuacion!$A:$A,$A15,Puntuacion!$C:$C,$C15,Puntuacion!$D:$D,"Adopcion",Puntuacion!$G:$G,"<>NA",Puntuacion!$G:$G,"<>NE"))) | Y15: =IF(COUNTIFS(Puntuacion!$A:$A,$A15,Puntuacion!$C:$C,$C15,Puntuacion!$D:$D,"Precio",Puntuacion!$G:$G,"<>NA")>0,1,0) | Z15: =IF(AND(Y15=1,COUNTIFS(Puntuacion!$A:$A,$A15,Puntuacion!$C:$C,$C15,Puntuacion!$D:$D,"Precio",Puntuacion!$G:$G,"NE")=0),1,0) | AA15: =IF(Y15=0,"NA",IF(Z15=0,"NE",AVERAGEIFS(Puntuacion!$G:$G,Puntuacion!$A:$A,$A15,Puntuacion!$C:$C,$C15,Puntuacion!$D:$D,"Precio",Puntuacion!$G:$G,"<>NA",Puntuacion!$G:$G,"<>NE"))) | AB15: =IF(COUNTIFS(Puntuacion!$A:$A,$A15,Puntuacion!$C:$C,$C15,Puntuacion!$D:$D,"Dependencia",Puntuacion!$G:$G,"<>NA")>0,1,0) | AC15: =IF(AND(AB15=1,COUNTIFS(Puntuacion!$A:$A,$A15,Puntuacion!$C:$C,$C15,Puntuacion!$D:$D,"Dependencia",Puntuacion!$G:$G,"NE")=0),1,0) | AD15: =IF(AB15=0,"NA",IF(AC15=0,"NE",AVERAGEIFS(Puntuacion!$G:$G,Puntuacion!$A:$A,$A15,Puntuacion!$C:$C,$C15,Puntuacion!$D:$D,"Dependencia",Puntuacion!$G:$G,"<>NA",Puntuacion!$G:$G,"<>NE"))) | AE15: =IFERROR(100*(E15*Pesos!$B$2+H15*Pesos!$B$3+K15*Pesos!$B$4+N15*Pesos!$B$5+Q15*Pesos!$B$6+T15*Pesos!$B$7+W15*Pesos!$B$8+Z15*Pesos!$B$9+AC15*Pesos!$B$10)/(D15*Pesos!$B$2+G15*Pesos!$B$3+J15*Pesos!$B$4+M15*Pesos!$B$5+P15*Pesos!$B$6+S15*Pesos!$B$7+V15*Pesos!$B$8+Y15*Pesos!$B$9+AB15*Pesos!$B$10),"Sin criterios aplicables") | AF15: =IFERROR(100*(E15*Pesos!$C$2+H15*Pesos!$C$3+K15*Pesos!$C$4+N15*Pesos!$C$5+Q15*Pesos!$C$6+T15*Pesos!$C$7+W15*Pesos!$C$8+Z15*Pesos!$C$9+AC15*Pesos!$C$10)/(D15*Pesos!$C$2+G15*Pesos!$C$3+J15*Pesos!$C$4+M15*Pesos!$C$5+P15*Pesos!$C$6+S15*Pesos!$C$7+V15*Pesos!$C$8+Y15*Pesos!$C$9+AB15*Pesos!$C$10),"Sin criterios aplicables") | AG15: =IF(OR(AE15="Sin criterios aplicables",AE15<70),"Insufficient evidence",100*(Pesos!$B$2*IF(E15=1,F15,0)+Pesos!$B$3*IF(H15=1,I15,0)+Pesos!$B$4*IF(K15=1,L15,0)+Pesos!$B$5*IF(N15=1,O15,0)+Pesos!$B$6*IF(Q15=1,R15,0)+Pesos!$B$7*IF(T15=1,U15,0)+Pesos!$B$8*IF(W15=1,X15,0)+Pesos!$B$9*IF(Z15=1,AA15,0)+Pesos!$B$10*IF(AC15=1,AD15,0))/(3*(Pesos!$B$2*E15+Pesos!$B$3*H15+Pesos!$B$4*K15+Pesos!$B$5*N15+Pesos!$B$6*Q15+Pesos!$B$7*T15+Pesos!$B$8*W15+Pesos!$B$9*Z15+Pesos!$B$10*AC15))) | AH15: =IF(OR(AF15="Sin criterios aplicables",AF15<70),"Insufficient evidence",100*(Pesos!$C$2*IF(E15=1,F15,0)+Pesos!$C$3*IF(H15=1,I15,0)+Pesos!$C$4*IF(K15=1,L15,0)+Pesos!$C$5*IF(N15=1,O15,0)+Pesos!$C$6*IF(Q15=1,R15,0)+Pesos!$C$7*IF(T15=1,U15,0)+Pesos!$C$8*IF(W15=1,X15,0)+Pesos!$C$9*IF(Z15=1,AA15,0)+Pesos!$C$10*IF(AC15=1,AD15,0))/(3*(Pesos!$C$2*E15+Pesos!$C$3*H15+Pesos!$C$4*K15+Pesos!$C$5*N15+Pesos!$C$6*Q15+Pesos!$C$7*T15+Pesos!$C$8*W15+Pesos!$C$9*Z15+Pesos!$C$10*AC15))) | AI15: =IF(AG15="Insufficient evidence","Insufficient evidence (cobertura<70%)",IF(AG15<50/3,"Insufficient",IF(AG15<50,"Basic",IF(AG15<250/3,"Solid","Advanced")))) | AJ15: =IF(AH15="Insufficient evidence","Insufficient evidence (cobertura<70%)",IF(AH15<50/3,"Insufficient",IF(AH15<50,"Basic",IF(AH15<250/3,"Solid","Advanced")))) | AK15: =IF(TRIM(IF(AND(ISNUMBER(R15),R15<1),"Multicloud","") & " " & IF(AND(ISNUMBER(AA15),AA15<1),"Precio",""))="","Ninguno",TRIM(IF(AND(ISNUMBER(R15),R15<1),"Multicloud","") & " " & IF(AND(ISNUMBER(AA15),AA15<1),"Precio","")))
A16: E2 | B16: Cloud nativa | C16: Google Cloud Billing | D16: =IF(COUNTIFS(Puntuacion!$A:$A,$A16,Puntuacion!$C:$C,$C16,Puntuacion!$D:$D,"Visibilidad",Puntuacion!$G:$G,"<>NA")>0,1,0) | E16: =IF(AND(D16=1,COUNTIFS(Puntuacion!$A:$A,$A16,Puntuacion!$C:$C,$C16,Puntuacion!$D:$D,"Visibilidad",Puntuacion!$G:$G,"NE")=0),1,0) | F16: =IF(D16=0,"NA",IF(E16=0,"NE",AVERAGEIFS(Puntuacion!$G:$G,Puntuacion!$A:$A,$A16,Puntuacion!$C:$C,$C16,Puntuacion!$D:$D,"Visibilidad",Puntuacion!$G:$G,"<>NA",Puntuacion!$G:$G,"<>NE"))) | G16: =IF(COUNTIFS(Puntuacion!$A:$A,$A16,Puntuacion!$C:$C,$C16,Puntuacion!$D:$D,"Asignacion",Puntuacion!$G:$G,"<>NA")>0,1,0) | H16: =IF(AND(G16=1,COUNTIFS(Puntuacion!$A:$A,$A16,Puntuacion!$C:$C,$C16,Puntuacion!$D:$D,"Asignacion",Puntuacion!$G:$G,"NE")=0),1,0) | I16: =IF(G16=0,"NA",IF(H16=0,"NE",AVERAGEIFS(Puntuacion!$G:$G,Puntuacion!$A:$A,$A16,Puntuacion!$C:$C,$C16,Puntuacion!$D:$D,"Asignacion",Puntuacion!$G:$G,"<>NA",Puntuacion!$G:$G,"<>NE"))) | J16: =IF(COUNTIFS(Puntuacion!$A:$A,$A16,Puntuacion!$C:$C,$C16,Puntuacion!$D:$D,"Optimizacion",Puntuacion!$G:$G,"<>NA")>0,1,0) | K16: =IF(AND(J16=1,COUNTIFS(Puntuacion!$A:$A,$A16,Puntuacion!$C:$C,$C16,Puntuacion!$D:$D,"Optimizacion",Puntuacion!$G:$G,"NE")=0),1,0) | L16: =IF(J16=0,"NA",IF(K16=0,"NE",AVERAGEIFS(Puntuacion!$G:$G,Puntuacion!$A:$A,$A16,Puntuacion!$C:$C,$C16,Puntuacion!$D:$D,"Optimizacion",Puntuacion!$G:$G,"<>NA",Puntuacion!$G:$G,"<>NE"))) | M16: =IF(COUNTIFS(Puntuacion!$A:$A,$A16,Puntuacion!$C:$C,$C16,Puntuacion!$D:$D,"Automatizacion",Puntuacion!$G:$G,"<>NA")>0,1,0) | N16: =IF(AND(M16=1,COUNTIFS(Puntuacion!$A:$A,$A16,Puntuacion!$C:$C,$C16,Puntuacion!$D:$D,"Automatizacion",Puntuacion!$G:$G,"NE")=0),1,0) | O16: =IF(M16=0,"NA",IF(N16=0,"NE",AVERAGEIFS(Puntuacion!$G:$G,Puntuacion!$A:$A,$A16,Puntuacion!$C:$C,$C16,Puntuacion!$D:$D,"Automatizacion",Puntuacion!$G:$G,"<>NA",Puntuacion!$G:$G,"<>NE"))) | P16: =IF(COUNTIFS(Puntuacion!$A:$A,$A16,Puntuacion!$C:$C,$C16,Puntuacion!$D:$D,"Multicloud",Puntuacion!$G:$G,"<>NA")>0,1,0) | Q16: =IF(AND(P16=1,COUNTIFS(Puntuacion!$A:$A,$A16,Puntuacion!$C:$C,$C16,Puntuacion!$D:$D,"Multicloud",Puntuacion!$G:$G,"NE")=0),1,0) | R16: =IF(P16=0,"NA",IF(Q16=0,"NE",AVERAGEIFS(Puntuacion!$G:$G,Puntuacion!$A:$A,$A16,Puntuacion!$C:$C,$C16,Puntuacion!$D:$D,"Multicloud",Puntuacion!$G:$G,"<>NA",Puntuacion!$G:$G,"<>NE"))) | S16: =IF(COUNTIFS(Puntuacion!$A:$A,$A16,Puntuacion!$C:$C,$C16,Puntuacion!$D:$D,"Integracion",Puntuacion!$G:$G,"<>NA")>0,1,0) | T16: =IF(AND(S16=1,COUNTIFS(Puntuacion!$A:$A,$A16,Puntuacion!$C:$C,$C16,Puntuacion!$D:$D,"Integracion",Puntuacion!$G:$G,"NE")=0),1,0) | U16: =IF(S16=0,"NA",IF(T16=0,"NE",AVERAGEIFS(Puntuacion!$G:$G,Puntuacion!$A:$A,$A16,Puntuacion!$C:$C,$C16,Puntuacion!$D:$D,"Integracion",Puntuacion!$G:$G,"<>NA",Puntuacion!$G:$G,"<>NE"))) | V16: =IF(COUNTIFS(Puntuacion!$A:$A,$A16,Puntuacion!$C:$C,$C16,Puntuacion!$D:$D,"Adopcion",Puntuacion!$G:$G,"<>NA")>0,1,0) | W16: =IF(AND(V16=1,COUNTIFS(Puntuacion!$A:$A,$A16,Puntuacion!$C:$C,$C16,Puntuacion!$D:$D,"Adopcion",Puntuacion!$G:$G,"NE")=0),1,0) | X16: =IF(V16=0,"NA",IF(W16=0,"NE",AVERAGEIFS(Puntuacion!$G:$G,Puntuacion!$A:$A,$A16,Puntuacion!$C:$C,$C16,Puntuacion!$D:$D,"Adopcion",Puntuacion!$G:$G,"<>NA",Puntuacion!$G:$G,"<>NE"))) | Y16: =IF(COUNTIFS(Puntuacion!$A:$A,$A16,Puntuacion!$C:$C,$C16,Puntuacion!$D:$D,"Precio",Puntuacion!$G:$G,"<>NA")>0,1,0) | Z16: =IF(AND(Y16=1,COUNTIFS(Puntuacion!$A:$A,$A16,Puntuacion!$C:$C,$C16,Puntuacion!$D:$D,"Precio",Puntuacion!$G:$G,"NE")=0),1,0) | AA16: =IF(Y16=0,"NA",IF(Z16=0,"NE",AVERAGEIFS(Puntuacion!$G:$G,Puntuacion!$A:$A,$A16,Puntuacion!$C:$C,$C16,Puntuacion!$D:$D,"Precio",Puntuacion!$G:$G,"<>NA",Puntuacion!$G:$G,"<>NE"))) | AB16: =IF(COUNTIFS(Puntuacion!$A:$A,$A16,Puntuacion!$C:$C,$C16,Puntuacion!$D:$D,"Dependencia",Puntuacion!$G:$G,"<>NA")>0,1,0) | AC16: =IF(AND(AB16=1,COUNTIFS(Puntuacion!$A:$A,$A16,Puntuacion!$C:$C,$C16,Puntuacion!$D:$D,"Dependencia",Puntuacion!$G:$G,"NE")=0),1,0) | AD16: =IF(AB16=0,"NA",IF(AC16=0,"NE",AVERAGEIFS(Puntuacion!$G:$G,Puntuacion!$A:$A,$A16,Puntuacion!$C:$C,$C16,Puntuacion!$D:$D,"Dependencia",Puntuacion!$G:$G,"<>NA",Puntuacion!$G:$G,"<>NE"))) | AE16: =IFERROR(100*(E16*Pesos!$B$2+H16*Pesos!$B$3+K16*Pesos!$B$4+N16*Pesos!$B$5+Q16*Pesos!$B$6+T16*Pesos!$B$7+W16*Pesos!$B$8+Z16*Pesos!$B$9+AC16*Pesos!$B$10)/(D16*Pesos!$B$2+G16*Pesos!$B$3+J16*Pesos!$B$4+M16*Pesos!$B$5+P16*Pesos!$B$6+S16*Pesos!$B$7+V16*Pesos!$B$8+Y16*Pesos!$B$9+AB16*Pesos!$B$10),"Sin criterios aplicables") | AF16: =IFERROR(100*(E16*Pesos!$C$2+H16*Pesos!$C$3+K16*Pesos!$C$4+N16*Pesos!$C$5+Q16*Pesos!$C$6+T16*Pesos!$C$7+W16*Pesos!$C$8+Z16*Pesos!$C$9+AC16*Pesos!$C$10)/(D16*Pesos!$C$2+G16*Pesos!$C$3+J16*Pesos!$C$4+M16*Pesos!$C$5+P16*Pesos!$C$6+S16*Pesos!$C$7+V16*Pesos!$C$8+Y16*Pesos!$C$9+AB16*Pesos!$C$10),"Sin criterios aplicables") | AG16: =IF(OR(AE16="Sin criterios aplicables",AE16<70),"Insufficient evidence",100*(Pesos!$B$2*IF(E16=1,F16,0)+Pesos!$B$3*IF(H16=1,I16,0)+Pesos!$B$4*IF(K16=1,L16,0)+Pesos!$B$5*IF(N16=1,O16,0)+Pesos!$B$6*IF(Q16=1,R16,0)+Pesos!$B$7*IF(T16=1,U16,0)+Pesos!$B$8*IF(W16=1,X16,0)+Pesos!$B$9*IF(Z16=1,AA16,0)+Pesos!$B$10*IF(AC16=1,AD16,0))/(3*(Pesos!$B$2*E16+Pesos!$B$3*H16+Pesos!$B$4*K16+Pesos!$B$5*N16+Pesos!$B$6*Q16+Pesos!$B$7*T16+Pesos!$B$8*W16+Pesos!$B$9*Z16+Pesos!$B$10*AC16))) | AH16: =IF(OR(AF16="Sin criterios aplicables",AF16<70),"Insufficient evidence",100*(Pesos!$C$2*IF(E16=1,F16,0)+Pesos!$C$3*IF(H16=1,I16,0)+Pesos!$C$4*IF(K16=1,L16,0)+Pesos!$C$5*IF(N16=1,O16,0)+Pesos!$C$6*IF(Q16=1,R16,0)+Pesos!$C$7*IF(T16=1,U16,0)+Pesos!$C$8*IF(W16=1,X16,0)+Pesos!$C$9*IF(Z16=1,AA16,0)+Pesos!$C$10*IF(AC16=1,AD16,0))/(3*(Pesos!$C$2*E16+Pesos!$C$3*H16+Pesos!$C$4*K16+Pesos!$C$5*N16+Pesos!$C$6*Q16+Pesos!$C$7*T16+Pesos!$C$8*W16+Pesos!$C$9*Z16+Pesos!$C$10*AC16))) | AI16: =IF(AG16="Insufficient evidence","Insufficient evidence (cobertura<70%)",IF(AG16<50/3,"Insufficient",IF(AG16<50,"Basic",IF(AG16<250/3,"Solid","Advanced")))) | AJ16: =IF(AH16="Insufficient evidence","Insufficient evidence (cobertura<70%)",IF(AH16<50/3,"Insufficient",IF(AH16<50,"Basic",IF(AH16<250/3,"Solid","Advanced")))) | AK16: =IF(TRIM(IF(AND(ISNUMBER(R16),R16<1),"Multicloud","") & " " & IF(AND(ISNUMBER(AA16),AA16<1),"Precio",""))="","Ninguno",TRIM(IF(AND(ISNUMBER(R16),R16<1),"Multicloud","") & " " & IF(AND(ISNUMBER(AA16),AA16<1),"Precio","")))
A17: E2 | B17: Cloud nativa | C17: Google Cloud FinOps Hub | D17: =IF(COUNTIFS(Puntuacion!$A:$A,$A17,Puntuacion!$C:$C,$C17,Puntuacion!$D:$D,"Visibilidad",Puntuacion!$G:$G,"<>NA")>0,1,0) | E17: =IF(AND(D17=1,COUNTIFS(Puntuacion!$A:$A,$A17,Puntuacion!$C:$C,$C17,Puntuacion!$D:$D,"Visibilidad",Puntuacion!$G:$G,"NE")=0),1,0) | F17: =IF(D17=0,"NA",IF(E17=0,"NE",AVERAGEIFS(Puntuacion!$G:$G,Puntuacion!$A:$A,$A17,Puntuacion!$C:$C,$C17,Puntuacion!$D:$D,"Visibilidad",Puntuacion!$G:$G,"<>NA",Puntuacion!$G:$G,"<>NE"))) | G17: =IF(COUNTIFS(Puntuacion!$A:$A,$A17,Puntuacion!$C:$C,$C17,Puntuacion!$D:$D,"Asignacion",Puntuacion!$G:$G,"<>NA")>0,1,0) | H17: =IF(AND(G17=1,COUNTIFS(Puntuacion!$A:$A,$A17,Puntuacion!$C:$C,$C17,Puntuacion!$D:$D,"Asignacion",Puntuacion!$G:$G,"NE")=0),1,0) | I17: =IF(G17=0,"NA",IF(H17=0,"NE",AVERAGEIFS(Puntuacion!$G:$G,Puntuacion!$A:$A,$A17,Puntuacion!$C:$C,$C17,Puntuacion!$D:$D,"Asignacion",Puntuacion!$G:$G,"<>NA",Puntuacion!$G:$G,"<>NE"))) | J17: =IF(COUNTIFS(Puntuacion!$A:$A,$A17,Puntuacion!$C:$C,$C17,Puntuacion!$D:$D,"Optimizacion",Puntuacion!$G:$G,"<>NA")>0,1,0) | K17: =IF(AND(J17=1,COUNTIFS(Puntuacion!$A:$A,$A17,Puntuacion!$C:$C,$C17,Puntuacion!$D:$D,"Optimizacion",Puntuacion!$G:$G,"NE")=0),1,0) | L17: =IF(J17=0,"NA",IF(K17=0,"NE",AVERAGEIFS(Puntuacion!$G:$G,Puntuacion!$A:$A,$A17,Puntuacion!$C:$C,$C17,Puntuacion!$D:$D,"Optimizacion",Puntuacion!$G:$G,"<>NA",Puntuacion!$G:$G,"<>NE"))) | M17: =IF(COUNTIFS(Puntuacion!$A:$A,$A17,Puntuacion!$C:$C,$C17,Puntuacion!$D:$D,"Automatizacion",Puntuacion!$G:$G,"<>NA")>0,1,0) | N17: =IF(AND(M17=1,COUNTIFS(Puntuacion!$A:$A,$A17,Puntuacion!$C:$C,$C17,Puntuacion!$D:$D,"Automatizacion",Puntuacion!$G:$G,"NE")=0),1,0) | O17: =IF(M17=0,"NA",IF(N17=0,"NE",AVERAGEIFS(Puntuacion!$G:$G,Puntuacion!$A:$A,$A17,Puntuacion!$C:$C,$C17,Puntuacion!$D:$D,"Automatizacion",Puntuacion!$G:$G,"<>NA",Puntuacion!$G:$G,"<>NE"))) | P17: =IF(COUNTIFS(Puntuacion!$A:$A,$A17,Puntuacion!$C:$C,$C17,Puntuacion!$D:$D,"Multicloud",Puntuacion!$G:$G,"<>NA")>0,1,0) | Q17: =IF(AND(P17=1,COUNTIFS(Puntuacion!$A:$A,$A17,Puntuacion!$C:$C,$C17,Puntuacion!$D:$D,"Multicloud",Puntuacion!$G:$G,"NE")=0),1,0) | R17: =IF(P17=0,"NA",IF(Q17=0,"NE",AVERAGEIFS(Puntuacion!$G:$G,Puntuacion!$A:$A,$A17,Puntuacion!$C:$C,$C17,Puntuacion!$D:$D,"Multicloud",Puntuacion!$G:$G,"<>NA",Puntuacion!$G:$G,"<>NE"))) | S17: =IF(COUNTIFS(Puntuacion!$A:$A,$A17,Puntuacion!$C:$C,$C17,Puntuacion!$D:$D,"Integracion",Puntuacion!$G:$G,"<>NA")>0,1,0) | T17: =IF(AND(S17=1,COUNTIFS(Puntuacion!$A:$A,$A17,Puntuacion!$C:$C,$C17,Puntuacion!$D:$D,"Integracion",Puntuacion!$G:$G,"NE")=0),1,0) | U17: =IF(S17=0,"NA",IF(T17=0,"NE",AVERAGEIFS(Puntuacion!$G:$G,Puntuacion!$A:$A,$A17,Puntuacion!$C:$C,$C17,Puntuacion!$D:$D,"Integracion",Puntuacion!$G:$G,"<>NA",Puntuacion!$G:$G,"<>NE"))) | V17: =IF(COUNTIFS(Puntuacion!$A:$A,$A17,Puntuacion!$C:$C,$C17,Puntuacion!$D:$D,"Adopcion",Puntuacion!$G:$G,"<>NA")>0,1,0) | W17: =IF(AND(V17=1,COUNTIFS(Puntuacion!$A:$A,$A17,Puntuacion!$C:$C,$C17,Puntuacion!$D:$D,"Adopcion",Puntuacion!$G:$G,"NE")=0),1,0) | X17: =IF(V17=0,"NA",IF(W17=0,"NE",AVERAGEIFS(Puntuacion!$G:$G,Puntuacion!$A:$A,$A17,Puntuacion!$C:$C,$C17,Puntuacion!$D:$D,"Adopcion",Puntuacion!$G:$G,"<>NA",Puntuacion!$G:$G,"<>NE"))) | Y17: =IF(COUNTIFS(Puntuacion!$A:$A,$A17,Puntuacion!$C:$C,$C17,Puntuacion!$D:$D,"Precio",Puntuacion!$G:$G,"<>NA")>0,1,0) | Z17: =IF(AND(Y17=1,COUNTIFS(Puntuacion!$A:$A,$A17,Puntuacion!$C:$C,$C17,Puntuacion!$D:$D,"Precio",Puntuacion!$G:$G,"NE")=0),1,0) | AA17: =IF(Y17=0,"NA",IF(Z17=0,"NE",AVERAGEIFS(Puntuacion!$G:$G,Puntuacion!$A:$A,$A17,Puntuacion!$C:$C,$C17,Puntuacion!$D:$D,"Precio",Puntuacion!$G:$G,"<>NA",Puntuacion!$G:$G,"<>NE"))) | AB17: =IF(COUNTIFS(Puntuacion!$A:$A,$A17,Puntuacion!$C:$C,$C17,Puntuacion!$D:$D,"Dependencia",Puntuacion!$G:$G,"<>NA")>0,1,0) | AC17: =IF(AND(AB17=1,COUNTIFS(Puntuacion!$A:$A,$A17,Puntuacion!$C:$C,$C17,Puntuacion!$D:$D,"Dependencia",Puntuacion!$G:$G,"NE")=0),1,0) | AD17: =IF(AB17=0,"NA",IF(AC17=0,"NE",AVERAGEIFS(Puntuacion!$G:$G,Puntuacion!$A:$A,$A17,Puntuacion!$C:$C,$C17,Puntuacion!$D:$D,"Dependencia",Puntuacion!$G:$G,"<>NA",Puntuacion!$G:$G,"<>NE"))) | AE17: =IFERROR(100*(E17*Pesos!$B$2+H17*Pesos!$B$3+K17*Pesos!$B$4+N17*Pesos!$B$5+Q17*Pesos!$B$6+T17*Pesos!$B$7+W17*Pesos!$B$8+Z17*Pesos!$B$9+AC17*Pesos!$B$10)/(D17*Pesos!$B$2+G17*Pesos!$B$3+J17*Pesos!$B$4+M17*Pesos!$B$5+P17*Pesos!$B$6+S17*Pesos!$B$7+V17*Pesos!$B$8+Y17*Pesos!$B$9+AB17*Pesos!$B$10),"Sin criterios aplicables") | AF17: =IFERROR(100*(E17*Pesos!$C$2+H17*Pesos!$C$3+K17*Pesos!$C$4+N17*Pesos!$C$5+Q17*Pesos!$C$6+T17*Pesos!$C$7+W17*Pesos!$C$8+Z17*Pesos!$C$9+AC17*Pesos!$C$10)/(D17*Pesos!$C$2+G17*Pesos!$C$3+J17*Pesos!$C$4+M17*Pesos!$C$5+P17*Pesos!$C$6+S17*Pesos!$C$7+V17*Pesos!$C$8+Y17*Pesos!$C$9+AB17*Pesos!$C$10),"Sin criterios aplicables") | AG17: =IF(OR(AE17="Sin criterios aplicables",AE17<70),"Insufficient evidence",100*(Pesos!$B$2*IF(E17=1,F17,0)+Pesos!$B$3*IF(H17=1,I17,0)+Pesos!$B$4*IF(K17=1,L17,0)+Pesos!$B$5*IF(N17=1,O17,0)+Pesos!$B$6*IF(Q17=1,R17,0)+Pesos!$B$7*IF(T17=1,U17,0)+Pesos!$B$8*IF(W17=1,X17,0)+Pesos!$B$9*IF(Z17=1,AA17,0)+Pesos!$B$10*IF(AC17=1,AD17,0))/(3*(Pesos!$B$2*E17+Pesos!$B$3*H17+Pesos!$B$4*K17+Pesos!$B$5*N17+Pesos!$B$6*Q17+Pesos!$B$7*T17+Pesos!$B$8*W17+Pesos!$B$9*Z17+Pesos!$B$10*AC17))) | AH17: =IF(OR(AF17="Sin criterios aplicables",AF17<70),"Insufficient evidence",100*(Pesos!$C$2*IF(E17=1,F17,0)+Pesos!$C$3*IF(H17=1,I17,0)+Pesos!$C$4*IF(K17=1,L17,0)+Pesos!$C$5*IF(N17=1,O17,0)+Pesos!$C$6*IF(Q17=1,R17,0)+Pesos!$C$7*IF(T17=1,U17,0)+Pesos!$C$8*IF(W17=1,X17,0)+Pesos!$C$9*IF(Z17=1,AA17,0)+Pesos!$C$10*IF(AC17=1,AD17,0))/(3*(Pesos!$C$2*E17+Pesos!$C$3*H17+Pesos!$C$4*K17+Pesos!$C$5*N17+Pesos!$C$6*Q17+Pesos!$C$7*T17+Pesos!$C$8*W17+Pesos!$C$9*Z17+Pesos!$C$10*AC17))) | AI17: =IF(AG17="Insufficient evidence","Insufficient evidence (cobertura<70%)",IF(AG17<50/3,"Insufficient",IF(AG17<50,"Basic",IF(AG17<250/3,"Solid","Advanced")))) | AJ17: =IF(AH17="Insufficient evidence","Insufficient evidence (cobertura<70%)",IF(AH17<50/3,"Insufficient",IF(AH17<50,"Basic",IF(AH17<250/3,"Solid","Advanced")))) | AK17: =IF(TRIM(IF(AND(ISNUMBER(R17),R17<1),"Multicloud","") & " " & IF(AND(ISNUMBER(AA17),AA17<1),"Precio",""))="","Ninguno",TRIM(IF(AND(ISNUMBER(R17),R17<1),"Multicloud","") & " " & IF(AND(ISNUMBER(AA17),AA17<1),"Precio","")))
A18: E2 | B18: Multicloud | C18: CloudHealth | D18: =IF(COUNTIFS(Puntuacion!$A:$A,$A18,Puntuacion!$C:$C,$C18,Puntuacion!$D:$D,"Visibilidad",Puntuacion!$G:$G,"<>NA")>0,1,0) | E18: =IF(AND(D18=1,COUNTIFS(Puntuacion!$A:$A,$A18,Puntuacion!$C:$C,$C18,Puntuacion!$D:$D,"Visibilidad",Puntuacion!$G:$G,"NE")=0),1,0) | F18: =IF(D18=0,"NA",IF(E18=0,"NE",AVERAGEIFS(Puntuacion!$G:$G,Puntuacion!$A:$A,$A18,Puntuacion!$C:$C,$C18,Puntuacion!$D:$D,"Visibilidad",Puntuacion!$G:$G,"<>NA",Puntuacion!$G:$G,"<>NE"))) | G18: =IF(COUNTIFS(Puntuacion!$A:$A,$A18,Puntuacion!$C:$C,$C18,Puntuacion!$D:$D,"Asignacion",Puntuacion!$G:$G,"<>NA")>0,1,0) | H18: =IF(AND(G18=1,COUNTIFS(Puntuacion!$A:$A,$A18,Puntuacion!$C:$C,$C18,Puntuacion!$D:$D,"Asignacion",Puntuacion!$G:$G,"NE")=0),1,0) | I18: =IF(G18=0,"NA",IF(H18=0,"NE",AVERAGEIFS(Puntuacion!$G:$G,Puntuacion!$A:$A,$A18,Puntuacion!$C:$C,$C18,Puntuacion!$D:$D,"Asignacion",Puntuacion!$G:$G,"<>NA",Puntuacion!$G:$G,"<>NE"))) | J18: =IF(COUNTIFS(Puntuacion!$A:$A,$A18,Puntuacion!$C:$C,$C18,Puntuacion!$D:$D,"Optimizacion",Puntuacion!$G:$G,"<>NA")>0,1,0) | K18: =IF(AND(J18=1,COUNTIFS(Puntuacion!$A:$A,$A18,Puntuacion!$C:$C,$C18,Puntuacion!$D:$D,"Optimizacion",Puntuacion!$G:$G,"NE")=0),1,0) | L18: =IF(J18=0,"NA",IF(K18=0,"NE",AVERAGEIFS(Puntuacion!$G:$G,Puntuacion!$A:$A,$A18,Puntuacion!$C:$C,$C18,Puntuacion!$D:$D,"Optimizacion",Puntuacion!$G:$G,"<>NA",Puntuacion!$G:$G,"<>NE"))) | M18: =IF(COUNTIFS(Puntuacion!$A:$A,$A18,Puntuacion!$C:$C,$C18,Puntuacion!$D:$D,"Automatizacion",Puntuacion!$G:$G,"<>NA")>0,1,0) | N18: =IF(AND(M18=1,COUNTIFS(Puntuacion!$A:$A,$A18,Puntuacion!$C:$C,$C18,Puntuacion!$D:$D,"Automatizacion",Puntuacion!$G:$G,"NE")=0),1,0) | O18: =IF(M18=0,"NA",IF(N18=0,"NE",AVERAGEIFS(Puntuacion!$G:$G,Puntuacion!$A:$A,$A18,Puntuacion!$C:$C,$C18,Puntuacion!$D:$D,"Automatizacion",Puntuacion!$G:$G,"<>NA",Puntuacion!$G:$G,"<>NE"))) | P18: =IF(COUNTIFS(Puntuacion!$A:$A,$A18,Puntuacion!$C:$C,$C18,Puntuacion!$D:$D,"Multicloud",Puntuacion!$G:$G,"<>NA")>0,1,0) | Q18: =IF(AND(P18=1,COUNTIFS(Puntuacion!$A:$A,$A18,Puntuacion!$C:$C,$C18,Puntuacion!$D:$D,"Multicloud",Puntuacion!$G:$G,"NE")=0),1,0) | R18: =IF(P18=0,"NA",IF(Q18=0,"NE",AVERAGEIFS(Puntuacion!$G:$G,Puntuacion!$A:$A,$A18,Puntuacion!$C:$C,$C18,Puntuacion!$D:$D,"Multicloud",Puntuacion!$G:$G,"<>NA",Puntuacion!$G:$G,"<>NE"))) | S18: =IF(COUNTIFS(Puntuacion!$A:$A,$A18,Puntuacion!$C:$C,$C18,Puntuacion!$D:$D,"Integracion",Puntuacion!$G:$G,"<>NA")>0,1,0) | T18: =IF(AND(S18=1,COUNTIFS(Puntuacion!$A:$A,$A18,Puntuacion!$C:$C,$C18,Puntuacion!$D:$D,"Integracion",Puntuacion!$G:$G,"NE")=0),1,0) | U18: =IF(S18=0,"NA",IF(T18=0,"NE",AVERAGEIFS(Puntuacion!$G:$G,Puntuacion!$A:$A,$A18,Puntuacion!$C:$C,$C18,Puntuacion!$D:$D,"Integracion",Puntuacion!$G:$G,"<>NA",Puntuacion!$G:$G,"<>NE"))) | V18: =IF(COUNTIFS(Puntuacion!$A:$A,$A18,Puntuacion!$C:$C,$C18,Puntuacion!$D:$D,"Adopcion",Puntuacion!$G:$G,"<>NA")>0,1,0) | W18: =IF(AND(V18=1,COUNTIFS(Puntuacion!$A:$A,$A18,Puntuacion!$C:$C,$C18,Puntuacion!$D:$D,"Adopcion",Puntuacion!$G:$G,"NE")=0),1,0) | X18: =IF(V18=0,"NA",IF(W18=0,"NE",AVERAGEIFS(Puntuacion!$G:$G,Puntuacion!$A:$A,$A18,Puntuacion!$C:$C,$C18,Puntuacion!$D:$D,"Adopcion",Puntuacion!$G:$G,"<>NA",Puntuacion!$G:$G,"<>NE"))) | Y18: =IF(COUNTIFS(Puntuacion!$A:$A,$A18,Puntuacion!$C:$C,$C18,Puntuacion!$D:$D,"Precio",Puntuacion!$G:$G,"<>NA")>0,1,0) | Z18: =IF(AND(Y18=1,COUNTIFS(Puntuacion!$A:$A,$A18,Puntuacion!$C:$C,$C18,Puntuacion!$D:$D,"Precio",Puntuacion!$G:$G,"NE")=0),1,0) | AA18: =IF(Y18=0,"NA",IF(Z18=0,"NE",AVERAGEIFS(Puntuacion!$G:$G,Puntuacion!$A:$A,$A18,Puntuacion!$C:$C,$C18,Puntuacion!$D:$D,"Precio",Puntuacion!$G:$G,"<>NA",Puntuacion!$G:$G,"<>NE"))) | AB18: =IF(COUNTIFS(Puntuacion!$A:$A,$A18,Puntuacion!$C:$C,$C18,Puntuacion!$D:$D,"Dependencia",Puntuacion!$G:$G,"<>NA")>0,1,0) | AC18: =IF(AND(AB18=1,COUNTIFS(Puntuacion!$A:$A,$A18,Puntuacion!$C:$C,$C18,Puntuacion!$D:$D,"Dependencia",Puntuacion!$G:$G,"NE")=0),1,0) | AD18: =IF(AB18=0,"NA",IF(AC18=0,"NE",AVERAGEIFS(Puntuacion!$G:$G,Puntuacion!$A:$A,$A18,Puntuacion!$C:$C,$C18,Puntuacion!$D:$D,"Dependencia",Puntuacion!$G:$G,"<>NA",Puntuacion!$G:$G,"<>NE"))) | AE18: =IFERROR(100*(E18*Pesos!$B$2+H18*Pesos!$B$3+K18*Pesos!$B$4+N18*Pesos!$B$5+Q18*Pesos!$B$6+T18*Pesos!$B$7+W18*Pesos!$B$8+Z18*Pesos!$B$9+AC18*Pesos!$B$10)/(D18*Pesos!$B$2+G18*Pesos!$B$3+J18*Pesos!$B$4+M18*Pesos!$B$5+P18*Pesos!$B$6+S18*Pesos!$B$7+V18*Pesos!$B$8+Y18*Pesos!$B$9+AB18*Pesos!$B$10),"Sin criterios aplicables") | AF18: =IFERROR(100*(E18*Pesos!$C$2+H18*Pesos!$C$3+K18*Pesos!$C$4+N18*Pesos!$C$5+Q18*Pesos!$C$6+T18*Pesos!$C$7+W18*Pesos!$C$8+Z18*Pesos!$C$9+AC18*Pesos!$C$10)/(D18*Pesos!$C$2+G18*Pesos!$C$3+J18*Pesos!$C$4+M18*Pesos!$C$5+P18*Pesos!$C$6+S18*Pesos!$C$7+V18*Pesos!$C$8+Y18*Pesos!$C$9+AB18*Pesos!$C$10),"Sin criterios aplicables") | AG18: =IF(OR(AE18="Sin criterios aplicables",AE18<70),"Insufficient evidence",100*(Pesos!$B$2*IF(E18=1,F18,0)+Pesos!$B$3*IF(H18=1,I18,0)+Pesos!$B$4*IF(K18=1,L18,0)+Pesos!$B$5*IF(N18=1,O18,0)+Pesos!$B$6*IF(Q18=1,R18,0)+Pesos!$B$7*IF(T18=1,U18,0)+Pesos!$B$8*IF(W18=1,X18,0)+Pesos!$B$9*IF(Z18=1,AA18,0)+Pesos!$B$10*IF(AC18=1,AD18,0))/(3*(Pesos!$B$2*E18+Pesos!$B$3*H18+Pesos!$B$4*K18+Pesos!$B$5*N18+Pesos!$B$6*Q18+Pesos!$B$7*T18+Pesos!$B$8*W18+Pesos!$B$9*Z18+Pesos!$B$10*AC18))) | AH18: =IF(OR(AF18="Sin criterios aplicables",AF18<70),"Insufficient evidence",100*(Pesos!$C$2*IF(E18=1,F18,0)+Pesos!$C$3*IF(H18=1,I18,0)+Pesos!$C$4*IF(K18=1,L18,0)+Pesos!$C$5*IF(N18=1,O18,0)+Pesos!$C$6*IF(Q18=1,R18,0)+Pesos!$C$7*IF(T18=1,U18,0)+Pesos!$C$8*IF(W18=1,X18,0)+Pesos!$C$9*IF(Z18=1,AA18,0)+Pesos!$C$10*IF(AC18=1,AD18,0))/(3*(Pesos!$C$2*E18+Pesos!$C$3*H18+Pesos!$C$4*K18+Pesos!$C$5*N18+Pesos!$C$6*Q18+Pesos!$C$7*T18+Pesos!$C$8*W18+Pesos!$C$9*Z18+Pesos!$C$10*AC18))) | AI18: =IF(AG18="Insufficient evidence","Insufficient evidence (cobertura<70%)",IF(AG18<50/3,"Insufficient",IF(AG18<50,"Basic",IF(AG18<250/3,"Solid","Advanced")))) | AJ18: =IF(AH18="Insufficient evidence","Insufficient evidence (cobertura<70%)",IF(AH18<50/3,"Insufficient",IF(AH18<50,"Basic",IF(AH18<250/3,"Solid","Advanced")))) | AK18: =IF(TRIM(IF(AND(ISNUMBER(R18),R18<1),"Multicloud","") & " " & IF(AND(ISNUMBER(AA18),AA18<1),"Precio",""))="","Ninguno",TRIM(IF(AND(ISNUMBER(R18),R18<1),"Multicloud","") & " " & IF(AND(ISNUMBER(AA18),AA18<1),"Precio","")))
A19: E2 | B19: Multicloud | C19: CloudZero | D19: =IF(COUNTIFS(Puntuacion!$A:$A,$A19,Puntuacion!$C:$C,$C19,Puntuacion!$D:$D,"Visibilidad",Puntuacion!$G:$G,"<>NA")>0,1,0) | E19: =IF(AND(D19=1,COUNTIFS(Puntuacion!$A:$A,$A19,Puntuacion!$C:$C,$C19,Puntuacion!$D:$D,"Visibilidad",Puntuacion!$G:$G,"NE")=0),1,0) | F19: =IF(D19=0,"NA",IF(E19=0,"NE",AVERAGEIFS(Puntuacion!$G:$G,Puntuacion!$A:$A,$A19,Puntuacion!$C:$C,$C19,Puntuacion!$D:$D,"Visibilidad",Puntuacion!$G:$G,"<>NA",Puntuacion!$G:$G,"<>NE"))) | G19: =IF(COUNTIFS(Puntuacion!$A:$A,$A19,Puntuacion!$C:$C,$C19,Puntuacion!$D:$D,"Asignacion",Puntuacion!$G:$G,"<>NA")>0,1,0) | H19: =IF(AND(G19=1,COUNTIFS(Puntuacion!$A:$A,$A19,Puntuacion!$C:$C,$C19,Puntuacion!$D:$D,"Asignacion",Puntuacion!$G:$G,"NE")=0),1,0) | I19: =IF(G19=0,"NA",IF(H19=0,"NE",AVERAGEIFS(Puntuacion!$G:$G,Puntuacion!$A:$A,$A19,Puntuacion!$C:$C,$C19,Puntuacion!$D:$D,"Asignacion",Puntuacion!$G:$G,"<>NA",Puntuacion!$G:$G,"<>NE"))) | J19: =IF(COUNTIFS(Puntuacion!$A:$A,$A19,Puntuacion!$C:$C,$C19,Puntuacion!$D:$D,"Optimizacion",Puntuacion!$G:$G,"<>NA")>0,1,0) | K19: =IF(AND(J19=1,COUNTIFS(Puntuacion!$A:$A,$A19,Puntuacion!$C:$C,$C19,Puntuacion!$D:$D,"Optimizacion",Puntuacion!$G:$G,"NE")=0),1,0) | L19: =IF(J19=0,"NA",IF(K19=0,"NE",AVERAGEIFS(Puntuacion!$G:$G,Puntuacion!$A:$A,$A19,Puntuacion!$C:$C,$C19,Puntuacion!$D:$D,"Optimizacion",Puntuacion!$G:$G,"<>NA",Puntuacion!$G:$G,"<>NE"))) | M19: =IF(COUNTIFS(Puntuacion!$A:$A,$A19,Puntuacion!$C:$C,$C19,Puntuacion!$D:$D,"Automatizacion",Puntuacion!$G:$G,"<>NA")>0,1,0) | N19: =IF(AND(M19=1,COUNTIFS(Puntuacion!$A:$A,$A19,Puntuacion!$C:$C,$C19,Puntuacion!$D:$D,"Automatizacion",Puntuacion!$G:$G,"NE")=0),1,0) | O19: =IF(M19=0,"NA",IF(N19=0,"NE",AVERAGEIFS(Puntuacion!$G:$G,Puntuacion!$A:$A,$A19,Puntuacion!$C:$C,$C19,Puntuacion!$D:$D,"Automatizacion",Puntuacion!$G:$G,"<>NA",Puntuacion!$G:$G,"<>NE"))) | P19: =IF(COUNTIFS(Puntuacion!$A:$A,$A19,Puntuacion!$C:$C,$C19,Puntuacion!$D:$D,"Multicloud",Puntuacion!$G:$G,"<>NA")>0,1,0) | Q19: =IF(AND(P19=1,COUNTIFS(Puntuacion!$A:$A,$A19,Puntuacion!$C:$C,$C19,Puntuacion!$D:$D,"Multicloud",Puntuacion!$G:$G,"NE")=0),1,0) | R19: =IF(P19=0,"NA",IF(Q19=0,"NE",AVERAGEIFS(Puntuacion!$G:$G,Puntuacion!$A:$A,$A19,Puntuacion!$C:$C,$C19,Puntuacion!$D:$D,"Multicloud",Puntuacion!$G:$G,"<>NA",Puntuacion!$G:$G,"<>NE"))) | S19: =IF(COUNTIFS(Puntuacion!$A:$A,$A19,Puntuacion!$C:$C,$C19,Puntuacion!$D:$D,"Integracion",Puntuacion!$G:$G,"<>NA")>0,1,0) | T19: =IF(AND(S19=1,COUNTIFS(Puntuacion!$A:$A,$A19,Puntuacion!$C:$C,$C19,Puntuacion!$D:$D,"Integracion",Puntuacion!$G:$G,"NE")=0),1,0) | U19: =IF(S19=0,"NA",IF(T19=0,"NE",AVERAGEIFS(Puntuacion!$G:$G,Puntuacion!$A:$A,$A19,Puntuacion!$C:$C,$C19,Puntuacion!$D:$D,"Integracion",Puntuacion!$G:$G,"<>NA",Puntuacion!$G:$G,"<>NE"))) | V19: =IF(COUNTIFS(Puntuacion!$A:$A,$A19,Puntuacion!$C:$C,$C19,Puntuacion!$D:$D,"Adopcion",Puntuacion!$G:$G,"<>NA")>0,1,0) | W19: =IF(AND(V19=1,COUNTIFS(Puntuacion!$A:$A,$A19,Puntuacion!$C:$C,$C19,Puntuacion!$D:$D,"Adopcion",Puntuacion!$G:$G,"NE")=0),1,0) | X19: =IF(V19=0,"NA",IF(W19=0,"NE",AVERAGEIFS(Puntuacion!$G:$G,Puntuacion!$A:$A,$A19,Puntuacion!$C:$C,$C19,Puntuacion!$D:$D,"Adopcion",Puntuacion!$G:$G,"<>NA",Puntuacion!$G:$G,"<>NE"))) | Y19: =IF(COUNTIFS(Puntuacion!$A:$A,$A19,Puntuacion!$C:$C,$C19,Puntuacion!$D:$D,"Precio",Puntuacion!$G:$G,"<>NA")>0,1,0) | Z19: =IF(AND(Y19=1,COUNTIFS(Puntuacion!$A:$A,$A19,Puntuacion!$C:$C,$C19,Puntuacion!$D:$D,"Precio",Puntuacion!$G:$G,"NE")=0),1,0) | AA19: =IF(Y19=0,"NA",IF(Z19=0,"NE",AVERAGEIFS(Puntuacion!$G:$G,Puntuacion!$A:$A,$A19,Puntuacion!$C:$C,$C19,Puntuacion!$D:$D,"Precio",Puntuacion!$G:$G,"<>NA",Puntuacion!$G:$G,"<>NE"))) | AB19: =IF(COUNTIFS(Puntuacion!$A:$A,$A19,Puntuacion!$C:$C,$C19,Puntuacion!$D:$D,"Dependencia",Puntuacion!$G:$G,"<>NA")>0,1,0) | AC19: =IF(AND(AB19=1,COUNTIFS(Puntuacion!$A:$A,$A19,Puntuacion!$C:$C,$C19,Puntuacion!$D:$D,"Dependencia",Puntuacion!$G:$G,"NE")=0),1,0) | AD19: =IF(AB19=0,"NA",IF(AC19=0,"NE",AVERAGEIFS(Puntuacion!$G:$G,Puntuacion!$A:$A,$A19,Puntuacion!$C:$C,$C19,Puntuacion!$D:$D,"Dependencia",Puntuacion!$G:$G,"<>NA",Puntuacion!$G:$G,"<>NE"))) | AE19: =IFERROR(100*(E19*Pesos!$B$2+H19*Pesos!$B$3+K19*Pesos!$B$4+N19*Pesos!$B$5+Q19*Pesos!$B$6+T19*Pesos!$B$7+W19*Pesos!$B$8+Z19*Pesos!$B$9+AC19*Pesos!$B$10)/(D19*Pesos!$B$2+G19*Pesos!$B$3+J19*Pesos!$B$4+M19*Pesos!$B$5+P19*Pesos!$B$6+S19*Pesos!$B$7+V19*Pesos!$B$8+Y19*Pesos!$B$9+AB19*Pesos!$B$10),"Sin criterios aplicables") | AF19: =IFERROR(100*(E19*Pesos!$C$2+H19*Pesos!$C$3+K19*Pesos!$C$4+N19*Pesos!$C$5+Q19*Pesos!$C$6+T19*Pesos!$C$7+W19*Pesos!$C$8+Z19*Pesos!$C$9+AC19*Pesos!$C$10)/(D19*Pesos!$C$2+G19*Pesos!$C$3+J19*Pesos!$C$4+M19*Pesos!$C$5+P19*Pesos!$C$6+S19*Pesos!$C$7+V19*Pesos!$C$8+Y19*Pesos!$C$9+AB19*Pesos!$C$10),"Sin criterios aplicables") | AG19: =IF(OR(AE19="Sin criterios aplicables",AE19<70),"Insufficient evidence",100*(Pesos!$B$2*IF(E19=1,F19,0)+Pesos!$B$3*IF(H19=1,I19,0)+Pesos!$B$4*IF(K19=1,L19,0)+Pesos!$B$5*IF(N19=1,O19,0)+Pesos!$B$6*IF(Q19=1,R19,0)+Pesos!$B$7*IF(T19=1,U19,0)+Pesos!$B$8*IF(W19=1,X19,0)+Pesos!$B$9*IF(Z19=1,AA19,0)+Pesos!$B$10*IF(AC19=1,AD19,0))/(3*(Pesos!$B$2*E19+Pesos!$B$3*H19+Pesos!$B$4*K19+Pesos!$B$5*N19+Pesos!$B$6*Q19+Pesos!$B$7*T19+Pesos!$B$8*W19+Pesos!$B$9*Z19+Pesos!$B$10*AC19))) | AH19: =IF(OR(AF19="Sin criterios aplicables",AF19<70),"Insufficient evidence",100*(Pesos!$C$2*IF(E19=1,F19,0)+Pesos!$C$3*IF(H19=1,I19,0)+Pesos!$C$4*IF(K19=1,L19,0)+Pesos!$C$5*IF(N19=1,O19,0)+Pesos!$C$6*IF(Q19=1,R19,0)+Pesos!$C$7*IF(T19=1,U19,0)+Pesos!$C$8*IF(W19=1,X19,0)+Pesos!$C$9*IF(Z19=1,AA19,0)+Pesos!$C$10*IF(AC19=1,AD19,0))/(3*(Pesos!$C$2*E19+Pesos!$C$3*H19+Pesos!$C$4*K19+Pesos!$C$5*N19+Pesos!$C$6*Q19+Pesos!$C$7*T19+Pesos!$C$8*W19+Pesos!$C$9*Z19+Pesos!$C$10*AC19))) | AI19: =IF(AG19="Insufficient evidence","Insufficient evidence (cobertura<70%)",IF(AG19<50/3,"Insufficient",IF(AG19<50,"Basic",IF(AG19<250/3,"Solid","Advanced")))) | AJ19: =IF(AH19="Insufficient evidence","Insufficient evidence (cobertura<70%)",IF(AH19<50/3,"Insufficient",IF(AH19<50,"Basic",IF(AH19<250/3,"Solid","Advanced")))) | AK19: =IF(TRIM(IF(AND(ISNUMBER(R19),R19<1),"Multicloud","") & " " & IF(AND(ISNUMBER(AA19),AA19<1),"Precio",""))="","Ninguno",TRIM(IF(AND(ISNUMBER(R19),R19<1),"Multicloud","") & " " & IF(AND(ISNUMBER(AA19),AA19<1),"Precio","")))
A20: E2 | B20: Multicloud | C20: Cloudability | D20: =IF(COUNTIFS(Puntuacion!$A:$A,$A20,Puntuacion!$C:$C,$C20,Puntuacion!$D:$D,"Visibilidad",Puntuacion!$G:$G,"<>NA")>0,1,0) | E20: =IF(AND(D20=1,COUNTIFS(Puntuacion!$A:$A,$A20,Puntuacion!$C:$C,$C20,Puntuacion!$D:$D,"Visibilidad",Puntuacion!$G:$G,"NE")=0),1,0) | F20: =IF(D20=0,"NA",IF(E20=0,"NE",AVERAGEIFS(Puntuacion!$G:$G,Puntuacion!$A:$A,$A20,Puntuacion!$C:$C,$C20,Puntuacion!$D:$D,"Visibilidad",Puntuacion!$G:$G,"<>NA",Puntuacion!$G:$G,"<>NE"))) | G20: =IF(COUNTIFS(Puntuacion!$A:$A,$A20,Puntuacion!$C:$C,$C20,Puntuacion!$D:$D,"Asignacion",Puntuacion!$G:$G,"<>NA")>0,1,0) | H20: =IF(AND(G20=1,COUNTIFS(Puntuacion!$A:$A,$A20,Puntuacion!$C:$C,$C20,Puntuacion!$D:$D,"Asignacion",Puntuacion!$G:$G,"NE")=0),1,0) | I20: =IF(G20=0,"NA",IF(H20=0,"NE",AVERAGEIFS(Puntuacion!$G:$G,Puntuacion!$A:$A,$A20,Puntuacion!$C:$C,$C20,Puntuacion!$D:$D,"Asignacion",Puntuacion!$G:$G,"<>NA",Puntuacion!$G:$G,"<>NE"))) | J20: =IF(COUNTIFS(Puntuacion!$A:$A,$A20,Puntuacion!$C:$C,$C20,Puntuacion!$D:$D,"Optimizacion",Puntuacion!$G:$G,"<>NA")>0,1,0) | K20: =IF(AND(J20=1,COUNTIFS(Puntuacion!$A:$A,$A20,Puntuacion!$C:$C,$C20,Puntuacion!$D:$D,"Optimizacion",Puntuacion!$G:$G,"NE")=0),1,0) | L20: =IF(J20=0,"NA",IF(K20=0,"NE",AVERAGEIFS(Puntuacion!$G:$G,Puntuacion!$A:$A,$A20,Puntuacion!$C:$C,$C20,Puntuacion!$D:$D,"Optimizacion",Puntuacion!$G:$G,"<>NA",Puntuacion!$G:$G,"<>NE"))) | M20: =IF(COUNTIFS(Puntuacion!$A:$A,$A20,Puntuacion!$C:$C,$C20,Puntuacion!$D:$D,"Automatizacion",Puntuacion!$G:$G,"<>NA")>0,1,0) | N20: =IF(AND(M20=1,COUNTIFS(Puntuacion!$A:$A,$A20,Puntuacion!$C:$C,$C20,Puntuacion!$D:$D,"Automatizacion",Puntuacion!$G:$G,"NE")=0),1,0) | O20: =IF(M20=0,"NA",IF(N20=0,"NE",AVERAGEIFS(Puntuacion!$G:$G,Puntuacion!$A:$A,$A20,Puntuacion!$C:$C,$C20,Puntuacion!$D:$D,"Automatizacion",Puntuacion!$G:$G,"<>NA",Puntuacion!$G:$G,"<>NE"))) | P20: =IF(COUNTIFS(Puntuacion!$A:$A,$A20,Puntuacion!$C:$C,$C20,Puntuacion!$D:$D,"Multicloud",Puntuacion!$G:$G,"<>NA")>0,1,0) | Q20: =IF(AND(P20=1,COUNTIFS(Puntuacion!$A:$A,$A20,Puntuacion!$C:$C,$C20,Puntuacion!$D:$D,"Multicloud",Puntuacion!$G:$G,"NE")=0),1,0) | R20: =IF(P20=0,"NA",IF(Q20=0,"NE",AVERAGEIFS(Puntuacion!$G:$G,Puntuacion!$A:$A,$A20,Puntuacion!$C:$C,$C20,Puntuacion!$D:$D,"Multicloud",Puntuacion!$G:$G,"<>NA",Puntuacion!$G:$G,"<>NE"))) | S20: =IF(COUNTIFS(Puntuacion!$A:$A,$A20,Puntuacion!$C:$C,$C20,Puntuacion!$D:$D,"Integracion",Puntuacion!$G:$G,"<>NA")>0,1,0) | T20: =IF(AND(S20=1,COUNTIFS(Puntuacion!$A:$A,$A20,Puntuacion!$C:$C,$C20,Puntuacion!$D:$D,"Integracion",Puntuacion!$G:$G,"NE")=0),1,0) | U20: =IF(S20=0,"NA",IF(T20=0,"NE",AVERAGEIFS(Puntuacion!$G:$G,Puntuacion!$A:$A,$A20,Puntuacion!$C:$C,$C20,Puntuacion!$D:$D,"Integracion",Puntuacion!$G:$G,"<>NA",Puntuacion!$G:$G,"<>NE"))) | V20: =IF(COUNTIFS(Puntuacion!$A:$A,$A20,Puntuacion!$C:$C,$C20,Puntuacion!$D:$D,"Adopcion",Puntuacion!$G:$G,"<>NA")>0,1,0) | W20: =IF(AND(V20=1,COUNTIFS(Puntuacion!$A:$A,$A20,Puntuacion!$C:$C,$C20,Puntuacion!$D:$D,"Adopcion",Puntuacion!$G:$G,"NE")=0),1,0) | X20: =IF(V20=0,"NA",IF(W20=0,"NE",AVERAGEIFS(Puntuacion!$G:$G,Puntuacion!$A:$A,$A20,Puntuacion!$C:$C,$C20,Puntuacion!$D:$D,"Adopcion",Puntuacion!$G:$G,"<>NA",Puntuacion!$G:$G,"<>NE"))) | Y20: =IF(COUNTIFS(Puntuacion!$A:$A,$A20,Puntuacion!$C:$C,$C20,Puntuacion!$D:$D,"Precio",Puntuacion!$G:$G,"<>NA")>0,1,0) | Z20: =IF(AND(Y20=1,COUNTIFS(Puntuacion!$A:$A,$A20,Puntuacion!$C:$C,$C20,Puntuacion!$D:$D,"Precio",Puntuacion!$G:$G,"NE")=0),1,0) | AA20: =IF(Y20=0,"NA",IF(Z20=0,"NE",AVERAGEIFS(Puntuacion!$G:$G,Puntuacion!$A:$A,$A20,Puntuacion!$C:$C,$C20,Puntuacion!$D:$D,"Precio",Puntuacion!$G:$G,"<>NA",Puntuacion!$G:$G,"<>NE"))) | AB20: =IF(COUNTIFS(Puntuacion!$A:$A,$A20,Puntuacion!$C:$C,$C20,Puntuacion!$D:$D,"Dependencia",Puntuacion!$G:$G,"<>NA")>0,1,0) | AC20: =IF(AND(AB20=1,COUNTIFS(Puntuacion!$A:$A,$A20,Puntuacion!$C:$C,$C20,Puntuacion!$D:$D,"Dependencia",Puntuacion!$G:$G,"NE")=0),1,0) | AD20: =IF(AB20=0,"NA",IF(AC20=0,"NE",AVERAGEIFS(Puntuacion!$G:$G,Puntuacion!$A:$A,$A20,Puntuacion!$C:$C,$C20,Puntuacion!$D:$D,"Dependencia",Puntuacion!$G:$G,"<>NA",Puntuacion!$G:$G,"<>NE"))) | AE20: =IFERROR(100*(E20*Pesos!$B$2+H20*Pesos!$B$3+K20*Pesos!$B$4+N20*Pesos!$B$5+Q20*Pesos!$B$6+T20*Pesos!$B$7+W20*Pesos!$B$8+Z20*Pesos!$B$9+AC20*Pesos!$B$10)/(D20*Pesos!$B$2+G20*Pesos!$B$3+J20*Pesos!$B$4+M20*Pesos!$B$5+P20*Pesos!$B$6+S20*Pesos!$B$7+V20*Pesos!$B$8+Y20*Pesos!$B$9+AB20*Pesos!$B$10),"Sin criterios aplicables") | AF20: =IFERROR(100*(E20*Pesos!$C$2+H20*Pesos!$C$3+K20*Pesos!$C$4+N20*Pesos!$C$5+Q20*Pesos!$C$6+T20*Pesos!$C$7+W20*Pesos!$C$8+Z20*Pesos!$C$9+AC20*Pesos!$C$10)/(D20*Pesos!$C$2+G20*Pesos!$C$3+J20*Pesos!$C$4+M20*Pesos!$C$5+P20*Pesos!$C$6+S20*Pesos!$C$7+V20*Pesos!$C$8+Y20*Pesos!$C$9+AB20*Pesos!$C$10),"Sin criterios aplicables") | AG20: =IF(OR(AE20="Sin criterios aplicables",AE20<70),"Insufficient evidence",100*(Pesos!$B$2*IF(E20=1,F20,0)+Pesos!$B$3*IF(H20=1,I20,0)+Pesos!$B$4*IF(K20=1,L20,0)+Pesos!$B$5*IF(N20=1,O20,0)+Pesos!$B$6*IF(Q20=1,R20,0)+Pesos!$B$7*IF(T20=1,U20,0)+Pesos!$B$8*IF(W20=1,X20,0)+Pesos!$B$9*IF(Z20=1,AA20,0)+Pesos!$B$10*IF(AC20=1,AD20,0))/(3*(Pesos!$B$2*E20+Pesos!$B$3*H20+Pesos!$B$4*K20+Pesos!$B$5*N20+Pesos!$B$6*Q20+Pesos!$B$7*T20+Pesos!$B$8*W20+Pesos!$B$9*Z20+Pesos!$B$10*AC20))) | AH20: =IF(OR(AF20="Sin criterios aplicables",AF20<70),"Insufficient evidence",100*(Pesos!$C$2*IF(E20=1,F20,0)+Pesos!$C$3*IF(H20=1,I20,0)+Pesos!$C$4*IF(K20=1,L20,0)+Pesos!$C$5*IF(N20=1,O20,0)+Pesos!$C$6*IF(Q20=1,R20,0)+Pesos!$C$7*IF(T20=1,U20,0)+Pesos!$C$8*IF(W20=1,X20,0)+Pesos!$C$9*IF(Z20=1,AA20,0)+Pesos!$C$10*IF(AC20=1,AD20,0))/(3*(Pesos!$C$2*E20+Pesos!$C$3*H20+Pesos!$C$4*K20+Pesos!$C$5*N20+Pesos!$C$6*Q20+Pesos!$C$7*T20+Pesos!$C$8*W20+Pesos!$C$9*Z20+Pesos!$C$10*AC20))) | AI20: =IF(AG20="Insufficient evidence","Insufficient evidence (cobertura<70%)",IF(AG20<50/3,"Insufficient",IF(AG20<50,"Basic",IF(AG20<250/3,"Solid","Advanced")))) | AJ20: =IF(AH20="Insufficient evidence","Insufficient evidence (cobertura<70%)",IF(AH20<50/3,"Insufficient",IF(AH20<50,"Basic",IF(AH20<250/3,"Solid","Advanced")))) | AK20: =IF(TRIM(IF(AND(ISNUMBER(R20),R20<1),"Multicloud","") & " " & IF(AND(ISNUMBER(AA20),AA20<1),"Precio",""))="","Ninguno",TRIM(IF(AND(ISNUMBER(R20),R20<1),"Multicloud","") & " " & IF(AND(ISNUMBER(AA20),AA20<1),"Precio","")))
